Workbook

Sheet Sheet1
A1: Артикул | B1: Родительский артикул | C1: Артикул для отображения на сайте | D1: Название модификации (UA) | E1: Название (UA) | F1: Бренд | G1: Раздел | H1: Цена | I1: Старая цена | J1: Валюта | K1: Отображать | L1: Country_of_origin | M1: Наличие | N1: Дополнительные разделы | O1: Фото | P1: Галерея | Q1: Обзор 360 | R1: Алиас | S1: Ссылка | T1: Дата добавления | U1: HTML title (UA) | V1: META keywords (UA) | W1: META description (UA) | X1: h1 заголовок (UA) | Y1: Поставщик | Z1: Иконки | AA1: Скидка % | AB1: Популярность | AC1: Количество | AD1: Описание товара (UA) | AE1: Короткое описание (UA) | AF1: Цвет | AG1: Тип гарантии | AH1: Гарантийный срок, мес. | AI1: Дата и время окончания акции | AJ1: Текст акции (UA) | AK1: Описание для маркетплейсов (UA) | AL1: Выгружать на маркетплейсы | AM1: Состояние товара | AN1: Только для взрослых | AO1: Код УКТ ВЭД | AP1: Срок доставки предзаказа в днях | AQ1: «Оплата частями» ПриватБанка | AR1: «Покупка частями» от monobank | AS1: Код налоговой группы Вчасно.Каса | AT1: Уникальный код налога | AU1: Штрихкод | AV1: Код производителя товара (MPN) | AW1: На складе для Prom | AX1: Электронный товар | AY1: Аксессуары(товары)
A2: 2009140 | B2: 2009140 | C2: 2009140 | D2: Щітка силіконова для тварин Fiskars , 2/6, 19L (2009140) | E2: Щітка силіконова для тварин Fiskars , 2/6, 19L (2009140) | F2: Fiskars | G2: FISKARS/ Аксесуари для тварин | H2: 1199.00 | I2: 0.00 | J2: UAH | K2: Да | L2: =VLOOKUP(C2,Sheet1!$C:$L,10,0) -> China | M2: Немає в наявності | O2: https://fiskars-gratis.com.ua/content/images/3/shchitka-sylikonova-dlia-tvaryn-fiskars-2-6-19l-1816520-19949308723507_+ef08531431.jpg; https://fiskars-gratis.com.ua/content/images/3/shchitka-sylikonova-dlia-tvaryn-fiskars-2-6-19l-1816520-14896186801593_+11eb0c30f6.jpg; https://fiskars-gratis.com.ua/content/images/3/shchitka-sylikonova-dlia-tvaryn-fiskars-2-6-19l-1816520-41587634878457_+dbfc746b32.jpg | R2: shchitka-sylikonova-dlia-tvaryn-fiskars-2-6-19l-1816520 | S2: https://fiskars-gratis.com.ua/shchitka-sylikonova-dlia-tvaryn-fiskars-2-6-19l-1816520/ | T2: 2026-03-15 23:17:10 | X2: Щітка силіконова для тварин Fiskars , 2/6, 19L | AA2: 0 | AB2: 0 | AC2: 0 | AD2: <p data-end="320" data-start="0"><span style="font-size:18px;"><strong data-end="49" data-start="0">Щітка силіконова для тварин Fiskars (2009140)</strong> </span><span style="font-size:14px;">&mdash; ручний інструмент для догляду за шерстю домашніх тварин, призначений для очищення шерсті, збирання випалого волосся та м&rsquo;якого масажу шкіри під час щоденного грумінгу. Використовується для догляду за собаками, котами та іншими домашніми тваринами у побутових умовах.</span></p> <p data-end="547" data-start="322"><span style="font-size:18px;"><strong data-end="338" data-start="322">Призначення:</strong> </span><span style="font-size:14px;">підходить для регулярного очищення шерсті від пилу, бруду та відмерлого волосся. Може застосовуватися під час сухого чищення або під час миття тварини для рівномірного розподілу води та засобів для догляду.</span></p> <p data-end="816" data-start="549"><span style="font-size:18px;"><strong data-end="565" data-start="549">Конструкція:</strong> </span><span style="font-size:14px;">робоча поверхня оснащена гнучкими силіконовими зубцями, які м&rsquo;яко контактують зі шкірою тварини та допомагають відокремлювати випалу шерсть без надмірного натискання. Форма інструмента дозволяє контролювати рухи під час обробки різних ділянок тіла.</span></p> <p data-end="991" data-start="818"><span style="font-size:18px;"><strong data-end="832" data-start="818">Матеріали:</strong> </span><span style="font-size:14px;">робоча частина виготовлена з еластичного силікону, стійкого до вологи та регулярного очищення. Корпус адаптований для ручного використання під час грумінгу.</span></p> <p data-end="1154" data-is-last-node="" data-is-only-node="" data-start="993"><span style="font-size:18px;"><strong data-end="1009" data-start="993">Особливості:</strong> </span><span style="font-size:14px;">інструмент призначений для систематичного догляду за домашніми тваринами та використовується як частина базового набору аксесуарів для грумінгу.</span></p> | AE2: Щітка силіконова для тварин Fiskars — ручний інструмент для догляду за шерстю домашніх тварин, призначений для очищення шерсті, збирання випалого волосся та м’якого масажу шкіри під час щоденного грумінгу. Використовується для догляду за собаками, котами та іншими домашніми тваринами у побутових умовах. | AH2: 0 | AI2: 2026-03-15 23:16:04 | AN2: Нет | AO2: 9603909100 | AP2: 0 | AQ2: Выкл | AR2: Выкл | AU2: 0046561816520 | AW2: Нет | AX2: Нет
A3: 2009136 | B3: 2009136 | C3: 2009136 | D3: Засіб для розплутування/розплутувач для тварин Fiskars, 2/6, 19L (2009136) | E3: Засіб для розплутування/розплутувач для тварин Fiskars, 2/6, 19L (2009136) | F3: Fiskars | G3: FISKARS/ Аксесуари для тварин | H3: 1199.00 | I3: 0.00 | J3: UAH | K3: Да | L3: =VLOOKUP(C3,Sheet1!$C:$L,10,0) -> China | M3: Немає в наявності | O3: https://fiskars-gratis.com.ua/content/images/4/zasib-dlia-rozplutuvannia-rozplutuvach-dlia-tvaryn-fiskars-2-6-19l-1816506-29339940044536_+86d4a5677e.jpg; https://fiskars-gratis.com.ua/content/images/4/zasib-dlia-rozplutuvannia-rozplutuvach-dlia-tvaryn-fiskars-2-6-19l-1816506-34032061364411_+dd836bc0c0.jpg | R3: zasib-dlia-rozplutuvannia-rozplutuvach-dlia-tvaryn-fiskars-2-6-19l-1816506 | S3: https://fiskars-gratis.com.ua/zasib-dlia-rozplutuvannia-rozplutuvach-dlia-tvaryn-fiskars-2-6-19l-1816506/ | T3: 2026-03-15 23:27:42 | X3: Засіб для розплутування/розплутувач для тварин Fiskars, 2/6, 19L | AA3: 0 | AB3: 0 | AC3: 0 | AD3: <p data-end="280" data-start="0"><span style="font-size:18px;"><strong data-end="59" data-start="0">Засіб для розплутування шерсті тварин Fiskars (2009136)</strong> </span><span style="font-size:14px;">&mdash; ручний інструмент для догляду за шерстю домашніх тварин, призначений для розплутування ковтунів і розділення зваляної шерсті. Використовується під час регулярного грумінгу собак і котів із середньою та довгою шерстю.</span></p> <p data-end="525" data-start="282"><span style="font-size:18px;"><strong data-end="298" data-start="282">Призначення:</strong></span><span style="font-size:14px;"> підходить для усунення ковтунів, розділення злиплих пасом шерсті та підготовки шерсті до подальшого вичісування. Застосовується під час догляду за домашніми тваринами у побутових умовах або під час базових процедур грумінгу.</span></p> <p data-end="777" data-start="527"><span style="font-size:18px;"><strong data-end="543" data-start="527">Конструкція:</strong></span><span style="font-size:14px;"> робоча частина оснащена кількома зубцями, розташованими таким чином, щоб поступово розділяти зваляну шерсть і зменшувати натяг під час розплутування. Форма інструмента дозволяє обробляти ділянки з густою шерстю та локальні ковтуни.</span></p> <p data-end="930" data-start="779"><span style="font-size:18px;"><strong data-end="793" data-start="779">Матеріали:</strong></span><span style="font-size:14px;"> зубці виготовлені зі сталі, розрахованої на регулярний контакт із щільною шерстю. Руків&rsquo;я адаптоване для контрольованої ручної роботи.</span></p> <p data-end="1080" data-is-last-node="" data-is-only-node="" data-start="932"><span style="font-size:18px;"><strong data-end="948" data-start="932">Особливості:</strong> </span><span style="font-size:14px;">інструмент призначений для систематичного догляду за шерстю домашніх тварин і використовується як частина базового набору грумінгу.</span></p> | AE3: Засіб для розплутування шерсті тварин Fiskars — ручний інструмент для догляду за шерстю домашніх тварин, призначений для розплутування ковтунів і розділення зваляної шерсті. Використовується під час регулярного грумінгу собак і котів із середньою та довгою шерстю. | AH3: 0 | AI3: 2026-03-15 23:27:09 | AN3: Нет | AO3: 9615190000 | AP3: 0 | AQ3: Выкл | AR3: Выкл | AU3: 0046561816506 | AW3: Нет | AX3: Нет
A4: 2009138 | B4: 2009138 | C4: 2009138 | D4: Щітка дротяна для тварин Fiskars, 2/6, 19L (2009138) | E4: Щітка дротяна для тварин Fiskars, 2/6, 19L (2009138) | F4: Fiskars | G4: FISKARS/ Аксесуари для тварин | H4: 1199.00 | I4: 0.00 | J4: UAH | K4: Да | L4: =VLOOKUP(C4,Sheet1!$C:$L,10,0) -> China | M4: Немає в наявності | O4: https://fiskars-gratis.com.ua/content/images/6/shchitka-drotiana-dlia-tvaryn-fiskars-2-6-19l-1816513-52365508642650_+475fdecdea.jpg; https://fiskars-gratis.com.ua/content/images/6/shchitka-drotiana-dlia-tvaryn-fiskars-2-6-19l-1816513-15244716117334_+0ff4db14f1.jpg | R4: shchitka-drotiana-dlia-tvaryn-fiskars-2-6-19l-1816513 | S4: https://fiskars-gratis.com.ua/shchitka-drotiana-dlia-tvaryn-fiskars-2-6-19l-1816513/ | T4: 2026-03-15 23:30:06 | X4: Щітка дротяна для тварин Fiskars, 2/6, 19L | AA4: 0 | AB4: 0 | AC4: 0 | AD4: <p data-end="306" data-start="0"><span style="font-size:18px;"><strong data-end="46" data-start="0">Щітка дротяна для тварин Fiskars (2009138)</strong> </span><span style="font-size:14px;">&mdash; ручний інструмент для догляду за шерстю домашніх тварин, призначений для вичісування підшерстка та видалення випалої шерсті під час регулярного грумінгу. Використовується для очищення шерсті собак і котів від пилу, дрібних забруднень і відмерлого волосся.</span></p> <p data-end="492" data-start="308"><span style="font-size:18px;"><strong data-end="324" data-start="308">Призначення:</strong></span><span style="font-size:14px;"> підходить для догляду за шерстю середньої та довгої довжини, видалення підшерстка під час линяння, а також для підтримання охайного стану шерстяного покриву тварини.</span></p> <p data-end="744" data-start="494"><span style="font-size:18px;"><strong data-end="510" data-start="494">Конструкція:</strong></span><span style="font-size:14px;"> робоча поверхня оснащена тонкими дротяними зубцями, розташованими на гнучкій основі. Така конструкція дозволяє проникати у верхні шари шерсті, відокремлювати випалу шерсть і рівномірно розподіляти навантаження під час розчісування.</span></p> <p data-end="938" data-start="746"><span style="font-size:18px;"><strong data-end="760" data-start="746">Матеріали:</strong> </span><span style="font-size:14px;">зубці виготовлені з металевого дроту, розрахованого на регулярний контакт із шерстю. Основа та руків&rsquo;я адаптовані для контрольованої ручної роботи під час догляду за твариною.</span></p> <p data-end="1106" data-is-last-node="" data-is-only-node="" data-start="940"><span style="font-size:18px;"><strong data-end="956" data-start="940">Особливості:</strong> </span><span style="font-size:14px;">інструмент призначений для систематичного грумінгу домашніх тварин і використовується для підтримання чистоти та структури шерсті у побутових умовах.</span></p> | AE4: Щітка дротяна для тварин Fiskars — ручний інструмент для догляду за шерстю домашніх тварин, призначений для вичісування підшерстка та видалення випалої шерсті під час регулярного грумінгу. Використовується для очищення шерсті собак і котів від пилу, дрібних забруднень і відмерлого волосся. | AH4: 0 | AI4: 2026-03-15 23:29:03 | AN4: Нет | AO4: 9603909100 | AP4: 0 | AQ4: Выкл | AR4: Выкл | AU4: 0046561816513 | AW4: Нет | AX4: Нет
A5: 2009144 | B5: 2009144 | C5: 2009144 | D5: Сумка для зберігання інструментів для грумінгу FISKARS, 2/6, 19L (2009144) | E5: Сумка для зберігання інструментів для грумінгу FISKARS, 2/6, 19L (2009144) | F5: Fiskars | G5: FISKARS/ Аксесуари для тварин | H5: 1199.00 | I5: 0.00 | J5: UAH | K5: Да | L5: =VLOOKUP(C5,Sheet1!$C:$L,10,0) -> China | M5: Немає в наявності | O5: https://fiskars-gratis.com.ua/content/images/7/sumka-dlia-zberihannia-instrumentiv-dlia-hruminhu-fiskars-2-6-19l-1816544-55397096399844_+7974f3c32c.jpg; https://fiskars-gratis.com.ua/content/images/7/sumka-dlia-zberihannia-instrumentiv-dlia-hruminhu-fiskars-2-6-19l-1816544-47667126360409_+2662186932.jpg | R5: sumka-dlia-zberihannia-instrumentiv-dlia-hruminhu-fiskars-2-6-19l-1816544 | S5: https://fiskars-gratis.com.ua/sumka-dlia-zberihannia-instrumentiv-dlia-hruminhu-fiskars-2-6-19l-1816544/ | T5: 2026-03-15 23:30:29 | X5: Сумка для зберігання інструментів для грумінгу FISKARS, 2/6, 19L | AA5: 0 | AB5: 0 | AC5: 0 | AD5: <p data-end="311" data-start="0"><span style="font-size:18px;"><strong data-end="68" data-start="0">Сумка для зберігання інструментів для грумінгу Fiskars (2009144)</strong> </span><span style="font-size:14px;">&mdash; допоміжний аксесуар для організації та транспортування інструментів догляду за домашніми тваринами. Використовується для зберігання щіток, гребінців, розплутувачів шерсті та інших предметів, що застосовуються під час регулярного грумінгу.</span></p> <p data-end="582" data-start="313"><span style="font-size:18px;"><strong data-end="329" data-start="313">Призначення:</strong></span><span style="font-size:14px;"> підходить для систематичного зберігання інструментів догляду за шерстю собак і котів, упорядкування аксесуарів для грумінгу та їх переміщення між місцями використання. Може застосовуватися у побутових умовах або під час виїзного догляду за тваринами.</span></p> <p data-end="795" data-start="584"><span style="font-size:18px;"><strong data-end="600" data-start="584">Конструкція:</strong></span><span style="font-size:14px;"> сумка має містке основне відділення та внутрішній простір, адаптований для розміщення інструментів різного формату. Форма виробу дозволяє зручно складати та діставати аксесуари під час роботи.</span></p> <p data-end="977" data-start="797"><span style="font-size:18px;"><strong data-end="811" data-start="797">Матеріали:</strong></span><span style="font-size:14px;"> корпус виготовлений із зносостійкого текстильного матеріалу, розрахованого на регулярне використання. Ручки забезпечують зручне перенесення сумки разом із вмістом.</span></p> <p data-end="1180" data-is-last-node="" data-is-only-node="" data-start="979"><span style="font-size:18px;"><strong data-end="995" data-start="979">Особливості:</strong></span><span style="font-size:14px;"> об&rsquo;єм сумки становить приблизно 19 л. Аксесуар призначений для організованого зберігання інструментів грумінгу та використовується як частина набору для догляду за домашніми тваринами.</span></p> | AE5: Сумка для зберігання інструментів для грумінгу Fiskars — допоміжний аксесуар для організації та транспортування інструментів догляду за домашніми тваринами. Використовується для зберігання щіток, гребінців, розплутувачів шерсті та інших предметів, що застосовуються під час регулярного грумінгу. | AH5: 0 | AI5: 2026-03-15 23:30:09 | AN5: Нет | AO5: 4202229090 | AP5: 0 | AQ5: Выкл | AR5: Выкл | AU5: 0046561816544 | AW5: Нет | AX5: Нет
A6: 2009124 | B6: 2009124 | C6: 2009124 | D6: Ножиці для тварин з закругленими кінцями Fiskars, 2/6, 19L (2009124) | E6: Ножиці для тварин з закругленими кінцями Fiskars, 2/6, 19L (2009124) | F6: Fiskars | G6: FISKARS/ Аксесуари для тварин | H6: 1199.00 | I6: 0.00 | J6: UAH | K6: Да | L6: =VLOOKUP(C6,Sheet1!$C:$L,10,0) -> China | M6: Немає в наявності | O6: https://fiskars-gratis.com.ua/content/images/11/nozhytsi-dlia-tvaryn-z-zakruhlenymy-kintsiamy-fiskars-2-6-19l-1816445-83110909485205_+9d0ed96364.jpg; https://fiskars-gratis.com.ua/content/images/11/nozhytsi-dlia-tvaryn-z-zakruhlenymy-kintsiamy-fiskars-2-6-19l-1816445-87437518294057_+56b0e0016b.jpg | R6: nozhytsi-dlia-tvaryn-z-zakruhlenymy-kintsiamy-fiskars-2-6-19l-1816445 | S6: https://fiskars-gratis.com.ua/nozhytsi-dlia-tvaryn-z-zakruhlenymy-kintsiamy-fiskars-2-6-19l-1816445/ | T6: 2026-03-15 23:32:07 | X6: Ножиці для тварин з закругленими кінцями Fiskars, 2/6, 19L | AA6: 0 | AB6: 0 | AC6: 0 | AD6: <article data-scroll-anchor="true" data-testid="conversation-turn-24" data-turn="assistant" data-turn-id="request-69b34cbf-a33c-8331-8c2a-2d7e0ab1d4ae-8" dir="auto" tabindex="-1"> <p data-end="322" data-start="0"><span style="font-size:18px;"><strong data-end="63" data-start="0">Ножиці для тварин із закругленими кінцями Fiskars (2009124)</strong> </span><span style="font-size:14px;">&mdash; ручний інструмент для догляду за шерстю домашніх тварин, призначений для підстригання та корекції шерсті під час базових процедур грумінгу. Використовуються для акуратної обробки окремих ділянок шерстяного покриву у собак, котів та інших домашніх тварин.</span></p> <p data-end="537" data-start="324"><span style="font-size:18px;"><strong data-end="340" data-start="324">Призначення:</strong></span><span style="font-size:14px;"> підходять для підрівнювання шерсті, видалення зайвих пасом та обробки делікатних зон, зокрема навколо лап, морди або вух. Застосовуються під час регулярного догляду за шерстю у побутових умовах.</span></p> <p data-end="770" data-start="539"><span style="font-size:18px;"><strong data-end="555" data-start="539">Конструкція:</strong></span><span style="font-size:14px;"> ножиці оснащені лезами із закругленими кінцями, що зменшує ризик випадкового травмування шкіри під час роботи. Форма інструмента дозволяє виконувати точне підстригання та контролювати рухи під час обробки шерсті.</span></p> <p data-end="937" data-start="772"><span style="font-size:18px;"><strong data-end="786" data-start="772">Матеріали:</strong></span><span style="font-size:14px;"> леза виготовлені зі сталі, стійкої до регулярного використання. Руків&rsquo;я адаптовані для стабільного утримання інструмента та контрольованого різання.</span></p> <p data-end="1102" data-is-last-node="" data-is-only-node="" data-start="939"><span style="font-size:18px;"><strong data-end="955" data-start="939">Особливості:</strong></span><span style="font-size:14px;"> інструмент призначений для систематичного догляду за шерстю домашніх тварин і використовується як частина базового набору аксесуарів для грумінгу.</span></p> </article> | AE6: Ножиці для тварин із закругленими кінцями Fiskars — ручний інструмент для догляду за шерстю домашніх тварин, призначений для підстригання та корекції шерсті під час базових процедур грумінгу. Використовуються для акуратної обробки окремих ділянок шерстяного покриву у собак, котів та інших домашніх тварин. | AH6: 0 | AI6: 2026-03-15 23:31:47 | AN6: Нет | AO6: 8213000000 | AP6: 0 | AQ6: Выкл | AR6: Выкл | AU6: 0046561816445 | AW6: Нет | AX6: Нет
A7: 2009126 | B7: 2009126 | C7: 2009126 | D7: Ножиці прямі для тварин Fiskars, 2/6, 19L (2009126) | E7: Ножиці прямі для тварин Fiskars, 2/6, 19L (2009126) | F7: Fiskars | G7: FISKARS/ Аксесуари для тварин | H7: 1499.00 | I7: 0.00 | J7: UAH | K7: Да | L7: =VLOOKUP(C7,Sheet1!$C:$L,10,0) -> China | M7: Немає в наявності | O7: https://fiskars-gratis.com.ua/content/images/12/nozhytsi-priami-dlia-tvaryn-fiskars-2-6-19l-1816452-71856194063740_+b99da2d1ee.jpg; https://fiskars-gratis.com.ua/content/images/12/nozhytsi-priami-dlia-tvaryn-fiskars-2-6-19l-1816452-81481929345795_+48d5b18bc4.jpg | R7: nozhytsi-priami-dlia-tvaryn-fiskars-2-6-19l-1816452 | S7: https://fiskars-gratis.com.ua/nozhytsi-priami-dlia-tvaryn-fiskars-2-6-19l-1816452/ | T7: 2026-03-15 23:32:33 | X7: Ножиці прямі для тварин Fiskars, 2/6, 19L | AA7: 0 | AB7: 0 | AC7: 0 | AD7: <p data-end="290" data-start="0"><span style="font-size:18px;"><strong data-end="45" data-start="0">Ножиці прямі для тварин Fiskars (2009126)</strong></span><span style="font-size:14px;"> &mdash; ручний інструмент для догляду за шерстю домашніх тварин, призначений для підстригання та вирівнювання шерстяного покриву під час процедур грумінгу. Використовуються для обробки окремих ділянок шерсті у собак, котів та інших домашніх тварин.</span></p> <p data-end="500" data-start="292"><span style="font-size:18px;"><strong data-end="308" data-start="292">Призначення:</strong></span><span style="font-size:14px;"> підходять для підрівнювання шерсті, видалення зайвих пасом і корекції форми шерстяного покриву. Можуть застосовуватися під час регулярного догляду за шерстю на різних ділянках тіла тварини.</span></p> <p data-end="712" data-start="502"><span style="font-size:18px;"><strong data-end="518" data-start="502">Конструкція:</strong></span><span style="font-size:14px;"> інструмент оснащений прямими ріжучими лезами, що дозволяє виконувати рівні та контрольовані зрізи шерсті. Форма ножиць забезпечує точність під час роботи та зручність обробки окремих ділянок.</span></p> <p data-end="904" data-start="714"><span style="font-size:18px;"><strong data-end="728" data-start="714">Матеріали:</strong></span><span style="font-size:14px;"> леза виготовлені зі сталі, стійкої до регулярного використання під час підстригання шерсті. Руків&rsquo;я адаптовані для стабільного утримання інструмента та контрольованих рухів.</span></p> <p data-end="1069" data-is-last-node="" data-is-only-node="" data-start="906"><span style="font-size:18px;"><strong data-end="922" data-start="906">Особливості:</strong></span><span style="font-size:14px;"> інструмент призначений для систематичного догляду за шерстю домашніх тварин і використовується як частина базового набору аксесуарів для грумінгу.</span></p> | AE7: Ножиці прямі для тварин Fiskars — ручний інструмент для догляду за шерстю домашніх тварин, призначений для підстригання та вирівнювання шерстяного покриву під час процедур грумінгу. Використовуються для обробки окремих ділянок шерсті у собак, котів та інших домашніх тварин. | AH7: 0 | AI7: 2026-03-15 23:32:10 | AN7: Нет | AO7: 8213000000 | AP7: 0 | AQ7: Выкл | AR7: Выкл | AU7: 0046561816452 | AW7: Нет | AX7: Нет
A8: 2009128 | B8: 2009128 | C8: 2009128 | D8: Ножиці філірувальні (блендінг) для тварин (Fiskars), 2/6, 19L (2009128) | E8: Ножиці філірувальні (блендінг) для тварин (Fiskars), 2/6, 19L (2009128) | F8: Fiskars | G8: FISKARS/ Аксесуари для тварин | H8: 1499.00 | I8: 0.00 | J8: UAH | K8: Да | L8: =VLOOKUP(C8,Sheet1!$C:$L,10,0) -> China | M8: Немає в наявності | O8: https://fiskars-gratis.com.ua/content/images/13/nozhytsi-filiruvalni-blendinh-dlia-tvaryn-fiskars-2-6-19l-1816469-78361708951723_+5249067c85.jpg; https://fiskars-gratis.com.ua/content/images/13/nozhytsi-filiruvalni-blendinh-dlia-tvaryn-fiskars-2-6-19l-1816469-34108446666732_+04c64bf6b4.jpg | R8: nozhytsi-filiruvalni-blendinh-dlia-tvaryn-fiskars-2-6-19l-1816469 | S8: https://fiskars-gratis.com.ua/nozhytsi-filiruvalni-blendinh-dlia-tvaryn-fiskars-2-6-19l-1816469/ | T8: 2026-03-15 23:32:57 | X8: Ножиці філірувальні (блендінг) для тварин (Fiskars), 2/6, 19L | AA8: 0 | AB8: 0 | AC8: 0 | AD8: <p data-end="332" data-start="0"><span style="font-size:18px;"><strong data-end="63" data-start="0">Ножиці філірувальні (блендінг) для тварин Fiskars (2009128)</strong> </span><span style="font-size:14px;">&mdash; ручний інструмент для догляду за шерстю домашніх тварин, призначений для проріджування та плавного вирівнювання шерстяного покриву під час процедур грумінгу. Використовуються для обробки шерсті у собак, котів та інших домашніх тварин із середньою та довгою шерстю.</span></p> <p data-end="583" data-start="334"><span style="font-size:18px;"><strong data-end="350" data-start="334">Призначення:</strong></span><span style="font-size:14px;"> підходять для зменшення густоти шерсті, пом&rsquo;якшення ліній після підстригання та формування природного переходу між ділянками різної довжини. Застосовуються під час корекції форми шерстяного покриву та завершального етапу грумінгу.</span></p> <p data-end="803" data-start="585"><span style="font-size:18px;"><strong data-end="601" data-start="585">Конструкція:</strong></span><span style="font-size:14px;"> один із ріжучих елементів має зубчасту кромку, що дозволяє частково зрізати пасма шерсті під час кожного руху. Така конструкція забезпечує поступове проріджування та контрольований результат обробки.</span></p> <p data-end="1006" data-start="805"><span style="font-size:18px;"><strong data-end="819" data-start="805">Матеріали:</strong></span><span style="font-size:14px;"> леза виготовлені зі сталі, стійкої до регулярного використання під час підстригання шерсті. Руків&rsquo;я адаптовані для стабільного утримання інструмента та точного контролю під час роботи.</span></p> <p data-end="1173" data-is-last-node="" data-is-only-node="" data-start="1008"><span style="font-size:18px;"><strong data-end="1024" data-start="1008">Особливості:</strong> </span><span style="font-size:14px;">інструмент призначений для систематичного догляду за шерстю домашніх тварин і використовується як частина базового набору інструментів для грумінгу.</span></p> | AE8: Ножиці філірувальні (блендінг) для тварин Fiskars — ручний інструмент для догляду за шерстю домашніх тварин, призначений для проріджування та плавного вирівнювання шерстяного покриву під час процедур грумінгу. Використовуються для обробки шерсті у собак, котів та інших домашніх тварин із середньою та довгою шерстю. | AH8: 0 | AI8: 2026-03-15 23:32:41 | AN8: Нет | AO8: 8213000000 | AP8: 0 | AQ8: Выкл | AR8: Выкл | AU8: 0046561816469 | AW8: Нет | AX8: Нет
A9: 2009142 | B9: 2009142 | C9: 2009142 | D9: Пилка для нігтів для тварин Fiskars, 2/6, 19L (2009142) | E9: Пилка для нігтів для тварин Fiskars, 2/6, 19L (2009142) | F9: Fiskars | G9: FISKARS/ Аксесуари для тварин | H9: 779.00 | I9: 0.00 | J9: UAH | K9: Да | L9: =VLOOKUP(C9,Sheet1!$C:$L,10,0) -> China | M9: Немає в наявності | O9: https://fiskars-gratis.com.ua/content/images/10/pylka-dlia-nihtiv-dlia-tvaryn-fiskars-2-6-19l-1816537-56320074752080_+f28095bc32.jpg; https://fiskars-gratis.com.ua/content/images/10/pylka-dlia-nihtiv-dlia-tvaryn-fiskars-2-6-19l-1816537-92642854358221_+32aec2c9ea.jpg | P9: https://fiskars-gratis.com.ua/content/images/10/pylka-dlia-nihtiv-dlia-tvaryn-fiskars-2-6-19l-1816537-60009927375491_+40112f27b8.jpg; https://fiskars-gratis.com.ua/content/images/10/pylka-dlia-nihtiv-dlia-tvaryn-fiskars-2-6-19l-1816537-44574560488484_+a3fdfeca40.jpg | R9: pylka-dlia-nihtiv-dlia-tvaryn-fiskars-2-6-19l-1816537 | S9: https://fiskars-gratis.com.ua/pylka-dlia-nihtiv-dlia-tvaryn-fiskars-2-6-19l-1816537/ | T9: 2026-03-15 23:31:42 | X9: Пилка для нігтів для тварин Fiskars, 2/6, 19L | AA9: 0 | AB9: 0 | AC9: 0 | AD9: <p data-end="283" data-start="0"><span style="font-size:18px;"><strong data-end="49" data-start="0">Пилка для нігтів для тварин Fiskars (2009142)</strong> </span><span style="font-size:14px;">&mdash; ручний інструмент для догляду за кігтями домашніх тварин, призначений для підпилювання та згладжування країв кігтів після підстригання. Використовується під час регулярного догляду за лапами собак, котів та інших домашніх тварин.</span></p> <p data-end="504" data-start="285"><span style="font-size:18px;"><strong data-end="301" data-start="285">Призначення:</strong> </span><span style="font-size:14px;">підходить для корекції форми кігтів, усунення гострих країв після обрізання та підтримання їх безпечної довжини. Може застосовуватися як завершальний етап догляду за кігтями під час процедур грумінгу.</span></p> <p data-end="722" data-start="506"><span style="font-size:18px;"><strong data-end="522" data-start="506">Конструкція:</strong></span><span style="font-size:14px;"> інструмент має подовжену робочу поверхню з абразивним покриттям, що дозволяє поступово знімати верхній шар кігтя та вирівнювати його край. Форма пилки забезпечує контрольовані рухи під час обробки.</span></p> <p data-end="915" data-start="724"><span style="font-size:18px;"><strong data-end="738" data-start="724">Матеріали:</strong></span><span style="font-size:14px;"> робоча частина виготовлена з матеріалу з абразивним покриттям, стійким до регулярного використання. Руків&rsquo;я адаптоване для ручної роботи та стабільного утримання інструмента.</span></p> <p data-end="1081" data-is-last-node="" data-is-only-node="" data-start="917"><span style="font-size:18px;"><strong data-end="933" data-start="917">Особливості:</strong></span><span style="font-size:14px;"> інструмент призначений для систематичного догляду за кігтями домашніх тварин і використовується як частина базового набору аксесуарів для грумінгу.</span></p> | AE9: Пилка для нігтів для тварин Fiskars — ручний інструмент для догляду за кігтями домашніх тварин, призначений для підпилювання та згладжування країв кігтів після підстригання. Використовується під час регулярного догляду за лапами собак, котів та інших домашніх тварин. | AH9: 0 | AI9: 2026-03-15 23:31:27 | AN9: Нет | AO9: 8214200000 | AP9: 0 | AQ9: Выкл | AR9: Выкл | AU9: 0046561816537 | AW9: Нет | AX9: Нет
A10: 2009134 | B10: 2009134 | C10: 2009134 | D10: Гребінець сталевий для тварин Fiskars , 2/6, 19L (2009134) | E10: Гребінець сталевий для тварин Fiskars , 2/6, 19L (2009134) | F10: Fiskars | G10: FISKARS/ Аксесуари для тварин | H10: 899.00 | I10: 0.00 | J10: UAH | K10: Да | L10: =VLOOKUP(C10,Sheet1!$C:$L,10,0) -> China | M10: Немає в наявності | O10: https://fiskars-gratis.com.ua/content/images/5/hrebinets-stalevyi-dlia-tvaryn-fiskars-2-6-19l-1816490-25490070556696_+0b2f5fff30.jpg; https://fiskars-gratis.com.ua/content/images/5/hrebinets-stalevyi-dlia-tvaryn-fiskars-2-6-19l-1816490-11869273543600_+251a60aef9.jpg | R10: hrebinets-stalevyi-dlia-tvaryn-fiskars-2-6-19l-1816490 | S10: https://fiskars-gratis.com.ua/hrebinets-stalevyi-dlia-tvaryn-fiskars-2-6-19l-1816490/ | T10: 2026-03-15 23:28:53 | X10: Гребінець сталевий для тварин Fiskars , 2/6, 19L | AA10: 0 | AB10: 0 | AC10: 0 | AD10: <p data-end="303" data-start="0"><span style="font-size:18px;"><strong data-end="51" data-start="0">Гребінець сталевий для тварин Fiskars 2009134)</strong> </span><span style="font-size:14px;">&mdash; ручний інструмент для догляду за шерстю домашніх тварин, призначений для розчісування, видалення випалої шерсті та підтримання охайного стану шерстяного покриву. Використовується під час регулярного грумінгу собак і котів із різними типами шерсті.</span></p> <p data-end="557" data-start="305"><span style="font-size:18px;"><strong data-end="321" data-start="305">Призначення:</strong></span><span style="font-size:14px;"> підходить для щоденного розчісування, розділення пасом шерсті, видалення пилу та випалого підшерстка. Може застосовуватися для догляду за шерстю на різних ділянках тіла тварини та для підготовки шерсті до подальших процедур грумінгу.</span></p> <p data-end="787" data-start="559"><span style="font-size:18px;"><strong data-end="575" data-start="559">Конструкція:</strong></span><span style="font-size:14px;"> робоча частина оснащена рядом металевих зубців, розташованих на оптимальній відстані для рівномірного проходження крізь шерсть. Така форма дозволяє акуратно розділяти шерсть і контролювати процес розчісування.</span></p> <p data-end="981" data-start="789"><span style="font-size:18px;"><strong data-end="803" data-start="789">Матеріали:</strong></span><span style="font-size:14px;"> зубці виготовлені зі сталі, стійкої до регулярного використання та контакту з шерстю. Руків&rsquo;я адаптоване для ручної роботи та стабільного контролю під час догляду за твариною.</span></p> <p data-end="1116" data-is-last-node="" data-is-only-node="" data-start="983"><span style="font-size:18px;"><strong data-end="999" data-start="983">Особливості:</strong></span><span style="font-size:14px;"> інструмент призначений для систематичного використання під час базового грумінгу домашніх тварин у побутових умовах.</span></p> | AH10: 0 | AI10: 2026-03-15 23:28:30 | AN10: Нет | AO10: 9615190000 | AP10: 0 | AQ10: Выкл | AR10: Выкл | AU10: 0046561816490 | AW10: Нет | AX10: Нет
A11: 2009130 | B11: 2009130 | C11: 2009130 | D11: Кусачки для кігтів тварин Fiskars, 2/6, 19L (2009130) | E11: Кусачки для кігтів тварин Fiskars, 2/6, 19L (2009130) | F11: Fiskars | G11: FISKARS/ Аксесуари для тварин | H11: 899.00 | I11: 0.00 | J11: UAH | K11: Да | L11: =VLOOKUP(C11,Sheet1!$C:$L,10,0) -> China | M11: Немає в наявності | O11: https://fiskars-gratis.com.ua/content/images/9/kusachky-dlia-kihtiv-tvaryn-fiskars-2-6-19l-1816476-86760677284993_+4c79a29113.jpg; https://fiskars-gratis.com.ua/content/images/9/kusachky-dlia-kihtiv-tvaryn-fiskars-2-6-19l-1816476-98965090991984_+e21c68fefc.jpg | R11: kusachky-dlia-kihtiv-tvaryn-fiskars-2-6-19l-1816476 | S11: https://fiskars-gratis.com.ua/kusachky-dlia-kihtiv-tvaryn-fiskars-2-6-19l-1816476/ | T11: 2026-03-15 23:31:16 | X11: Кусачки для кігтів тварин Fiskars, 2/6, 19L | AA11: 0 | AB11: 0 | AC11: 0 | AD11: <article data-scroll-anchor="false" data-testid="conversation-turn-19" data-turn="user" data-turn-id="4a6859b5-372f-4ff1-9c57-2b6de5d35b36" dir="auto" tabindex="-1"><span style="font-size: 18px;"><strong data-end="47" data-start="0">Кусачки для кігтів тварин Fiskars (2009130)</strong> </span><span style="font-size: 14px;">&mdash; ручний інструмент для підстригання кігтів у домашніх тварин під час регулярного догляду. Використовуються для акуратного вкорочення кігтів у собак, котів та інших домашніх тварин у побутових умовах або під час базових процедур грумінгу.</span></article> <article data-scroll-anchor="true" data-testid="conversation-turn-20" data-turn="assistant" data-turn-id="request-69b34cbf-a33c-8331-8c2a-2d7e0ab1d4ae-6" dir="auto" tabindex="-1"> <p data-end="493" data-start="290"><span style="font-size:18px;"><strong data-end="306" data-start="290">Призначення:</strong></span><span style="font-size:14px;"> підходять для підтримання оптимальної довжини кігтів, запобігання їх надмірному відростанню та дискомфорту під час руху тварини. Застосовуються у процесі регулярного догляду за лапами.</span></p> <p data-end="739" data-start="495"><span style="font-size:18px;"><strong data-end="511" data-start="495">Конструкція:</strong> </span><span style="font-size:14px;">інструмент оснащений ріжучим механізмом кусачкового типу, що забезпечує контрольоване стискання лез під час обрізання кігтя. Форма ріжучої частини дозволяє точно позиціонувати інструмент і виконувати обрізання окремих кігтів.</span></p> <p data-end="950" data-start="741"><span style="font-size:18px;"><strong data-end="755" data-start="741">Матеріали:</strong></span><span style="font-size:14px;"> леза виготовлені зі сталі, стійкої до регулярного використання та механічних навантажень. Руків&rsquo;я адаптовані для стабільного утримання інструмента та контрольованого натискання під час роботи.</span></p> <p data-end="1115" data-is-last-node="" data-is-only-node="" data-start="952"><span style="font-size:18px;"><strong data-end="968" data-start="952">Особливості:</strong></span><span style="font-size:14px;"> інструмент призначений для систематичного догляду за домашніми тваринами та використовується як частина базового набору інструментів для грумінгу.</span></p> </article> | AE11: Кусачки для кігтів тварин Fiskars— ручний інструмент для підстригання кігтів у домашніх тварин під час регулярного догляду. Використовуються для акуратного вкорочення кігтів у собак, котів та інших домашніх тварин у побутових умовах або під час базових процедур грумінгу. | AH11: 0 | AI11: 2026-03-15 23:31:05 | AN11: Нет | AO11: 8214200000 | AP11: 0 | AQ11: Выкл | AR11: Выкл | AU11: 0046561816476 | AW11: Нет | AX11: Нет
A12: 2009132 | B12: 2009132 | C12: 2009132 | D12: Кусачки великі для кігтів тварин Fiskars , 2/6, 19L (2009132) | E12: Кусачки великі для кігтів тварин Fiskars , 2/6, 19L (2009132) | F12: Fiskars | G12: FISKARS/ Аксесуари для тварин | H12: 999.00 | I12: 0.00 | J12: UAH | K12: Да | L12: =VLOOKUP(C12,Sheet1!$C:$L,10,0) -> China | M12: Немає в наявності | O12: https://fiskars-gratis.com.ua/content/images/8/kusachky-velyki-dlia-kihtiv-tvaryn-fiskars-2-6-19l-1816483-21980176405223_+61b33ae7cd.jpg; https://fiskars-gratis.com.ua/content/images/8/kusachky-velyki-dlia-kihtiv-tvaryn-fiskars-2-6-19l-1816483-11302373923839_+51e6451da7.jpg | R12: kusachky-velyki-dlia-kihtiv-tvaryn-fiskars-2-6-19l-1816483 | S12: https://fiskars-gratis.com.ua/kusachky-velyki-dlia-kihtiv-tvaryn-fiskars-2-6-19l-1816483/ | T12: 2026-03-15 23:30:54 | X12: Кусачки великі для кігтів тварин Fiskars , 2/6, 19L | AA12: 0 | AB12: 0 | AC12: 0 | AD12: <article data-scroll-anchor="false" data-testid="conversation-turn-17" data-turn="user" data-turn-id="3f36e1f7-214d-4254-b13f-8799e9026099" dir="auto" tabindex="-1">&nbsp;</article> <article data-scroll-anchor="true" data-testid="conversation-turn-18" data-turn="assistant" data-turn-id="request-69b34cbf-a33c-8331-8c2a-2d7e0ab1d4ae-5" dir="auto" tabindex="-1"> <p data-end="295" data-start="0"><span style="font-size:18px;"><strong data-end="54" data-start="0">Кусачки великі для кігтів тварин Fiskars (2009132)</strong> </span><span style="font-size:14px;">&mdash; ручний інструмент для підстригання кігтів у домашніх тварин під час регулярного догляду. Використовуються для акуратного вкорочення кігтів у собак, котів та інших домашніх тварин у побутових умовах або під час базових процедур грумінгу.</span></p> <p data-end="523" data-start="297"><span style="font-size:18px;"><strong data-end="313" data-start="297">Призначення:</strong></span><span style="font-size:14px;"> підходять для підстригання відрослих кігтів, підтримання їх оптимальної довжини та запобігання надмірному стиранню або деформації під час руху тварини. Застосовуються у процесі регулярного догляду за лапами.</span></p> <p data-end="746" data-start="525"><span style="font-size:18px;"><strong data-end="541" data-start="525">Конструкція:</strong></span><span style="font-size:14px;"> інструмент оснащений ріжучим механізмом кусачкового типу, що забезпечує контрольоване стискання лез під час обрізання кігтя. Форма ріжучої частини дозволяє точно позиціонувати інструмент під час роботи.</span></p> <p data-end="931" data-start="748"><span style="font-size:18px;"><strong data-end="762" data-start="748">Матеріали:</strong> </span><span style="font-size:14px;">леза виготовлені зі сталі, стійкої до регулярного використання. Руків&rsquo;я адаптовані для стабільного утримання інструмента та контрольованого зусилля під час обрізання.</span></p> <p data-end="1094" data-is-last-node="" data-is-only-node="" data-start="933"><span style="font-size:18px;"><strong data-end="949" data-start="933">Особливості:</strong></span><span style="font-size:14px;"> інструмент призначений для систематичного догляду за домашніми тваринами та використовується як частина базового набору аксесуарів для грумінгу.</span></p> </article> | AE12: Кусачки великі для кігтів тварин Fiskars— ручний інструмент для підстригання кігтів у домашніх тварин під час регулярного догляду. Використовуються для акуратного вкорочення кігтів у собак, котів та інших домашніх тварин у побутових умовах або під час базових процедур грумінгу. | AH12: 0 | AI12: 2026-03-15 23:30:40 | AN12: Нет | AO12: 8214200000 | AP12: 0 | AQ12: Выкл | AR12: Выкл | AU12: 0046561816483 | AW12: Нет | AX12: Нет
A13: 1019354 | B13: 1019354 | C13: 1019354 | D13: Скребок автомобільний Fiskars Solid (1019354) | E13: Скребок автомобільний Fiskars Solid (1019354) | F13: Fiskars | G13: FISKARS/Автоаксесуари Fiskars/Щітки та скрібки для авто | H13: 319.00 | I13: 0.00 | J13: UAH | K13: Да | L13: =VLOOKUP(C13,Sheet1!$C:$L,10,0) -> China | M13: В наявності | N13: FISKARS/Автоаксесуари Fiskars | O13: https://fiskars-gratis.com.ua/content/images/31/skrebok-avtomobilnyi-fiskars-solid-1019354-46861657243390_+d1c2ae8995.jpg; https://fiskars-gratis.com.ua/content/images/31/skrebok-avtomobilnyi-fiskars-solid-1019354-82231664622799_+61bc64ffe5.jpg; https://fiskars-gratis.com.ua/content/images/31/skrebok-avtomobilnyi-fiskars-solid-1019354-67176702943325_+7b3f0ff99f.jpg; https://fiskars-gratis.com.ua/content/images/31/skrebok-avtomobilnyi-fiskars-solid-1019354-16081562994669_+d6a00c0495.jpg | R13: skrebok-avtomobilnyi-fiskars-solid-1019354 | S13: https://fiskars-gratis.com.ua/skrebok-avtomobilnyi-fiskars-solid-1019354/ | T13: 2026-02-22 01:06:29 | X13: Скребок автомобільний Fiskars Solid | AA13: 0 | AB13: 0 | AC13: 24 | AD13: <p data-end="311" data-start="0"><span style="font-size:18px;"><strong data-end="49" data-start="0">Скребок автомобільний Fiskars Solid (1019354)</strong> </span><span style="font-size:14px;">&mdash; ручний зимовий інструмент для очищення автомобільних стекол і зовнішніх поверхонь від льоду, намерзлого снігу та криги. Використовується для зняття льоду з лобового, бокових і заднього скла, а також дзеркал та інших зовнішніх деталей автомобіля перед виїздом.</span></p> <p data-end="543" data-start="313"><span style="font-size:18px;"><strong data-end="329" data-start="313">Призначення:</strong></span><span style="font-size:14px;"> підходить для очищення автомобільних вікон і дзеркал у зимовий період, коли на поверхні утворюється льодовий наліт; застосовується для швидкого видалення льоду без застосування аерозолів чи інших хімічних засобів.</span></p> <p data-end="786" data-start="545"><span style="font-size:18px;"><strong data-end="561" data-start="545">Конструкція:</strong></span><span style="font-size:14px;"> робоча частина оснащена твердою кромкою або щіточним елементом для зчищення льоду зі скла. Ергономічна рукоять забезпечує надійний захват та контроль під час чищення, зменшуючи навантаження на руку і підвищуючи ефективність.</span></p> <p data-end="1008" data-start="788"><span style="font-size:18px;"><strong data-end="802" data-start="788">Матеріали:</strong> </span><span style="font-size:14px;">скребок виготовлений із міцного пластику або композитного матеріалу, стійкого до низьких температур і механічних навантажень. Рукоять адаптована для комфортного використання в холодних умовах без ковзання.</span></p> <p data-end="1206" data-start="1010"><span style="font-size:18px;"><strong data-end="1026" data-start="1010">Особливості:</strong></span><span style="font-size:14px;"> інструмент належить до серії Solid бренду Fiskars та призначений для регулярного очищення автомобільних поверхонь від льоду й снігу в зимовий період.</span></p> | AE13: Скребок автомобільний Fiskars Solid — ручний зимовий інструмент для очищення автомобільних стекол і зовнішніх поверхонь від льоду, намерзлого снігу та криги. | AH13: 0 | AI13: 2026-02-22 23:14:10 | AM13: Новий | AN13: Нет | AO13: 9603909900 | AP13: 0 | AQ13: Выкл | AR13: Выкл | AU13: 6411501430632 | AW13: Нет | AX13: Нет
A14: 1078497 | B14: 1078497 | C14: 1078497 | D14: Скребок для льоду Fiskars Solid (1078497) | E14: Скребок для льоду Fiskars Solid (1078497) | F14: Fiskars | G14: FISKARS/Автоаксесуари Fiskars/Щітки та скрібки для авто | H14: 729.00 | I14: 0.00 | J14: UAH | K14: Да | L14: =VLOOKUP(C14,Sheet1!$C:$L,10,0) -> China | M14: В наявності | N14: FISKARS/Автоаксесуари Fiskars | O14: https://fiskars-gratis.com.ua/content/images/30/skrebok-dlia-lodu-fiskars-solid-1078497-69704877253493_+68d07e6800.jpg; https://fiskars-gratis.com.ua/content/images/30/skrebok-dlia-lodu-fiskars-solid-1078497-58463316290665_+765853dd9e.jpg; https://fiskars-gratis.com.ua/content/images/30/skrebok-dlia-lodu-fiskars-solid-1078497-79477715670594_+1c3f69b42b.jpg; https://fiskars-gratis.com.ua/content/images/30/skrebok-dlia-lodu-fiskars-solid-1078497-21271282967417_+1277b3a838.jpg | R14: skrebok-dlia-lodu-fiskars-solid-1078497 | S14: https://fiskars-gratis.com.ua/skrebok-dlia-lodu-fiskars-solid-1078497/ | T14: 2026-02-22 01:06:28 | X14: Скребок для льоду Fiskars Solid | AA14: 0 | AB14: 0 | AC14: 24 | AD14: <p data-end="304" data-start="0"><span style="font-size:18px;"><strong data-end="45" data-start="0">Скребок для льоду Fiskars Solid (1078497)</strong></span><span style="font-size:14px;"> &mdash; ручний зимовий інструмент для видалення льоду та намерзлого снігу з різних поверхонь. Використовується для очищення скла автомобіля, стекол, дзеркал, вітрових стекол, а також твердих горизонтальних поверхонь, де утворюється тонкий або середній шар льоду.</span></p> <p data-end="514" data-start="306"><span style="font-size:18px;"><strong data-end="322" data-start="306">Призначення:</strong></span><span style="font-size:14px;"> підходить для очищення автомобільних стекол і дзеркал, дверних прорізів, терас, сходинок і інших відкритих поверхонь, де потрібно ефективно усунути льодові утворення без пошкодження основи.</span></p> <p data-end="754" data-start="516"><span style="font-size:18px;"><strong data-end="532" data-start="516">Конструкція:</strong> </span><span style="font-size:14px;">оснащений твердою ріжучою кромкою, що дозволяє зчищати лід із поверхні шляхом легкого натискання та переміщення вздовж. Ергономічна рукоять адаптована для комфортного захвату й контролю під час роботи в холодних умовах.</span></p> <p data-end="1006" data-start="756"><span style="font-size:18px;"><strong data-end="770" data-start="756">Матеріали:</strong></span><span style="font-size:14px;"> робочий елемент виготовлений із міцного пластику або композитного матеріалу, стійкого до механічного навантаження й впливу низьких температур. Рукоять виконана з міцного матеріалу, що забезпечує надійний захват під час чищення льоду.</span></p> <p data-end="1201" data-start="1008"><span style="font-size:18px;"><strong data-end="1024" data-start="1008">Особливості:</strong></span><span style="font-size:14px;"> скребок належить до серії Solid бренду Fiskars та призначений для ефективного видалення льоду з поверхонь без застосування важких фізичних зусиль.</span></p> | AE14: Скребок для льоду Fiskars Solid — ручний зимовий інструмент для видалення льоду та намерзлого снігу з різних поверхонь. | AH14: 0 | AI14: 2026-02-22 23:13:01 | AM14: Новий | AN14: Нет | AO14: 3926909790 | AP14: 0 | AQ14: Выкл | AR14: Выкл | AU14: 6411501410573 | AW14: Нет | AX14: Нет
A15: 1082341 | B15: 1082341 | C15: 1082341 | D15: Акумулятор Fiskars 12V-4Ah (1082341) | E15: Акумулятор Fiskars 12V-4Ah (1082341) | F15: Fiskars | G15: FISKARS/Акумуляторний інструмент | H15: 4199.00 | I15: 5999.00 | J15: UAH | K15: Да | L15: =VLOOKUP(C15,Sheet1!$C:$L,10,0) -> China | M15: Немає в наявності | O15: https://fiskars-gratis.com.ua/content/images/15/akumuliator-fiskars-12v-4ah-1082341-65541202309766_+64755191c4.jpg | R15: akumuliator-fiskars-12v-4ah-1082341 | S15: https://fiskars-gratis.com.ua/akumuliator-fiskars-12v-4ah-1082341/ | T15: 2026-03-17 07:43:56 | X15: Акумулятор Fiskars 12V-4Ah | AA15: 0 | AB15: 0 | AC15: 0 | AD15: <p data-end="296" data-start="0"><span style="font-size:18px;"><strong data-end="40" data-start="0">Акумулятор Fiskars 12V-4Ah (1082341)</strong> </span><span style="font-size:14px;">&mdash; змінний акумуляторний блок для живлення садових електроінструментів акумуляторної лінійки Fiskars. Використовується як джерело енергії для бездротових інструментів під час виконання садових робіт на присадибних ділянках, у садах і господарських зонах.</span></p> <p data-end="557" data-start="298"><span style="font-size:18px;"><strong data-end="314" data-start="298">Призначення:</strong></span><span style="font-size:14px;"> підходить для забезпечення автономної роботи сумісних акумуляторних інструментів Fiskars, зокрема обладнання для обрізання рослин та інших робіт із догляду за садом. Дозволяє підтримувати роботу інструмента без підключення до електромережі.</span></p> <p data-end="803" data-start="559"><span style="font-size:18px;"><strong data-end="575" data-start="559">Конструкція:</strong></span><span style="font-size:14px;"> акумулятор виконаний у вигляді компактного змінного блока, який встановлюється у відповідний відсік інструмента та фіксується під час роботи. Форм-фактор забезпечує швидке встановлення та зняття під час заміни або заряджання.</span></p> <p data-end="943" data-start="805"><span style="font-size:18px;"><strong data-end="819" data-start="805">Матеріали:</strong></span><span style="font-size:14px;"> корпус виготовлений із ударостійкого технічного пластику, що захищає внутрішні елементи акумулятора під час експлуатації.</span></p> <p data-end="1113" data-is-last-node="" data-is-only-node="" data-start="945"><span style="font-size:18px;"><strong data-end="961" data-start="945">Особливості:</strong></span><span style="font-size:14px;"> акумулятор має робочу напругу 12 В і ємність 4 Ah. Призначений для багаторазового використання з сумісними акумуляторними інструментами бренду Fiskars.</span></p> | AE15: Акумулятор Fiskars 12V-4Ah — змінний акумуляторний блок для живлення садових електроінструментів акумуляторної лінійки Fiskars. Використовується як джерело енергії для бездротових інструментів під час виконання садових робіт на присадибних ділянках, у садах і господарських зонах. | AH15: 24 | AI15: 2026-03-17 07:43:29 | AN15: Нет | AO15: 8507 20 90 00 | AP15: 0 | AQ15: Выкл | AR15: Выкл | AU15: 46561816599 | AW15: Нет | AX15: Нет
A16: 1082298 | B16: 1082298 | C16: 1082298 | D16: Секатор акумуляторний Fiskars ePruner L, Bypass, Tool-Only без АКБ (1082298) | E16: Секатор акумуляторний Fiskars ePruner L, Bypass, Tool-Only без АКБ (1082298) | F16: Fiskars | G16: FISKARS/Акумуляторний інструмент | H16: 9999.00 | I16: 14999.00 | J16: UAH | K16: Да | L16: =VLOOKUP(C16,Sheet1!$C:$L,10,0) -> China | M16: Немає в наявності | O16: https://fiskars-gratis.com.ua/content/images/16/sekator-akumuliatornyi-fiskars-epruner-l-bypass-tool-only-bez-akb-1082298-43321917548533_+1b48282937.jpg; https://fiskars-gratis.com.ua/content/images/16/sekator-akumuliatornyi-fiskars-epruner-l-bypass-tool-only-bez-akb-1082298-25520542414971_+a5825b55f9.jpg | R16: sekator-akumuliatornyi-fiskars-epruner-l-bypass-tool-only-bez-akb-1082298 | S16: https://fiskars-gratis.com.ua/sekator-akumuliatornyi-fiskars-epruner-l-bypass-tool-only-bez-akb-1082298/ | T16: 2026-03-17 07:46:40 | X16: Секатор акумуляторний Fiskars ePruner L, Bypass, Tool-Only без АКБ | AA16: 0 | AB16: 0 | AC16: 0 | AD16: <p data-end="307" data-start="0"><span style="font-size:18px;"><strong data-end="80" data-start="0">Секатор акумуляторний Fiskars ePruner L, Bypass, Tool-Only без АКБ (1082298)</strong> </span><span style="font-size:14px;">&mdash; електричний ручний інструмент для обрізання гілок і догляду за деревами, кущами та декоративними рослинами у саду. Використовується для чистого зрізу живих пагонів під час формувального, санітарного та сезонного обрізання.</span></p> <p data-end="505" data-start="309"><span style="font-size:18px;"><strong data-end="325" data-start="309">Призначення:</strong></span><span style="font-size:14px;"> підходить для обрізання молодих і напівтвердих гілок, догляду за плодовими деревами, ягідними кущами, виноградом та декоративними насадженнями на присадибних і садових ділянках.</span></p> <p data-end="769" data-start="507"><span style="font-size:18px;"><strong data-end="523" data-start="507">Конструкція:</strong> </span><span style="font-size:14px;">ріжучий механізм типу bypass працює за принципом перехресного руху лез, що забезпечує точний зріз без значного пошкодження рослинних тканин. Електропривід автоматизує процес стискання лез і зменшує фізичне навантаження під час тривалої роботи.</span></p> <p data-end="960" data-start="771"><span style="font-size:18px;"><strong data-end="785" data-start="771">Матеріали:</strong></span><span style="font-size:14px;"> ріжучі леза виготовлені зі сталі, розрахованої на регулярне використання при обрізанні рослин. Корпус інструмента адаптований для ручної роботи та контролю під час різання.</span></p> <p data-end="1206" data-is-last-node="" data-is-only-node="" data-start="962"><span style="font-size:18px;"><strong data-end="978" data-start="962">Особливості:</strong> </span><span style="font-size:14px;">модель постачається у комплектації Tool-Only без акумулятора та зарядного пристрою і належить до акумуляторної садової лінійки бренду Fiskars. Призначена для систематичного використання під час догляду за садовими насадженнями.</span></p> | AE16: Секатор акумуляторний Fiskars ePruner L, Bypass, Tool-Only без АКБ — електричний ручний інструмент для обрізання гілок і догляду за деревами, кущами та декоративними рослинами у саду. Використовується для чистого зрізу живих пагонів під час формувального, санітарного та сезонного обрізання. | AH16: 24 | AI16: 2026-03-17 07:49:47 | AM16: Новий | AN16: Нет | AO16: 8467 29 00 00 | AP16: 0 | AQ16: Выкл | AR16: Выкл | AU16: 46561816568 | AW16: Нет | AX16: Нет
A17: 1082297 | B17: 1082297 | C17: 1082297 | D17: Секатор акумуляторний Fiskars ePruner M Bypassі з вбудованим акумулятором 8В 4 4Ah (1082297) | E17: Секатор акумуляторний Fiskars ePruner M Bypassі з вбудованим акумулятором 8В 4 4Ah (1082297) | F17: Fiskars | G17: FISKARS/Акумуляторний інструмент | H17: 9999.00 | I17: 14999.00 | J17: UAH | K17: Да | L17: =VLOOKUP(C17,Sheet1!$C:$L,10,0) -> China | M17: Немає в наявності | O17: https://fiskars-gratis.com.ua/content/images/17/sekator-akumuliatornyi-fiskars-epruner-m-bypassi-z-vbudovanym-akumuliatorom-8v-4-4ah-1082297-33665381691237_+f8640934ac.jpg; https://fiskars-gratis.com.ua/content/images/17/sekator-akumuliatornyi-fiskars-epruner-m-bypassi-z-vbudovanym-akumuliatorom-8v-4-4ah-1082297-71495293473480_+29081396f5.jpg; https://fiskars-gratis.com.ua/content/images/17/sekator-akumuliatornyi-fiskars-epruner-m-bypassi-z-vbudovanym-akumuliatorom-8v-4-4ah-1082297-84160697752622_+9ebb1b0aef.jpg | R17: sekator-akumuliatornyi-fiskars-epruner-m-bypassi-z-vbudovanym-akumuliatorom-8v-4-4ah-1082297 | S17: https://fiskars-gratis.com.ua/sekator-akumuliatornyi-fiskars-epruner-m-bypassi-z-vbudovanym-akumuliatorom-8v-4-4ah-1082297/ | T17: 2026-03-17 07:46:41 | X17: Секатор акумуляторний Fiskars ePruner M Bypass із вбудованим акумулятором 8В 4,4Ah | AA17: 0 | AB17: 0 | AC17: 0 | AD17: <p data-end="336" data-start="0"><span style="font-size:18px;"><strong data-end="96" data-start="0">Секатор акумуляторний Fiskars ePruner M Bypass із вбудованим акумулятором 8В 4,4Ah (1082297)</strong></span><span style="font-size:14px;"> &mdash; електричний ручний інструмент для обрізання гілок під час догляду за деревами, кущами та декоративними рослинами. Використовується для формувального та санітарного обрізання живих пагонів у садах, розсадниках і на присадибних ділянках.</span></p> <p data-end="596" data-start="338"><span style="font-size:18px;"><strong data-end="354" data-start="338">Призначення:</strong> </span><span style="font-size:14px;">підходить для обрізання молодих і напівтвердих гілок, догляду за плодовими деревами, ягідними кущами, виноградом та декоративними насадженнями. Дає змогу виконувати регулярні роботи з формування крони та підтримання здорового росту рослин.</span></p> <p data-end="893" data-start="598"><span style="font-size:18px;"><strong data-end="614" data-start="598">Конструкція:</strong></span><span style="font-size:14px;"> ріжучий механізм типу bypass працює за принципом перехресного руху лез, що забезпечує чистий зріз без значного пошкодження рослинних тканин. Електропривід автоматизує рух лез і зменшує фізичне навантаження під час роботи. Компактний корпус розрахований на роботу однією рукою.</span></p> <p data-end="1070" data-start="895"><span style="font-size:18px;"><strong data-end="909" data-start="895">Матеріали:</strong></span><span style="font-size:14px;"> леза виготовлені зі сталі, стійкої до регулярного використання при обрізанні рослин. Руків&rsquo;я адаптоване для контрольованого різання та тривалої ручної роботи.</span></p> <p data-end="1337" data-is-last-node="" data-is-only-node="" data-start="1072"><span style="font-size:18px;"><strong data-end="1088" data-start="1072">Особливості:</strong></span><span style="font-size:14px;"> модель оснащена вбудованим акумулятором 8 В ємністю 4,4 Ah, що забезпечує автономну роботу без зовнішнього джерела живлення. Інструмент належить до акумуляторної садової лінійки бренду Fiskars та призначений для систематичного догляду за рослинами.</span></p> | AE17: Секатор акумуляторний Fiskars ePruner M Bypass із вбудованим акумулятором 8В 4,4Ah — електричний ручний інструмент для обрізання гілок під час догляду за деревами, кущами та декоративними рослинами. Використовується для формувального та санітарного обрізання живих пагонів у садах, розсадниках і на присадибних ділянках. | AH17: 24 | AI17: 2026-03-17 07:50:16 | AM17: Новий | AN17: Нет | AO17: 8467 29 00 00 | AP17: 0 | AQ17: Выкл | AR17: Выкл | AU17: 46561816551 | AW17: Нет | AX17: Нет
A18: 1052240 | B18: 1052240 | C18: 1052240 | D18: Каструля Fiskars Hard Face Steel 3,5 л (1052240) | E18: Каструля Fiskars Hard Face Steel 3,5 л (1052240) | F18: Fiskars | G18: FISKARS/Посуд та кухонний інвентар Fiskars/Каструлі | H18: 3999.00 | I18: 5475.00 | J18: UAH | K18: Да | L18: =VLOOKUP(C18,Sheet1!$C:$L,10,0) -> Finland | M18: В наявності | N18: FISKARS/Посуд та кухонний інвентар Fiskars/Кухонне приладдя | O18: https://fiskars-gratis.com.ua/content/images/16/kastrulia-fiskars-hard-face-steel-35-l-1052240-48318519716309_+ab392840bb.jpg; https://fiskars-gratis.com.ua/content/images/16/kastrulia-fiskars-hard-face-steel-35-l-1052240-41910918198591_+9b7aeda45a.jpg; https://fiskars-gratis.com.ua/content/images/16/kastrulia-fiskars-hard-face-steel-35-l-1052240-91388840221464_+7df24964f1.jpg; https://fiskars-gratis.com.ua/content/images/16/kastrulia-fiskars-hard-face-steel-35-l-1052240-54369771624979_+9691b89190.jpg | R18: kastrulia-fiskars-hard-face-steel-35-l-1052240 | S18: https://fiskars-gratis.com.ua/kastrulia-fiskars-hard-face-steel-35-l-1052240/ | T18: 2026-02-22 16:32:03 | X18: Каструля Fiskars Hard Face Steel 3,5 л | AA18: 0 | AB18: 0 | AC18: 34 | AD18: <p><span style="font-size:18px;"><strong>Каструля Fiskars Hard Face Steel 3,5 л (1052240)</strong> </span><span style="font-size:14px;">&mdash; кухонний посуд для приготування рідких і напіврідких страв на плиті. Використовується для варіння супів, бульйонів, соусів, тушкування овочів, м&rsquo;яса та інших інгредієнтів, що потребують рівномірного нагріву і достатнього об&rsquo;єму.</span></p> <p data-end="503" data-start="287"><span style="font-size:18px;"><strong data-end="303" data-start="287">Призначення:</strong> </span><span style="font-size:14px;">підходить для повсякденного приготування страв великого і середнього обсягу у домашній кухні, де важливі стабільний розподіл тепла, контроль температури і можливість тривалого томління під кришкою.</span></p> <p data-end="808" data-start="505"><span style="font-size:18px;"><strong data-end="521" data-start="505">Конструкція:</strong> </span><span style="font-size:14px;">об&rsquo;єм 3,5 л і висока циліндрична форма забезпечують достатній простір для рідких страв і тушкованих сумішей. Кришка утримує пар і вологу під час приготування, сприяючи збереженню смакових якостей інгредієнтів. Руків&rsquo;я адаптоване для надійного захвату при перемішуванні та перенесенні.</span></p> <p data-end="1103" data-start="810"><span style="font-size:18px;"><strong data-end="824" data-start="810">Матеріали:</strong> </span><span style="font-size:14px;">корпус і робоча частина виготовлені зі сталі з твердим покриттям Hard Face Steel, що підвищує стійкість до подряпин і деформацій при регулярному використанні. Покриття сприяє рівномірному розподіленню тепла по поверхні. Руків&rsquo;я забезпечує контроль і комфорт під час готування.</span></p> <p data-end="1340" data-is-last-node="" data-is-only-node="" data-start="1105"><span style="font-size:18px;"><strong data-end="1121" data-start="1105">Особливості:</strong> </span><span style="font-size:14px;">каструля належить до серії Hard Face Steel бренду Fiskars та призначена для систематичного використання у процесі приготування страв, що потребують значного об&rsquo;єму і рівномірного прогріву.</span></p> | AE18: Каструля Fiskars Hard Face Steel 3,5 л — кухонний посуд для приготування рідких і напіврідких страв на плиті. Використовується для варіння супів, бульйонів, соусів, тушкування овочів, м’яса та інших інгредієнтів, що потребують рівномірного нагріву і достатнього об’єму. | AH18: 0 | AI18: 2026-02-22 23:01:38 | AL18: Facebook Feed; Google Feed for Merchant Center | AM18: Новий | AN18: Нет | AO18: 7323930090 | AP18: 0 | AQ18: Выкл | AR18: Выкл | AU18: 6411501702579 | AW18: Нет | AX18: Нет
A19: 40033792 | B19: 40033792 | C19: 40033792 | D19: Набір стаканів Waterford Marquis Maxwell 310 мл, 4 шт (40033792) | E19: Набір стаканів Waterford Marquis Maxwell 310 мл, 4 шт (40033792) | F19: Marquis | G19: FISKARS/Посуд та кухонний інвентар Fiskars/Кришталь | H19: 1999.00 | I19: 0.00 | J19: UAH | K19: Да | L19: =VLOOKUP(C19,Sheet1!$C:$L,10,0) -> Italy | M19: В наявності | O19: https://fiskars-gratis.com.ua/content/images/17/nabir-stakaniv-waterford-marquis-maxwell-310-ml-4-sht-40033792-73826755838475_+b8fa57ce3b.jpg; https://fiskars-gratis.com.ua/content/images/17/nabir-stakaniv-waterford-marquis-maxwell-310-ml-4-sht-40033792-76118528872844_+cda51bb92a.jpg; https://fiskars-gratis.com.ua/content/images/17/nabir-stakaniv-waterford-marquis-maxwell-310-ml-4-sht-40033792-76290828439155_+fbd11954cf.jpg; https://fiskars-gratis.com.ua/content/images/17/nabir-stakaniv-waterford-marquis-maxwell-310-ml-4-sht-40033792-40033361756709_+eead561a79.jpg | R19: nabir-stakaniv-waterford-marquis-maxwell-310-ml-4-sht-40033792 | S19: https://fiskars-gratis.com.ua/nabir-stakaniv-waterford-marquis-maxwell-310-ml-4-sht-40033792/ | T19: 2026-02-22 00:14:39 | X19: Набір стаканів Waterford Marquis Maxwell 310 мл, 4 шт | AA19: 0 | AB19: 0 | AC19: 4 | AD19: <p><span style="font-size:18px;"><b>Набір стаканів Waterford Marquis Maxwell 310 мл, 4 шт (40033792)</b> </span><span style="font-size:14px;">&mdash; комплект скляного посуду для сервірування напоїв у побутових та гостинних умовах. Використовується для подачі води, соків, безалкогольних напоїв, коктейлів і напоїв з льодом у повсякденному використанні або під час сервірування столу.</span></p> <p data-end="465" data-start="303"><span style="font-size:18px;"><b>Призначення:</b> </span><span style="font-size:14px;">підходить для домашнього вжитку, сервірування обіднього чи святкового столу, використання в їдальнях, гостьових зонах та подарункових наборах посуду.</span></p> <p data-end="689" data-start="467"><span style="font-size:18px;"><b>Конструкція:</b></span><span style="font-size:14px;"> стакани мають класичну циліндричну форму з виразним рельєфним візерунком, що забезпечує зручне утримання та візуальну структурованість подачі напоїв. Об&rsquo;єм 310 мл є універсальним для більшості холодних напоїв.</span></p> <p data-end="865" data-start="691"><span style="font-size:18px;"><b>Матеріали:</b> </span><span style="font-size:14px;">виготовлені з прозорого скла, розрахованого на регулярне використання та миття. Матеріал зберігає прозорість і форму при стандартних експлуатаційних навантаженнях.</span></p> <p data-end="1035" data-is-last-node="" data-is-only-node="" data-start="867"><span style="font-size:18px;"><b>Особливості:</b></span><span style="font-size:14px;"> набір належить до колекції Marquis бренду Waterford та орієнтований на поєднання функціональності й декоративної подачі напоїв.</span></p> | AE19: Набір стаканів Waterford Marquis Maxwell 310 мл, 4 шт — комплект скляного посуду для сервірування напоїв у побутових та гостинних умовах. | AH19: 0 | AI19: 2026-02-22 00:19:02 | AL19: Facebook Feed; Google Feed for Merchant Center | AM19: Новий | AN19: Нет | AO19: 7013379100 | AP19: 0 | AQ19: Выкл | AR19: Выкл | AU19: 701587408578 | AW19: Нет | AX19: Нет
A20: 40033803 | B20: 40033803 | C20: 40033803 | D20: Набір стаканів Marquis Moments 390 мл, 4 шт (40033803) | E20: Набір стаканів Marquis Moments 390 мл, 4 шт (40033803) | F20: Marquis | G20: FISKARS/Посуд та кухонний інвентар Fiskars/Кришталь | H20: 2999.00 | I20: 0.00 | J20: UAH | K20: Да | L20: =VLOOKUP(C20,Sheet1!$C:$L,10,0) -> Slovakia | M20: В наявності | O20: https://fiskars-gratis.com.ua/content/images/18/nabir-stakaniv-marquis-moments-390-ml-4-sht-40033803-27375478509570_+ed004a4514.jpg; https://fiskars-gratis.com.ua/content/images/18/nabir-stakaniv-marquis-moments-390-ml-4-sht-40033803-87287725661235_+282e7ce3c5.jpg; https://fiskars-gratis.com.ua/content/images/18/nabir-stakaniv-marquis-moments-390-ml-4-sht-40033803-72780130953544_+04cfa38bd2.jpg | R20: nabir-stakaniv-marquis-moments-390-ml-4-sht-40033803 | S20: https://fiskars-gratis.com.ua/nabir-stakaniv-marquis-moments-390-ml-4-sht-40033803/ | T20: 2026-02-22 00:14:39 | X20: Набір стаканів Marquis Moments 390 мл, 4 шт | AA20: 0 | AB20: 0 | AC20: 6 | AD20: <p><span style="font-size:18px;"><b>Набір стаканів Marquis Moments 390 мл, 4 шт (40033803)</b> </span><span style="font-size:14px;">&mdash; комплект скляного посуду для сервірування холодних напоїв у побутових і гостинних умовах. Використовується для подачі води, соків, лимонадів, коктейлів та напоїв з льодом у повсякденному використанні або під час накриття столу.</span></p> <p data-end="464" data-start="286"><span style="font-size:18px;"><b>Призначення:</b> </span><span style="font-size:14px;">підходить для домашнього користування, сервірування обіднього та святкового столу, використання в гостьових зонах, їдальнях і як елемент подарункового набору посуду.</span></p> <p data-end="699" data-start="466"><span style="font-size:18px;"><b>Конструкція:</b> </span><span style="font-size:14px;">стакани мають збільшений об&rsquo;єм 390 мл і класичну форму з декоративним рельєфним малюнком, що забезпечує зручне утримання в руці та впорядкований вигляд сервірування. Товсті стінки сприяють стабільності на поверхні столу.</span></p> <p data-end="833" data-start="701"><span style="font-size:18px;"><b>Матеріали:</b></span><span style="font-size:14px;"> виготовлені з прозорого скла, розрахованого на регулярне миття та щоденне використання без втрати прозорості й геометрії.</span></p> <p data-end="1007" data-is-last-node="" data-is-only-node="" data-start="835"><span style="font-size:18px;"><b>Особливості:</b> </span><span style="font-size:14px;">набір належить до серії Marquis бренду Waterford та орієнтований на практичне використання з акцентом на декоративну подачу напоїв.</span></p> | AE20: Набір стаканів Marquis Moments 390 мл, 4 шт — комплект скляного посуду для сервірування холодних напоїв у побутових і гостинних умовах. | AH20: 0 | AI20: 2026-02-22 00:18:15 | AL20: Facebook Feed; Google Feed for Merchant Center | AM20: Новий | AN20: Нет | AO20: 7013379100 | AP20: 0 | AQ20: Выкл | AR20: Выкл | AU20: 701587408660 | AW20: Нет | AX20: Нет
A21: 1065586 | B21: 1065586 | C21: 1065586 | D21: Ніж для чищення з рухомим лезом Fiskrs Essential, 6 см (1065586) | E21: Ніж для чищення з рухомим лезом Fiskrs Essential, 6 см (1065586) | F21: Fiskars | G21: FISKARS/Посуд та кухонний інвентар Fiskars/Кухонні ножі | H21: 387.00 | I21: 0.00 | J21: UAH | K21: Да | L21: =VLOOKUP(C21,Sheet1!$C:$L,10,0) -> China | M21: В наявності | O21: https://fiskars-gratis.com.ua/content/images/9/nizh-dlia-chyshchennia-z-rukhomym-lezom-fiskrs-essential-6-sm-1065586-91206989650470_+49fc39037f.jpg; https://fiskars-gratis.com.ua/content/images/9/nizh-dlia-chyshchennia-z-rukhomym-lezom-fiskrs-essential-6-sm-1065586-18014872494415_+0ee7986aa2.jpg; https://fiskars-gratis.com.ua/content/images/9/nizh-dlia-chyshchennia-z-rukhomym-lezom-fiskrs-essential-6-sm-1065586-86641223836252_+e876999031.jpg | R21: nizh-dlia-chyshchennia-z-rukhomym-lezom-fiskrs-essential-6-sm-1065586 | S21: https://fiskars-gratis.com.ua/nizh-dlia-chyshchennia-z-rukhomym-lezom-fiskrs-essential-6-sm-1065586/ | T21: 2026-02-22 02:02:09 | X21: Ніж для чищення з рухомим лезом Fiskrs Essential, 6 см | AA21: 0 | AB21: 0 | AC21: 5 | AD21: <p><span style="font-size:18px;"><b>Ніж для чищення з рухомим лезом Fiskars Essential, 6 </b><b>см (1065586)</b> </span><span style="font-size:14px;">&mdash; кухонний інструмент для підготовчих операцій з овочами, фруктами та іншими продуктами, що потребують контролю точних надрізів. Використовується для чищення, підрізання та обробки продуктів невеликого розміру, де потрібне гнучке й точне управління лезом.</span></p> <p><span style="font-size:18px;"><b>Призначення:</b> </span><span style="font-size:14px;">підходить для видалення шкірки, очищення внутрішніх частин овочів і фруктів, видалення насіння або підготовки продуктів до подальшого нарізання чи термічної обробки в домашній кухні.</span></p> <p><span style="font-size:18px;"><b>Конструкція:</b> </span><span style="font-size:14px;">коротке рухоме лезо довжиною 6 см розташоване під кутом, що забезпечує контрольований рух по поверхні продукту та дозволяє виконувати тонкі надрізи і скоблення. Ергономічна руків&rsquo;я забезпечує комфортний захват і контроль під час ручної роботи.</span></p> <p><span style="font-size:18px;"><b>Матеріали:</b></span><span style="font-size:14px;"> ріжуча частина із сталі високої якості підтримує гостроту кромки й витривалість при регулярному використанні. Руків&rsquo;я виготовлене з матеріалу, стійкого до зношування, та адаптоване для комфортної експлуатації.</span></p> <p><span style="font-size:18px;"><b>Особливості:</b> </span><span style="font-size:14px;">інструмент належить до серії Essential бренду Fiskars та призначений для точних і контрольованих кулінарних операцій із чищення та підготовки продуктів.</span></p> | AE21: Ніж для чищення з рухомим лезом Fiskars Essential, 6 см — кухонний інструмент для підготовчих операцій з овочами, фруктами та іншими продуктами, що потребують контролю точних надрізів. | AH21: 0 | AI21: 2026-02-22 22:27:31 | AM21: Новий | AN21: Нет | AO21: 8211920000 | AP21: 0 | AQ21: Выкл | AR21: Выкл | AU21: 6424002015659 | AW21: Нет | AX21: Нет
A22: 1000773 | B22: 1000773 | C22: 1000773 | D22: Набір ножів в дерев'яному блоці FISKARS Kitchen Devil (1000773) | E22: Набір ножів в деревяному блоці FISKARS Kitchen Devil (1000773) | F22: Fiskars | G22: FISKARS/Посуд та кухонний інвентар Fiskars/Кухонні ножі | H22: 3999.00 | I22: 0.00 | J22: UAH | K22: Да | L22: =VLOOKUP(C22,Sheet1!$C:$L,10,0) -> China | M22: В наявності | N22: FISKARS/Посуд та кухонний інвентар Fiskars/Кухонне приладдя | O22: https://fiskars-gratis.com.ua/content/images/22/nabir-nozhiv-v-derevianomu-blotsi-fiskars-kitchen-devil-1000773-63780900637716_+75525b7782.jpg; https://fiskars-gratis.com.ua/content/images/22/nabir-nozhiv-v-derevianomu-blotsi-fiskars-kitchen-devil-1000773-98312023505074_+813f2acc62.png | R22: nabir-nozhiv-v-derevianomu-blotsi-fiskars-kitchen-devil-1000773 | S22: https://fiskars-gratis.com.ua/nabir-nozhiv-v-derevianomu-blotsi-fiskars-kitchen-devil-1000773/ | T22: 2026-02-22 16:57:58 | X22: Набір ножів в дерев'яному блоці FISKARS Kitchen Devil | Z22: Хіт | AA22: 0 | AB22: 0 | AC22: 64 | AD22: <p><span style="font-size:18px;"><strong>Набір ножів у дерев&rsquo;яному блоці Fiskars Kitchen Devils (1000773)</strong> </span><span style="font-size:14px;">&mdash; комплект кухонних різальних інструментів із підставкою для зберігання, що включає ножі різних типів для широкого спектра кулінарних задач. Використовується для нарізання, чищення, подрібнення та поділу продуктів під час підготовки страв у домашній кухні.</span></p> <p data-end="543" data-start="327"><span style="font-size:18px;"><strong data-end="343" data-start="327">Призначення:</strong> </span><span style="font-size:14px;">підходить для повсякденних кулінарних операцій &mdash; підготовки овочів, фруктів, м&rsquo;яса, риби та інших інгредієнтів, що потребують різних технік обробки: від тонких надрізів до великих порційних розрізів.</span></p> <p data-end="879" data-start="545"><span style="font-size:18px;"><strong data-end="561" data-start="545">Конструкція:</strong> </span><span style="font-size:14px;">набір складається з кількох ножів із різною довжиною й формою лез, оптимізованих для конкретних завдань (універсальне, шеф-ніж, ніж для хліба тощо), а також дерев&rsquo;яного блока для організованого зберігання та легкого доступу до інструментів. Ергономічні руків&rsquo;я забезпечують надійний захват і контроль під час різання.</span></p> <p data-end="1140" data-start="881"><span style="font-size:18px;"><strong data-end="895" data-start="881">Матеріали:</strong></span><span style="font-size:14px;"> ріжучі частини виготовлені з високоякісної сталі, що підтримує гостроту кромок та витримує регулярне використання. Дерев&rsquo;яний блок виготовлений із міцної породи деревини, адаптованої для зберігання ножів і зручної організації робочого простору.</span></p> <p data-end="1387" data-is-last-node="" data-is-only-node="" data-start="1142"><span style="font-size:18px;"><strong data-end="1158" data-start="1142">Особливості:</strong> </span><span style="font-size:14px;">набір належить до серії Kitchen Devils бренду Fiskars та призначений для систематичного використання під час приготування різноманітних страв із контролем точності і організованим зберіганням ножів.</span></p> | AE22: Набір ножів у дерев’яному блоці Fiskars Kitchen Devils — комплект кухонних різальних інструментів із підставкою для зберігання, що включає ножі різних типів для широкого спектра кулінарних задач | AH22: 0 | AI22: 2026-02-22 22:49:41 | AM22: Новий | AN22: Нет | AO22: 8211920000 | AP22: 0 | AQ22: Выкл | AR22: Выкл | AU22: 5010624437385 | AW22: Нет | AX22: Нет
A23: 1065599 | B23: 1065599 | C23: 1065599 | D23: Ніж для чищення з поперечним лезом Fiskars Essential (1065599) | E23: Ніж для чищення з поперечним лезом Fiskars Essential (1065599) | F23: Fiskars | G23: FISKARS/Посуд та кухонний інвентар Fiskars/Кухонні ножі | H23: 568.00 | I23: 0.00 | J23: UAH | K23: Да | L23: =VLOOKUP(C23,Sheet1!$C:$L,10,0) -> China | M23: В наявності | O23: https://fiskars-gratis.com.ua/content/images/8/nizh-dlia-chyshchennia-z-poperechnym-lezom-fiskars-essential-1065599-91647425061699_+efb38d53f1.jpg; https://fiskars-gratis.com.ua/content/images/8/nizh-dlia-chyshchennia-z-poperechnym-lezom-fiskars-essential-1065599-73465714108127_+1ba4af3b5a.jpg; https://fiskars-gratis.com.ua/content/images/8/nizh-dlia-chyshchennia-z-poperechnym-lezom-fiskars-essential-1065599-35122456426225_+4bd9306169.jpg | R23: nizh-dlia-chyshchennia-z-poperechnym-lezom-fiskars-essential-1065599 | S23: https://fiskars-gratis.com.ua/nizh-dlia-chyshchennia-z-poperechnym-lezom-fiskars-essential-1065599/ | T23: 2026-02-22 02:02:09 | X23: Ніж для чищення з поперечним лезом Fiskars Essential | AA23: 0 | AB23: 0 | AC23: 5 | AD23: <p><span style="font-size:18px;"><b>Ніж для чищення з поперечним лезом Fiskars Essential (1065599)</b> </span><span style="font-size:14px;">&mdash; кухонний різальний інструмент для точних підготовчих операцій з овочами і фруктами. Використовується для чищення, видалення шкірки, формування та тонких контрольованих надрізів на продуктах невеликого розміру.</span></p> <p><span style="font-size:18px;"><b>Призначення:</b></span><span style="font-size:14px;"> підходить для підготовки овочів і фруктів перед подрібненням чи подачею, акуратного видалення шкірки, кореневих частин, а також для контролю форми і розміру шматочків при приготуванні салатів і гарнірів.</span></p> <p><span style="font-size:18px;"><b>Конструкція:</b> </span><span style="font-size:14px;">поперечне коротке лезо зігнуто для комфортного та контрольованого руху по поверхні продукту. Ергономічна руків&rsquo;я адаптована для надійного захвату та точного контролю ножа під час роботи з дрібними інгредієнтами.</span></p> <p><span style="font-size:18px;"><b>Матеріали:</b> </span><span style="font-size:14px;">ріжуча частина виготовлена з високоякісної сталі, що забезпечує гостроту кромки й тривалий ресурс використання. Руків&rsquo;я виготовлене з матеріалу, стійкого до зношування, що забезпечує комфорт під час роботи.</span></p> <p><span style="font-size:18px;"><b>Особливості:</b></span><span style="font-size:14px;"> ніж належить до серії Essential бренду Fiskars та призначений для ефективної та контрольованої обробки овочів і фруктів у кулінарних задачах.</span></p> | AE23: Ніж для чищення з поперечним лезом Fiskars Essential — кухонний різальний інструмент для точних підготовчих операцій з овочами і фруктами. | AH23: 0 | AI23: 2026-02-22 22:26:07 | AM23: Новий | AN23: Нет | AO23: 8211920000 | AP23: 0 | AQ23: Выкл | AR23: Выкл | AU23: 6424002015789 | AW23: Нет | AX23: Нет
A24: 1065567 | B24: 1065567 | C24: 1065567 | D24: Ніж філейний Fiskars Essential, 18 см (1065567) | E24: Ніж філейний Fiskars Essential, 18 см (1065567) | F24: Fiskars | G24: FISKARS/Посуд та кухонний інвентар Fiskars/Кухонні ножі | H24: 847.00 | I24: 0.00 | J24: UAH | K24: Да | L24: =VLOOKUP(C24,Sheet1!$C:$L,10,0) -> China | M24: В наявності | N24: FISKARS/Посуд та кухонний інвентар Fiskars/Кухонне приладдя | O24: https://fiskars-gratis.com.ua/content/images/6/nizh-fileinyi-fiskars-essential-18-sm-1065567-50960032720090_+eb1df98459.jpg; https://fiskars-gratis.com.ua/content/images/6/nizh-fileinyi-fiskars-essential-18-sm-1065567-14489302758900_+e099408490.jpg; https://fiskars-gratis.com.ua/content/images/6/nizh-fileinyi-fiskars-essential-18-sm-1065567-93027943353915_+27d98a70fd.jpg | R24: nizh-fileinyi-fiskars-essential-18-sm-1065567 | S24: https://fiskars-gratis.com.ua/nizh-fileinyi-fiskars-essential-18-sm-1065567/ | T24: 2026-02-22 02:02:09 | X24: Ніж філейний Fiskars Essential, 18 см | AA24: 0 | AB24: 0 | AC24: 5 | AD24: <p><span style="display: none;">&nbsp;</span><b>Ніж філейний Fiskars Essential, 18 см (1065567)</b><span style="display: none;">&nbsp;</span><span style="font-size:14px;"> &mdash; кухонний різальний інструмент для тонкого нарізання м&rsquo;яса, риби й інших продуктів. Використовується для філеювання, розділення тушок, тонких і точних розрізів уздовж кісток, а також для обробки великих шматків продуктів із контролем руху леза.</span></p> <p><span style="font-size:18px;"><b>Призначення:</b> </span><span style="font-size:14px;">підходить для підготовчих операцій у кулінарії &mdash; філеювання риби, розрізання м&rsquo;яса на тонкі шматки, видалення кісток і шкіри, точного нарізання продуктів під час приготування страв у домашніх і професійних умовах.</span></p> <p><span style="font-size:18px;"><b>Конструкція:</b> </span><span style="font-size:14px;">довге тонке лезо довжиною 18 см і вузька форма забезпечують гнучкість під час обробки продуктів, точну передачу руху та контроль над кутом нарізання. Комфортна руків&rsquo;я адаптована для надійного захвату та контролю під час різання.</span></p> <p><span style="font-size:18px;"><b>Матеріали:</b></span><span style="font-size:14px;"> ріжуча частина виготовлена з високоякісної сталі, що забезпечує гостроту ріжучої кромки й можливість тривалого використання. Руків&rsquo;я з матеріалу, стійкого до зношування, забезпечує стабільний захват і комфорт під час роботи.</span></p> <p><span style="font-size:18px;"><b>Особливості:</b></span><span style="font-size:14px;"> ніж належить до серії Essential бренду Fiskars та призначений для точних і контрольованих кулінарних задач із тонким нарізанням і обробкою продуктів.</span></p> | AE24: Ніж філейний Fiskars Essential, 18 см — кухонний різальний інструмент для тонкого нарізання м’яса, риби й інших продуктів. | AH24: 0 | AI24: 2026-02-22 22:20:34 | AM24: Новий | AN24: Нет | AO24: 8211920000 | AP24: 0 | AQ24: Выкл | AR24: Выкл | AU24: 6424002015567 | AW24: Нет | AX24: Нет
A25: 1065565 | B25: 1065565 | C25: 1065565 | D25: Ніж для шеф-кухаря Fiskars Essential, 21см (1065565) | E25: Ніж для шеф-кухаря Fiskars Essential, 21см (1065565) | F25: Fiskars | G25: FISKARS/Посуд та кухонний інвентар Fiskars/Кухонні ножі | H25: 847.00 | I25: 0.00 | J25: UAH | K25: Да | L25: =VLOOKUP(C25,Sheet1!$C:$L,10,0) -> China | M25: В наявності | O25: https://fiskars-gratis.com.ua/content/images/7/nizh-dlia-shef-kukharia-fiskars-essential-21sm-1065565-53553694462884_+1683d9f6e4.jpg; https://fiskars-gratis.com.ua/content/images/7/nizh-dlia-shef-kukharia-fiskars-essential-21sm-1065565-79749504191256_+d8b16edd5b.jpg; https://fiskars-gratis.com.ua/content/images/7/nizh-dlia-shef-kukharia-fiskars-essential-21sm-1065565-56849158667769_+da695c7c17.jpg | R25: nizh-dlia-shef-kukharia-fiskars-essential-21sm-1065565 | S25: https://fiskars-gratis.com.ua/nizh-dlia-shef-kukharia-fiskars-essential-21sm-1065565/ | T25: 2026-02-22 02:02:09 | X25: Ніж для шеф-кухаря Fiskars Essential, 21см | AA25: 0 | AB25: 0 | AC25: 5 | AD25: <p><span style="display: none;">&nbsp;</span><b>Ніж для шеф‑кухаря Fiskars Essential, 21 см (1065565)</b><span style="display: none;">&nbsp;</span><span style="font-size:14px;"> &mdash; кухонний різальний інструмент універсального призначення для підготовки і обробки продуктів. Використовується для нарізання, рубання, шинкування і подрібнення м&rsquo;яса, овочів, фруктів та інших інгредієнтів під час приготування страв.</span></p> <p><span style="font-size:18px;"><b>Призначення:</b> </span><span style="font-size:14px;">підходить для щоденної кулінарної роботи в домашніх і професійних умовах, де потрібна універсальна ріжуча кромка для різних технік обробки продуктів: від тонких скибок до кубиків та шматочків.</span></p> <p><span style="font-size:18px;"><b>Конструкція:</b></span><span style="font-size:14px;"> довжина леза 21 см і загальна форма ножа створені для комфортного виконання різних кухонних операцій. Руків&rsquo;я адаптоване для зручного, контрольованого захвату під час різання та подрібнення продуктів.</span></p> <p><span style="font-size:18px;"><b>Матеріали:</b></span><span style="font-size:14px;"> ріжуча частина виготовлена з високоякісної сталі, що забезпечує гостроту кромки і тривалий термін експлуатації. Руків&rsquo;я виготовлене з міцного матеріалу, стійкого до механічного зношування і забезпечує надійний та комфортний захват.</span></p> <p><span style="font-size:18px;"><b>Особливості:</b> </span><span style="font-size:14px;">ніж належить до серії Essential бренду Fiskars та призначений для широкого спектра кулінарних задач з контролем точності і ефективності різання.</span></p> | AH25: 0 | AI25: 2026-02-22 22:22:36 | AM25: Новий | AN25: Нет | AO25: 8211920000 | AP25: 0 | AQ25: Выкл | AR25: Выкл | AU25: 6424002015543 | AW25: Нет | AX25: Нет
A26: 1065587 | B26: 1065587 | C26: 1065587 | D26: Кухонний ніж Fiskars Essential для сиру 21 см Black (1065587) | E26: Кухонний ніж Fiskars Essential для сиру 21 см Black (1065587) | F26: Fiskars | G26: FISKARS/Посуд та кухонний інвентар Fiskars/Кухонні ножі/Кухонні ножі Fiskars Essential | H26: 635.00 | I26: 900.00 | J26: UAH | K26: Да | L26: =VLOOKUP(C26,Sheet1!$C:$L,10,0) -> China | M26: В наявності | O26: https://fiskars-gratis.com.ua/content/images/13/kukhonnyi-nizh-fiskars-essential-dlia-syru-21-sm-black-1065587-59179465975563_+685acdbc75.jpg; https://fiskars-gratis.com.ua/content/images/13/kukhonnyi-nizh-fiskars-essential-dlia-syru-21-sm-black-1065587-87024309318355_+29ccd0cfc3.jpg | P26: https://fiskars-gratis.com.ua/content/images/13/kukhonnyi-nizh-fiskars-essential-dlia-syru-21-sm-black-1065587-36437256096250_+6b3e7e0392.jpg | R26: kukhonnyi-nizh-fiskars-essential-dlia-syru-21-sm-black-1065587 | S26: https://fiskars-gratis.com.ua/kukhonnyi-nizh-fiskars-essential-dlia-syru-21-sm-black-1065587/ | T26: 2026-01-13 21:48:02 | X26: Кухонний ніж Fiskars Essential для сиру 21 см Black | AA26: 0 | AB26: 0 | AC26: 3 | AD26: <p>Ніж‑слайсер для сиру&nbsp;<strong data-end="50" data-start="29">Fiskars Essential</strong>&nbsp;21 см (1065587) з гострим лезом зі сталі. Кут леза мінімізує кришення. Ергономічна чорна ручка &mdash; легкість і контроль.</p> <p>Ніж‑слайсер для сиру&nbsp;<strong data-end="42" data-start="21">Fiskars Essential</strong>&nbsp;(21 см, 1065587) &mdash; надійний інструмент для ідеальних скибок пармезану, чеддера або інших твердих сирів. Унікальний кут леза з нержавіючої сталі дозволяє нарізати рівно й без кришення сиру. Ергономічна ручка з якісного пластику дає комфорт і контроль.</p> <p>Компактний дизайн і легкість у догляді &mdash; помічник на кожен день на вашій кухні.</p> | AE26: Ніж‑слайсер для сиру Fiskars Essential 21 см з гострим лезом зі сталі | AF26: Сірий | AG26: Виробник | AH26: 0 | AI26: 2026-02-18 21:45:30 | AN26: Нет | AO26: 8214900000 | AP26: 0 | AQ26: Выкл | AR26: Выкл | AU26: 1065587 | AW26: Нет | AX26: Нет
A27: 1024458 | B27: 1024458 | C27: 1024458 | D27: Сковорода Fiskars Handy 28 см (1024458) | E27: Сковорода Fiskars Handy 28 см (1024458) | F27: Fiskars | G27: FISKARS/Посуд та кухонний інвентар Fiskars/Сковороди | H27: 1299.00 | I27: 1900.00 | J27: UAH | K27: Да | L27: =VLOOKUP(C27,Sheet1!$C:$L,10,0) -> Finland | M27: В наявності | O27: https://fiskars-gratis.com.ua/content/images/12/skovoroda-fiskars-handy-28-sm-1024458-35260909044832_+5273e73a6e.jpg | R27: skovoroda-fiskars-handy-28-sm-1024458 | S27: https://fiskars-gratis.com.ua/skovoroda-fiskars-handy-28-sm-1024458/ | T27: 2026-02-22 16:24:46 | X27: Сковорода Fiskars Handy 28 см | AA27: 0 | AB27: 0 | AC27: 6 | AD27: <p><span style="font-size:18px;"><b>Сковорода Fiskars Handy 28 см (1024458)</b> </span><span style="font-size:14px;">&mdash; кухонний посуд для приготування страв методом смаження, тушкування та обсмажування на плиті. Використовується для обробки м&rsquo;яса, риби, овочів та інших продуктів із рівномірним прогріванням і контролем температури.</span></p> <p><span style="font-size:18px;"><b>Призначення:</b></span><span style="font-size:14px;"> підходить для щоденного приготування страв, розігрівання продуктів і обсмажування в домашніх умовах, де важлива легкість і зручність у використанні.</span></p> <p><span style="font-size:18px;"><b>Конструкція:</b> </span><span style="font-size:14px;">діаметр 28 см забезпечує оптимальну площу для розподілу продуктів. Ергономічне руків&rsquo;я дозволяє комфортно утримувати сковороду під час перемішування або перенесення, а висока стінка зменшує розбризкування.</span></p> <p><span style="font-size:18px;"><b>Матеріали:</b> </span><span style="font-size:14px;">робоча частина виготовлена зі сталі з антипригарним покриттям, що забезпечує рівномірний нагрів і стійкість до деформацій при регулярному використанні. Руків&rsquo;я адаптоване для зручного та надійного захвату під час приготування.</span></p> <p><span style="font-size:18px;"><b>Особливості:</b> </span><span style="font-size:14px;">сковорода належить до серії Handy бренду Fiskars та призначена для зручного та тривалого використання у повсякденному приготуванні страв із контролем температури та легким очищенням.</span></p> | AE27: Сковорода Fiskars Handy 28 см — кухонний посуд для приготування страв методом смаження, тушкування та обсмажування на плиті. | AH27: 0 | AI27: 2026-02-22 22:10:50 | AL27: Facebook Feed; Google Feed for Merchant Center | AM27: Новий | AN27: Нет | AO27: 7615108000 | AP27: 0 | AQ27: Выкл | AR27: Выкл | AU27: 6428517001077 | AW27: Нет | AX27: Нет
A28: 1052247 | B28: 1052247 | C28: 1052247 | D28: Сковорода Fiskars Hard Face Steel 28 см (1052247) | E28: Сковорода Fiskars Hard Face Steel 28 см (1052247) | F28: Fiskars | G28: FISKARS/Посуд та кухонний інвентар Fiskars/Сковороди | H28: 1999.00 | I28: 3649.00 | J28: UAH | K28: Да | L28: =VLOOKUP(C28,Sheet1!$C:$L,10,0) -> Finland | M28: В наявності | O28: https://fiskars-gratis.com.ua/content/images/11/skovoroda-fiskars-hard-face-steel-28-sm-1052247-97232654657027_+15a3753e88.jpg; https://fiskars-gratis.com.ua/content/images/11/skovoroda-fiskars-hard-face-steel-28-sm-1052247-39122952639056_+a9650d1d39.jpg; https://fiskars-gratis.com.ua/content/images/11/skovoroda-fiskars-hard-face-steel-28-sm-1052247-93402270231406_+9daae4912f.jpg; https://fiskars-gratis.com.ua/content/images/11/skovoroda-fiskars-hard-face-steel-28-sm-1052247-65270858181955_+10f3b2bd98.jpg; https://fiskars-gratis.com.ua/content/images/11/skovoroda-fiskars-hard-face-steel-28-sm-1052247-66666586457570_+73244f6653.jpg | R28: skovoroda-fiskars-hard-face-steel-28-sm-1052247 | S28: https://fiskars-gratis.com.ua/skovoroda-fiskars-hard-face-steel-28-sm-1052247/ | T28: 2026-02-22 16:24:46 | X28: Сковорода Fiskars Hard Face Steel 28 см | AA28: 0 | AB28: 0 | AC28: 6 | AD28: <p><span style="font-size:18px;"><b>Сковорода Fiskars Hard Face Steel 28 см (1052247)</b> </span><span style="font-size:14px;">&mdash; кухонний посуд для приготування страв методом смаження, тушкування та обсмажування на плиті. Використовується для обробки м&rsquo;яса, риби, овочів і інших продуктів із контролем температури та рівномірним прогріванням.</span></p> <p><span style="font-size:18px;"><b>Призначення:</b> </span><span style="font-size:14px;">підходить для щоденного приготування гарячих страв, розігрівання продуктів і обсмажування в домашніх і професійних умовах, де важлива зносостійкість і довготривала експлуатація поверхні.</span></p> <p><span style="font-size:18px;"><b>Конструкція:</b> </span><span style="font-size:14px;">діаметр 28 см і висока стінка забезпечують рівномірне розподілення продуктів і запобігають розбризкуванню. Ергономічне руків&rsquo;я дозволяє комфортно утримувати посуд під час перемішування і перенесення.</span></p> <p><span style="font-size:18px;"><b>Матеріали:</b> </span><span style="font-size:14px;">робоча поверхня виготовлена зі сталі з твердим покриттям Hard Face, що підвищує стійкість до подряпин і деформацій при регулярному використанні. Руків&rsquo;я забезпечує надійний захват і контроль під час приготування.</span></p> <p><span style="font-size:18px;"><b>Особливості:</b> </span><span style="font-size:14px;">сковорода належить до серії Hard Face Steel бренду Fiskars та орієнтована на тривале використання з рівномірним прогріванням продуктів і підвищеною стійкістю робочої поверхні.</span></p> | AE28: Сковорода Fiskars Hard Face Steel 28 см — кухонний посуд для приготування страв методом смаження, тушкування та обсмажування на плиті. | AH28: 0 | AI28: 2026-02-22 22:08:23 | AL28: Facebook Feed; Google Feed for Merchant Center | AM28: Новий | AN28: Нет | AO28: 7323930090 | AP28: 0 | AQ28: Выкл | AR28: Выкл | AU28: 6411501702647 | AW28: Нет | AX28: Нет
A29: 1059096 | B29: 1059096 | C29: 1059096 | D29: Сковорода Fiskars Steel 28 см (1059096) | E29: Сковорода Fiskars Steel 28 см (1059096) | F29: Fiskars | G29: FISKARS/Посуд та кухонний інвентар Fiskars/Сковороди | H29: 2300.00 | I29: 0.00 | J29: UAH | K29: Да | L29: =VLOOKUP(C29,Sheet1!$C:$L,10,0) -> Finland | M29: В наявності | O29: https://fiskars-gratis.com.ua/content/images/10/skovoroda-fiskars-steel-28-sm-1059096-91628952092943_+c6ceebf7e4.jpeg; https://fiskars-gratis.com.ua/content/images/10/skovoroda-fiskars-steel-28-sm-1059096-69073930909240_+b9cf4aff94.jpeg; https://fiskars-gratis.com.ua/content/images/10/skovoroda-fiskars-steel-28-sm-1059096-23524419194146_+a22fd94b93.jpeg | R29: skovoroda-fiskars-steel-28-sm-1059096 | S29: https://fiskars-gratis.com.ua/skovoroda-fiskars-steel-28-sm-1059096/ | T29: 2026-02-22 16:24:45 | X29: Сковорода Fiskars Steel 28 см | AA29: 0 | AB29: 0 | AC29: 36 | AD29: <p><span style="font-size:18px;"><b>Сковорода Fiskars Steel 28 см (1059096)</b> </span><span style="font-size:14px;">&mdash; кухонний посуд для приготування різноманітних страв на плиті. Використовується для смаження, тушкування, обсмажування овочів, м&rsquo;яса, риби та інших продуктів із контрольованою температурою приготування.</span></p> <p><span style="font-size:18px;"><b>Призначення:</b></span><span style="font-size:14px;"> підходить для щоденного приготування страв, розігрівання продуктів і обсмажування в домашніх та професійних умовах, де потрібна рівномірна теплопередача і стійкість до високих температур.</span></p> <p><span style="font-size:18px;"><b>Конструкція:</b> </span><span style="font-size:14px;">кругла форма діаметром 28 см забезпечує рівномірне розподілення продуктів по поверхні. Довга руків&rsquo;я дозволяє зручно утримувати посуд під час перемішування або перенесення, а висока стінка обмежує розбризкування жирів.</span></p> <p><span style="font-size:18px;"><b>Матеріали:</b> </span><span style="font-size:14px;">робоча частина виготовлена з міцної сталі, що рівномірно нагрівається і стійка до деформації при регулярному використанні. Руків&rsquo;я забезпечує комфортний захват і контроль посуду під час приготування.</span></p> <p><span style="font-size:18px;"><b>Особливості:</b> </span><span style="font-size:14px;">сковорода належить до серії Steel бренду Fiskars та призначена для систематичного приготування страв із рівномірним прогріванням і зручним управлінням під час процесу.</span></p> | AE29: Сковорода Fiskars Steel 28 см — кухонний посуд для приготування різноманітних страв на плиті. | AH29: 0 | AI29: 2026-02-22 22:06:29 | AL29: Facebook Feed; Google Feed for Merchant Center | AM29: Новий | AN29: Нет | AO29: 7323930090 | AP29: 0 | AQ29: Выкл | AR29: Выкл | AU29: 6424002013501 | AW29: Нет | AX29: Нет
A30: 1023739 | B30: 1023739 | C30: 1023739 | D30: Сковорода Fiskars Rotisser 24 см (1023739) | E30: Сковорода Fiskars Rotisser 24 см (1023739) | F30: Fiskars | G30: FISKARS/Посуд та кухонний інвентар Fiskars/Сковороди | H30: 2529.00 | I30: 0.00 | J30: UAH | K30: Да | L30: =VLOOKUP(C30,Sheet1!$C:$L,10,0) -> Finland | M30: В наявності | O30: https://fiskars-gratis.com.ua/content/images/14/skovoroda-fiskars-rotisser-24-sm-1023739-19717725326156_+0fc56ffea6.jpg; https://fiskars-gratis.com.ua/content/images/14/skovoroda-fiskars-rotisser-24-sm-1023739-17437096741886_+60614983d8.jpg; https://fiskars-gratis.com.ua/content/images/14/skovoroda-fiskars-rotisser-24-sm-1023739-42794243905700_+8c4b555a65.jpg | R30: skovoroda-fiskars-rotisser-24-sm-1023739 | S30: https://fiskars-gratis.com.ua/skovoroda-fiskars-rotisser-24-sm-1023739/ | T30: 2026-02-22 16:24:46 | X30: Сковорода Fiskars Rotisser 24 см | AA30: 0 | AB30: 0 | AC30: 36 | AD30: <p><span style="font-size:18px;"><b>Сковорода Fiskars Rotisser 24 </b><b>см (1023739)</b> </span><span style="font-size:14px;">&mdash; кухонний посуд для приготування страв методом смаження, тушкування та обсмажування на плиті. Використовується для обробки м&rsquo;яса, риби, овочів і інших продуктів із контрольованим розподілом тепла і можливістю рівномірного готування невеликих порцій.</span></p> <p><span style="font-size:18px;"><b>Призначення:</b> </span><span style="font-size:14px;">підходить для щоденного приготування гарячих страв, розігрівання продуктів і обсмажування у домашніх умовах, де важлива зручність у використанні та рівномірна теплопередача на робочій поверхні.</span></p> <p><span style="font-size:18px;"><b>Конструкція:</b></span><span style="font-size:14px;"> діаметр 24 см забезпечує оптимальну площу для приготування порцій середнього розміру. Бортик і форма сковороди забезпечують контроль при додаванні інгредієнтів і зменшують розбризкування під час готування. Ергономічне руків&rsquo;я адаптоване для комфортного захвату і контролю під час перемішування, перенесення і подачі страв.</span></p> <p><span style="font-size:18px;"><b>Матеріали:</b></span><span style="font-size:14px;"> робоча частина виготовлена зі сталі з антипригарним покриттям, що сприяє рівномірному нагріву і знижує ризик прилипання продуктів до поверхні. Руків&rsquo;я забезпечує надійний захват у процесі приготування.</span></p> <p><span style="font-size:18px;"><b>Особливості:</b> </span><span style="font-size:14px;">сковорода належить до серії Rotisser бренду Fiskars та призначена для систематичного приготування страв із рівномірним прогріванням і полегшеним доглядом за поверхнею.</span></p> | AE30: Сковорода Fiskars Rotisser 24 см — кухонний посуд для приготування страв методом смаження, тушкування та обсмажування на плиті. | AH30: 0 | AI30: 2026-02-22 22:14:17 | AL30: Facebook Feed; Google Feed for Merchant Center | AM30: Новий | AN30: Нет | AO30: 7615108000 | AP30: 0 | AQ30: Выкл | AR30: Выкл | AU30: 6424002005926 | AW30: Нет | AX30: Нет
A31: 1075041 | B31: 1075041 | C31: 1075041 | D31: Сковорода Fiskars 375 Anniversary 24cm (1075041) | E31: Сковорода Fiskars 375 Anniversary 24cm (1075041) | F31: Fiskars | G31: FISKARS/Посуд та кухонний інвентар Fiskars/Сковороди | H31: 2618.00 | I31: 0.00 | J31: UAH | K31: Да | L31: =VLOOKUP(C31,Sheet1!$C:$L,10,0) -> Finland | M31: В наявності | O31: https://fiskars-gratis.com.ua/content/images/13/skovoroda-fiskars-375-anniversary-24cm-1075041-78701288961717_+2ec1bcddae.jpg; https://fiskars-gratis.com.ua/content/images/13/skovoroda-fiskars-375-anniversary-24cm-1075041-39386612873535_+461253fa59.jpg; https://fiskars-gratis.com.ua/content/images/13/skovoroda-fiskars-375-anniversary-24cm-1075041-36178488189768_+d73d30e555.jpg; https://fiskars-gratis.com.ua/content/images/13/skovoroda-fiskars-375-anniversary-24cm-1075041-22784691057209_+47698c45ed.jpg | R31: skovoroda-fiskars-375-anniversary-24cm-1075041 | S31: https://fiskars-gratis.com.ua/skovoroda-fiskars-375-anniversary-24cm-1075041/ | T31: 2026-02-22 16:24:46 | X31: Сковорода Fiskars 375 Anniversary 24cm | AA31: 0 | AB31: 0 | AC31: 36 | AD31: <p><span style="display: none;">&nbsp;</span><b>Сковорода Fiskars 375 Anniversary 24 см (1075041)</b><span style="display: none;">&nbsp;</span><span style="font-size:14px;"> &mdash; кухонний посуд для приготування страв методом смаження, тушкування та обсмажування на плиті. Використовується для обробки м&rsquo;яса, риби, овочів і інших продуктів із контрольованим розподілом тепла по поверхні.</span></p> <p><span style="font-size:18px;"><b>Призначення:</b></span><span style="font-size:14px;"> підходить для щоденного приготування гарячих страв, розігрівання і обсмажування порцій середнього розміру у домашніх умовах, де важлива рівномірна теплопередача та зручність у використанні.</span></p> <p><span style="font-size:18px;"><b>Конструкція:</b></span><span style="font-size:14px;"> діаметр 24 см забезпечує оптимальну площу для приготування невеликих і середніх порцій. Руків&rsquo;я адаптоване для комфортного захвату та контролю посуду під час перемішування, перенесення або подачі страв.</span></p> <p><span style="font-size:18px;"><b>Матеріали:</b> </span><span style="font-size:14px;">робоча частина виготовлена зі сталі, що рівномірно прогрівається та стійка до деформацій при регулярному використанні. Поверхня має покриття, що полегшує процес приготування і зменшує прилипання продуктів. Руків&rsquo;я забезпечує надійний захват під час роботи на плиті.</span></p> <p><span style="font-size:18px;"><b>Особливості:</b> </span><span style="font-size:14px;">сковорода випущена до ювілейної серії 375 Anniversary бренду Fiskars та призначена для систематичного приготування страв із рівномірним прогріванням і зручним контролем під час готування.</span></p> | AE31: Сковорода Fiskars 375 Anniversary 24 см — кухонний посуд для приготування страв методом смаження, тушкування та обсмажування на плиті. | AH31: 0 | AI31: 2026-02-22 22:12:41 | AL31: Facebook Feed; Google Feed for Merchant Center | AM31: Новий | AN31: Нет | AO31: 7323930090 | AP31: 0 | AQ31: Выкл | AR31: Выкл | AU31: 6424002019800 | AW31: Нет | AX31: Нет
A32: 1023752 | B32: 1023752 | C32: 1023752 | D32: Сотейник Fiskars Rotisser 26 см з кришкою (1023752) | E32: Сотейник Fiskars Rotisser 26 см з кришкою (1023752) | F32: Fiskars | G32: FISKARS/Посуд та кухонний інвентар Fiskars/Сотейники | H32: 2999.00 | I32: 6109.00 | J32: UAH | K32: Да | L32: =VLOOKUP(C32,Sheet1!$C:$L,10,0) -> Finland | M32: В наявності | N32: FISKARS/Посуд та кухонний інвентар Fiskars/Кухонне приладдя | O32: https://fiskars-gratis.com.ua/content/images/15/soteinyk-fiskars-rotisser-26-sm-z-kryshkoiu-1023752-44644687503273_+29fa61e697.jpg | R32: soteinyk-fiskars-rotisser-26-sm-z-kryshkoiu-1023752 | S32: https://fiskars-gratis.com.ua/soteinyk-fiskars-rotisser-26-sm-z-kryshkoiu-1023752/ | T32: 2026-02-22 16:28:33 | X32: Сотейник Fiskars Rotisser 26 см з кришкою | AA32: 0 | AB32: 0 | AC32: 4 | AD32: <p><span style="font-size:18px;"><strong>Сотейник Fiskars Rotisser 26 см з кришкою (1023752)</strong></span><span style="font-size:14px;"> &mdash; кухонний посуд для приготування страв методом смаження, тушкування, випаровування та варіння на плиті з використанням кришки. Використовується для обробки м&rsquo;яса, птиці, риби, овочів і соусів із контролем тепла та вологи під час приготування.</span></p> <p data-end="590" data-start="301"><span style="font-size:18px;"><strong data-end="317" data-start="301">Призначення:</strong> </span><span style="font-size:14px;">підходить для щоденного приготування гарячих страв середнього обсягу в домашніх умовах, де потрібен контроль над процесом теплової обробки під кришкою або без неї: соусів, рагу, тушкованих страв, овочевих сумішей та інгредієнтів, що потребують рівномірної теплопередачі.</span></p> <p data-end="933" data-start="592"><span style="font-size:18px;"><strong data-end="608" data-start="592">Конструкція:</strong> </span><span style="font-size:14px;">форма сотейника діаметром 26 см дозволяє рівномірно розподіляти продукти та теплову енергію. Високі стінки й кришка допомагають утримувати вологу під час готування, зменшуючи випаровування і сприяючи акуратній обробці інгредієнтів. Ергономічне руків&rsquo;я адаптоване для комфортного захвату під час перемішування та перенесення.</span></p> <p data-end="1215" data-start="935"><span style="font-size:18px;"><strong data-end="949" data-start="935">Матеріали:</strong> </span><span style="font-size:14px;">робоча частина виготовлена зі сталі з антипригарним покриттям для рівномірного нагріву й зниження прилипання їжі. Кришка забезпечує контрольований режим приготування під час теплової обробки. Руків&rsquo;я виготовлене з міцного матеріалу, що забезпечує стабільний захват.</span></p> <p data-end="1418" data-is-last-node="" data-is-only-node="" data-start="1217"><span style="font-size:18px;"><strong data-end="1233" data-start="1217">Особливості:</strong> </span><span style="font-size:14px;">сотейник належить до серії Rotisser бренду Fiskars та призначений для універсальних кулінарних задач із комбінованою тепловою обробкою продуктів на плиті.</span></p> | AE32: Сотейник Fiskars Rotisser 26 см з кришкою — кухонний посуд для приготування страв методом смаження, тушкування, випаровування та варіння на плиті з використанням кришки. | AH32: 0 | AI32: 2026-02-22 22:57:25 | AM32: Новий | AN32: Нет | AO32: 7615108000 | AP32: 0 | AQ32: Выкл | AR32: Выкл | AU32: 6424002005957 | AW32: Нет | AX32: Нет
A33: 1001577 | B33: 1001577 | C33: 1001577 | D33: Вила для сіна Fiskars ErgoComfort (1001577) | E33: Вила для сіна Fiskars ErgoComfort (1001577) | F33: Fiskars | G33: FISKARS/Садовий інвентар Fiskars/Вила для саду | H33: 1069.00 | I33: 3299.00 | J33: UAH | K33: Да | L33: =VLOOKUP(C33,Sheet1!$C:$L,10,0) -> Poland | M33: В наявності | O33: https://fiskars-gratis.com.ua/content/images/28/vyla-dlia-sina-ergocomfort-90489817686205_+145949ee90.png | R33: vyla-dlia-sina-ergocomfort | S33: https://fiskars-gratis.com.ua/vyla-dlia-sina-ergocomfort/ | T33: 2026-01-19 15:36:12 | X33: Вила для сіна Fiskars ErgoComfort | AA33: 0 | AB33: 0 | AC33: 3 | AD33: <p data-end="273" data-start="0"><span style="font-size:18px;"><strong data-end="47" data-start="0">Вила для сіна Fiskars ErgoComfort (1001577)</strong> </span><span style="font-size:14px;">&mdash; ручний інструмент для роботи з легкими об&rsquo;ємними матеріалами у сільському господарстві та на присадибних ділянках. Використовуються для підхоплення, перевертання та переміщення сіна, соломи, сухої трави й подібної органіки.</span></p> <p data-end="452" data-start="275"><span style="font-size:18px;"><strong data-end="291" data-start="275">Призначення:</strong></span><span style="font-size:14px;"> підходять для заготівлі та розподілу сіна, прибирання сухих рослинних залишків, формування скирти, догляду за тваринницькими приміщеннями та складськими зонами.</span></p> <p data-end="625" data-start="454"><span style="font-size:18px;"><strong data-end="470" data-start="454">Конструкція:</strong></span><span style="font-size:14px;"> подовжений держак дозволяє працювати у вертикальному положенні. Кілька довгих зубців оптимізовані для захоплення великого об&rsquo;єму матеріалу без ущільнення.</span></p> <p data-end="775" data-start="627"><span style="font-size:18px;"><strong data-end="641" data-start="627">Матеріали:</strong></span><span style="font-size:14px;"> робоча частина виготовлена зі сталі, стійкої до згинання при регулярних навантаженнях. Руків&rsquo;я адаптоване для тривалої ручної роботи.</span></p> <p data-end="950" data-is-last-node="" data-is-only-node="" data-start="777"><span style="font-size:18px;"><strong data-end="793" data-start="777">Особливості:</strong></span><span style="font-size:14px;"> інструмент належить до серії ErgoComfort бренду Fiskars та призначений для систематичного використання в господарських умовах.</span></p> <div id="gtx-trans" style="position: absolute; left: 150px; top: 57.5px;"> <div class="gtx-trans-icon">&nbsp;</div> </div> | AE33: Вила для сіна Fiskars ErgoComfort - ручний інструмент для роботи з легкими об’ємними матеріалами | AH33: 60 | AI33: 2026-01-19 15:43:14 | AL33: Facebook Feed; Google Feed for Merchant Center | AM33: Новий | AN33: Нет | AO33: 8201 10 00 90 | AP33: 0 | AQ33: Выкл | AR33: Выкл | AU33: 6411503330220 | AW33: Нет | AX33: Нет
A34: 1004814 | B34: 1004814 | C34: 1004814 | D34: Вила садові полегшені Fiskars Ergo (1004814) | E34: Вила садові полегшені Fiskars Ergo (1004814) | F34: Fiskars | G34: FISKARS/Садовий інвентар Fiskars/Вила для саду | H34: 1680.00 | I34: 0.00 | J34: UAH | K34: Да | L34: =VLOOKUP(C34,Sheet1!$C:$L,10,0) -> Poland | M34: В наявності | O34: https://fiskars-gratis.com.ua/content/images/40/vyla-sadovi-polehsheni-fiskars-ergo-1004814-93572176974926_+737ccf4302.jpeg | R34: vyla-sadovi-polehsheni-fiskars-ergo-1004814 | S34: https://fiskars-gratis.com.ua/vyla-sadovi-polehsheni-fiskars-ergo-1004814/ | T34: 2026-02-15 16:41:16 | X34: Вила садові полегшені Fiskars Ergo | AA34: 0 | AB34: 0 | AC34: 4 | AD34: <article data-scroll-anchor="false" data-testid="conversation-turn-1" data-turn="user" data-turn-id="ae4b7823-6345-4f38-b529-7b319f1e5311" dir="auto" tabindex="-1"> <p data-end="294" data-start="0"><span style="font-size:18px;"><strong data-end="48" data-start="0">Вила садові полегшені Fiskars Ergo (1004814)</strong></span><span style="font-size:14px;"> &mdash; ручний садовий інструмент для роботи з ґрунтом і органічними матеріалами на присадибних ділянках. Використовуються для розпушування землі, аерації ґрунту, перекладання компосту, гною, мульчі та рослинних залишків без повного перевертання шару.</span></p> <p data-end="432" data-start="296"><span style="font-size:18px;"><strong data-end="312" data-start="296">Призначення:</strong></span><span style="font-size:14px;"> підходять для догляду за грядками, підготовки ґрунту до посадки, обробки компостних куп, робіт у теплицях і на клумбах.</span></p> <p data-end="630" data-start="434"><span style="font-size:18px;"><strong data-end="450" data-start="434">Конструкція:</strong></span><span style="font-size:14px;"> полегшена форма з ергономічним кутом держака забезпечує контроль рухів і зручне положення тіла під час ручної роботи. Зубці розраховані на проникнення в ґрунт середньої щільності.</span></p> <p data-end="788" data-start="632"><span style="font-size:18px;"><strong data-end="646" data-start="632">Матеріали:</strong></span><span style="font-size:14px;"> робоча частина виготовлена з міцної сталі, стійкої до деформації при регулярних навантаженнях. Руків&rsquo;я адаптоване для тривалого використання.</span></p> <p data-end="961" data-is-last-node="" data-is-only-node="" data-start="790"><span style="font-size:18px;"><strong data-end="806" data-start="790">Особливості:</strong></span><span style="font-size:14px;"> інструмент належить до серії Ergo бренду Fiskars та орієнтований на сезонні садові роботи з помірним фізичним навантаженням.</span></p> </article> | AE34: Вила садові полегшені Fiskars Ergo – це садовий інструмент для переміщення ґрунту, листя, компосту та інших сипких матеріалів | AH34: 60 | AI34: 2026-02-15 17:27:39 | AL34: Facebook Feed; Google Feed for Merchant Center | AM34: Новий | AN34: Нет | AO34: 8201 10 00 90 | AP34: 0 | AQ34: Выкл | AR34: Выкл | AU34: 5702261122037 | AW34: Нет | AX34: Нет
A35: 1070715 | B35: 1070715 | C35: 1070715 | D35: Вила садові Fiskars White (1070715) | E35: Вила садові Fiskars White (1070715) | F35: Fiskars | G35: FISKARS/Садовий інвентар Fiskars/Вила для саду | H35: 2099.00 | I35: 0.00 | J35: UAH | K35: Да | L35: =VLOOKUP(C35,Sheet1!$C:$L,10,0) -> Poland | M35: Немає в наявності | O35: https://fiskars-gratis.com.ua/content/images/26/vyla-sadovi-white-62686653962191_+c46fc2327b.jpg | P35: https://fiskars-gratis.com.ua/content/images/26/vyla-sadovi-white-60988540014067_+db5cb4a77e.jpg; https://fiskars-gratis.com.ua/content/images/26/vyla-sadovi-white-66385483801039_+784208e76a.jpg; https://fiskars-gratis.com.ua/content/images/26/vyla-sadovi-white-37934782281539_+d2210a176a.jpg | R35: vyla-sadovi-white | S35: https://fiskars-gratis.com.ua/vyla-sadovi-white/ | T35: 2026-01-19 15:36:12 | X35: Вила садові Fiskars White | AA35: 0 | AB35: 0 | AC35: 0 | AD35: <p data-end="240" data-start="0"><span style="font-size:18px;"><strong data-end="39" data-start="0">Вила садові Fiskars White (1070715)</strong> </span><span style="font-size:14px;">&mdash; ручний садовий інструмент, призначений для розпушування ґрунту, перекопування грядок і переміщення органічних матеріалів. Використовується під час догляду за городом, садом і присадибними ділянками.</span></p> <p data-end="442" data-start="242"><span style="font-size:18px;"><strong data-end="258" data-start="242">Призначення:</strong></span><span style="font-size:14px;"> підходять для аерації ґрунту, підняття та перевертання землі, роботи з компостом, перегноєм, гноєм, мульчею, а також для збирання рослинних залишків після обрізки або збирання врожаю.</span></p> <p data-end="659" data-start="444"><span style="font-size:18px;"><strong data-end="460" data-start="444">Конструкція:</strong></span><span style="font-size:14px;"> кілька міцних загострених зубців забезпечують рівномірне проникнення в ґрунт і зручне підхоплення матеріалу. Подовжений держак дозволяє працювати у вертикальному положенні з контрольованим зусиллям.</span></p> <p data-end="798" data-start="661"><span style="font-size:18px;"><strong data-end="675" data-start="661">Матеріали:</strong></span><span style="font-size:14px;"> робоча частина виготовлена зі сталі, стійкої до навантажень і деформацій. Держак оптимізований для тривалої ручної роботи.</span></p> <p data-end="948" data-is-last-node="" data-is-only-node="" data-start="800"><span style="font-size:18px;"><strong data-end="816" data-start="800">Особливості:</strong></span><span style="font-size:14px;"> інструмент належить до лінійки White бренду Fiskars та орієнтований на регулярне садове використання.</span></p> | AE35: Вила садові Fiskars White - ручний садовий інструмент, призначений для розпушування ґрунту, перекопування грядок і переміщення органічних матеріалів | AH35: 60 | AI35: 2026-01-19 15:36:32 | AL35: Facebook Feed; Google Feed for Merchant Center | AM35: Новий | AN35: Нет | AO35: 8201 10 00 90 | AP35: 0 | AQ35: Выкл | AR35: Выкл | AU35: 6411501705631 | AW35: Нет | AX35: Нет
A36: 1011570 | B36: 1011570 | C36: 1011570 | D36: Вила для компосту Fiskars пластикові (1011570) | E36: Вила для компосту Fiskars пластикові (1011570) | F36: Fiskars | G36: FISKARS/Садовий інвентар Fiskars/Вила для саду | H36: 349.00 | I36: 0.00 | J36: UAH | K36: Да | L36: =VLOOKUP(C36,Sheet1!$C:$L,10,0) -> Poland | M36: В наявності | O36: https://fiskars-gratis.com.ua/content/images/39/vyla-dlia-kompostu-fiskars-plastykovi-1011570-47215227791569_+49c9b09729.jpg | R36: vyla-dlia-kompostu-fiskars-plastykovi-1011570 | S36: https://fiskars-gratis.com.ua/vyla-dlia-kompostu-fiskars-plastykovi-1011570/ | T36: 2026-02-15 16:41:16 | X36: Вила для компосту Fiskars пластикові | AA36: 0 | AB36: 0 | AC36: 6 | AD36: <p data-end="252" data-start="0"><span style="font-size:18px;"><strong data-end="50" data-start="0">Вила для компосту Fiskars пластикові (1011570)</strong></span><span style="font-size:14px;"> &mdash; ручний садовий інструмент для роботи з легкими органічними матеріалами. Використовуються для перемішування, аерації та переміщення компосту, мульчі, листя, скошеної трави та інших рослинних залишків.</span></p> <p data-end="448" data-start="254"><span style="font-size:18px;"><strong data-end="270" data-start="254">Призначення:</strong></span><span style="font-size:14px;"> підходять для догляду за компостними купами, рівномірного перемішування органіки під час дозрівання, розподілу мульчі на грядках, а також для прибирання легких садових відходів.</span></p> <p data-end="654" data-start="450"><span style="font-size:18px;"><strong data-end="466" data-start="450">Конструкція:</strong> </span><span style="font-size:14px;">кілька широких зубців забезпечують захоплення об&rsquo;ємних, але нещільних матеріалів без їх подрібнення. Подовжений держак дозволяє працювати у вертикальному положенні з контрольованим рухом.</span></p> <p data-end="810" data-start="656"><span style="font-size:18px;"><strong data-end="670" data-start="656">Матеріали:</strong></span><span style="font-size:14px;"> робоча частина виготовлена з міцного пластику, стійкого до вологи та органічних середовищ. Держак адаптований для регулярної ручної роботи.</span></p> <p data-end="970" data-is-last-node="" data-is-only-node="" data-start="812"><span style="font-size:18px;"><strong data-end="828" data-start="812">Особливості:</strong></span><span style="font-size:14px;"> інструмент розроблений брендом Fiskars для побутового садового використання під час сезонних робіт з органікою.</span></p> | AH36: 60 | AI36: 2026-02-15 17:21:03 | AL36: Facebook Feed; Google Feed for Merchant Center | AM36: Новий | AN36: Нет | AO36: 8201 10 00 90 | AP36: 0 | AQ36: Выкл | AR36: Выкл | AU36: 7317791500019 | AW36: Нет | AX36: Нет
A37: 1014810 | B37: 1014810 | C37: 1014810 | D37: Вила короткі Fiskars Solid (1014810) | E37: Вила короткі Fiskars Solid (1014810) | F37: Fiskars | G37: FISKARS/Садовий інвентар Fiskars/Вила для саду | H37: 649.00 | I37: 1199.00 | J37: UAH | K37: Да | L37: =VLOOKUP(C37,Sheet1!$C:$L,10,0) -> Poland | M37: В наявності | O37: https://fiskars-gratis.com.ua/content/images/27/vyla-korotki-solid-30245336963469_+61b3f9a06d.jpeg | R37: vyla-korotki-solid | S37: https://fiskars-gratis.com.ua/vyla-korotki-solid/ | T37: 2026-01-19 15:36:12 | X37: Вила короткі Fiskars Solid | AA37: 0 | AB37: 0 | AC37: 3 | AD37: <p data-end="255" data-start="0"><span style="font-size:18px;"><strong data-end="40" data-start="0">Вила короткі Fiskars Solid (1014810)</strong> </span><span style="font-size:14px;">&mdash; компактний ручний садовий інструмент для локальних робіт із ґрунтом та органічними матеріалами. Використовуються для розпушування землі в обмеженому просторі, роботи на грядках, у теплицях, контейнерах і клумбах.</span></p> <p data-end="428" data-start="257"><span style="font-size:18px;"><strong data-end="273" data-start="257">Призначення:</strong></span><span style="font-size:14px;"> підходять для аерації ґрунту, підняття та переміщення компосту, мульчі, перегною, рослинних залишків, а також для догляду за посадками на невеликій площі.</span></p> <p data-end="625" data-start="430"><span style="font-size:18px;"><strong data-end="446" data-start="430">Конструкція:</strong> </span><span style="font-size:14px;">короткий держак забезпечує точний контроль інструмента та зручну роботу однією або двома руками. Загострені зубці дозволяють легко входити в ґрунт і підхоплювати сипкі матеріали.</span></p> <p data-end="759" data-start="627"><span style="font-size:18px;"><strong data-end="641" data-start="627">Матеріали:</strong></span><span style="font-size:14px;"> робоча частина виготовлена зі сталі, стійкої до механічних навантажень. Держак адаптований до тривалої ручної роботи.</span></p> <p data-end="926" data-is-last-node="" data-is-only-node="" data-start="761"><span style="font-size:18px;"><strong data-end="777" data-start="761">Особливості:</strong></span><span style="font-size:14px;"> інструмент належить до серії Solid бренду Fiskars і розрахований на регулярне використання в побутових садових умовах.</span></p> | AE37: Вила короткі Fiskars Solid для локальних робіт із ґрунтом та органічними матеріалами для розпушування землі в обмеженому просторі, роботи на грядках, у теплицях, контейнерах і клумбах | AH37: 60 | AI37: 2026-01-19 15:37:00 | AL37: Facebook Feed; Google Feed for Merchant Center | AM37: Новий | AN37: Нет | AO37: 8201 10 00 90 | AP37: 0 | AQ37: Выкл | AR37: Выкл | AU37: 6411501334244 | AW37: Нет | AX37: Нет
A38: 1001553 | B38: 1001553 | C38: 1001553 | D38: Гілкоріз площинний із загнутим лезом Fiskars PowerGear L76 (1001553) | E38: Гілкоріз площинний із загнутим лезом Fiskars PowerGear L76 (1001553) | F38: Fiskars | G38: FISKARS/Садовий інвентар Fiskars/Гілкорізи | H38: 1699.00 | I38: 3299.00 | J38: UAH | K38: Да | L38: =VLOOKUP(C38,Sheet1!$C:$L,10,0) -> Poland | M38: В наявності | O38: https://fiskars-gratis.com.ua/content/images/5/hilkoriz-ploshchynnyi-iz-zahnutym-lezom-fiskars-powergear-l76-1001553-41850968687303_+a0e0f8cd43.jpg; https://fiskars-gratis.com.ua/content/images/5/hilkoriz-ploshchynnyi-iz-zahnutym-lezom-fiskars-powergear-l76-1001553-25024222887881_+ee7c4b2b58.jpg | R38: hilkoriz-ploshchynnyi-iz-zahnutym-lezom-fiskars-powergear-l76-1001553 | S38: https://fiskars-gratis.com.ua/hilkoriz-ploshchynnyi-iz-zahnutym-lezom-fiskars-powergear-l76-1001553/ | T38: 2026-02-13 19:49:41 | X38: Гілкоріз площинний із загнутим лезом Fiskars PowerGear L76 | Z38: Хіт | AA38: 0 | AB38: 0 | AC38: 34 | AD38: <article data-scroll-anchor="false" data-testid="conversation-turn-37" data-turn="user" data-turn-id="30adf650-c68e-44d1-b1af-31030448f206" dir="auto" tabindex="-1"><span style="font-size: 18px;"><strong data-end="72" data-start="0">Гілкоріз площинний із загнутим лезом Fiskars PowerGear L76 (1001553)</strong></span><span style="font-size: 14px;"> &mdash; ручний садовий інструмент з довгими ручками для обрізання та видалення гілок на висоті й у важкодоступних місцях. Використовується для формування крони дерев і кущів, проріджування насаджень, зрізання сухих і живих гілок середнього діаметру без застосування драбини.</span></article> <article data-scroll-anchor="true" data-testid="conversation-turn-38" data-turn="assistant" data-turn-id="request-WEB:b3f4340d-c2c6-4e86-a74b-1bce73fc80d0-18" dir="auto" tabindex="-1"> <p data-end="547" data-start="343"><span style="font-size:18px;"><strong data-end="359" data-start="343">Призначення:</strong> </span><span style="font-size:14px;">підходить для догляду за деревними і кущовими рослинами на присадибних ділянках, ландшафтних масивах і у великих садових зонах, де потрібно обрізати гілки над головою або вгору по висоті.</span></p> <p data-end="803" data-start="549"><span style="font-size:18px;"><strong data-end="565" data-start="549">Конструкція:</strong></span><span style="font-size:14px;"> загнуте ріжуче лезо забезпечує кращий контакт із гілкою та сприяє чистому зрізу під кутом. Довгі ручки створюють важіль для докладання зусиль при роботі на висоті або з товстішими гілками. Ергономічна форма руків&rsquo;я сприяє контролю рухів.</span></p> <p data-end="975" data-start="805"><span style="font-size:18px;"><strong data-end="819" data-start="805">Матеріали:</strong></span><span style="font-size:14px;"> леза виготовлені зі сталі, стійкої до механічного зношування та корозії при регулярному використанні. Руків&rsquo;я розраховане на інтенсивну ручну експлуатацію.</span></p> <p data-end="1190" data-is-last-node="" data-is-only-node="" data-start="977"><span style="font-size:18px;"><strong data-end="993" data-start="977">Особливості:</strong></span><span style="font-size:14px;"> інструмент належить до серії PowerGear бренду Fiskars та призначений для систематичного догляду за деревними насадженнями із застосуванням механічної переваги важеля.</span></p> </article> | AE38: Гілкоріз площинний із загнутим лезом Fiskars PowerGear L76 — ручний садовий інструмент з довгими ручками для обрізання та видалення гілок на висоті й у важкодоступних місцях. | AH38: 24 | AI38: 2026-02-15 15:00:18 | AM38: Новий | AN38: Нет | AO38: 8201 50 00 00 | AP38: 0 | AQ38: Выкл | AR38: Выкл | AU38: 6411501123008 | AW38: Нет | AX38: Нет
A39: 1027528 | B39: 1027528 | C39: 1027528 | D39: Гілкоріз площинний телескопічний Fiskars Solid L13 (1027528) | E39: Гілкоріз площинний телескопічний Fiskars Solid L13 (1027528) | F39: Fiskars | G39: FISKARS/Садовий інвентар Fiskars/Гілкорізи | H39: 2300.00 | I39: 0.00 | J39: UAH | K39: Да | L39: =VLOOKUP(C39,Sheet1!$C:$L,10,0) -> China | M39: Немає в наявності | O39: https://fiskars-gratis.com.ua/content/images/3/hilkoriz-ploshchynnyi-teleskopichnyi-fiskars-solid-l13-35773768022595_+e04fe55b4f.jpg; https://fiskars-gratis.com.ua/content/images/3/hilkoriz-ploshchynnyi-teleskopichnyi-fiskars-solid-l13-70456469269564_+d577bc798a.jpg | R39: hilkoriz-ploshchynnyi-teleskopichnyi-fiskars-solid-l13 | S39: https://fiskars-gratis.com.ua/hilkoriz-ploshchynnyi-teleskopichnyi-fiskars-solid-l13/ | T39: 2026-02-13 19:49:41 | X39: Гілкоріз площинний телескопічний Fiskars Solid L13 | Z39: Хіт | AA39: 0 | AB39: 0 | AC39: 0 | AD39: <p data-end="286" data-start="0"><span style="font-size:18px;"><strong data-end="54" data-start="0">Гілкоріз площинний телескопічний Fiskars Solid L13 (1027528)</strong> </span><span style="font-size:14px;">&mdash; ручний садовий інструмент з подовжувальними ручками для обрізання та видалення гілок на різній висоті. Використовується для догляду за деревами та кущами, зрізання сухих і живих гілок середнього діаметру без застосування драбини.</span></p> <p data-end="478" data-start="288"><span style="font-size:18px;"><strong data-end="304" data-start="288">Призначення:</strong> </span><span style="font-size:14px;">підходить для формування крони, проріджування гілок, підтримки здоров&rsquo;я дерев і чагарників на присадибних ділянках та в ландшафтних масивах, де потрібне обрізання на висоті.</span></p> <p data-end="728" data-start="480"><span style="font-size:18px;"><strong data-end="496" data-start="480">Конструкція:</strong></span><span style="font-size:14px;"> площинні леза забезпечують чистий зріз гілок. Телескопічні ручки дозволяють регулювати довжину інструмента для роботи на різній висоті без додаткових пристроїв. Ручки створюють необхідний важіль для докладання зусиль при обрізанні.</span></p> <p data-end="911" data-start="730"><span style="font-size:18px;"><strong data-end="744" data-start="730">Матеріали:</strong> </span><span style="font-size:14px;">леза виготовлені зі сталі, стійкої до зношування та корозії при регулярному використанні. Подовжувальні ручки забезпечують жорсткість і контроль рухів під час роботи.</span></p> <p data-end="1096" data-is-last-node="" data-is-only-node="" data-start="913"><span style="font-size:18px;"><strong data-end="929" data-start="913">Особливості:</strong> </span><span style="font-size:14px;">інструмент належить до серії Solid бренду Fiskars та призначений для систематичного догляду за деревними насадженнями на різних висотах.</span></p> | AE39: Гілкоріз площинний телескопічний Fiskars Solid L13 — ручний садовий інструмент з подовжувальними ручками для обрізання та видалення гілок на різній висоті. | AH39: 24 | AI39: 2026-02-15 14:47:46 | AM39: Новий | AN39: Нет | AO39: 8201 50 00 00 | AP39: 0 | AQ39: Выкл | AR39: Выкл | AU39: 6411501150370 | AW39: Нет | AX39: Нет
A40: 1026930 | B40: 1026930 | C40: 1026930 | D40: Гілкоріз Fiskars White L32 (1026930) | E40: Гілкоріз Fiskars White L32 (1026930) | F40: Fiskars | G40: FISKARS/Садовий інвентар Fiskars/Гілкорізи | H40: 2699.00 | I40: 0.00 | J40: UAH | K40: Да | L40: =VLOOKUP(C40,Sheet1!$C:$L,10,0) -> Poland | M40: В наявності | O40: https://fiskars-gratis.com.ua/content/images/4/hilkoriz-fiskars-white-l32-1026930-92647425246952_+3548994504.jpeg; https://fiskars-gratis.com.ua/content/images/4/hilkoriz-fiskars-white-l32-1026930-88148517336668_+e2edb540b2.jpeg; https://fiskars-gratis.com.ua/content/images/4/hilkoriz-fiskars-white-l32-1026930-44166924168142_+0f097f2324.jpeg | R40: hilkoriz-fiskars-white-l32-1026930 | S40: https://fiskars-gratis.com.ua/hilkoriz-fiskars-white-l32-1026930/ | T40: 2026-02-13 19:49:41 | X40: Гілкоріз Fiskars White L32 | Z40: Хіт | AA40: 0 | AB40: 0 | AC40: 89 | AD40: <article data-scroll-anchor="false" data-testid="conversation-turn-35" data-turn="user" data-turn-id="392ebe67-deb5-4d37-b046-bfb74b775311" dir="auto" tabindex="-1"><span style="font-size: 18px;"><strong data-end="40" data-start="0">Гілкоріз Fiskars White L32 (1026930)</strong> </span><span style="font-size: 14px;">&mdash; ручний садовий інструмент з подовженими ручками для обрізання та видалення гілок на середній висоті. Використовується для догляду за деревами й чагарниками, зрізання сухих і живих гілок середнього діаметру, формування крони та проріджування насаджень.</span></article> <article data-scroll-anchor="true" data-testid="conversation-turn-36" data-turn="assistant" data-turn-id="request-WEB:b3f4340d-c2c6-4e86-a74b-1bce73fc80d0-17" dir="auto" tabindex="-1"> <p data-end="487" data-start="296"><span style="font-size:18px;"><strong data-end="312" data-start="296">Призначення:</strong></span><span style="font-size:14px;"> підходить для садово-городніх робіт із догляду за деревними і кущовими рослинами, де потрібне обрізання гілок над рівнем плечей без застосування додаткових підйомних засобів.</span></p> <p data-end="714" data-start="489"><span style="font-size:18px;"><strong data-end="505" data-start="489">Конструкція:</strong> </span><span style="font-size:14px;">подовжені ручки створюють важіль для докладання зусиль при зрізанні гілок, а площинні ріжучі леза забезпечують чистий зріз. Руків&rsquo;я оптимальної довжини дозволяє працювати у більш розпрямленому положенні тіла.</span></p> <p data-end="884" data-start="716"><span style="font-size:18px;"><strong data-end="730" data-start="716">Матеріали:</strong> </span><span style="font-size:14px;">леза виготовлені зі сталі, стійкої до корозії та механічного зношування при регулярному використанні. Руків&rsquo;я адаптоване для тривалого ручного утримання.</span></p> <p data-end="1055" data-is-last-node="" data-is-only-node="" data-start="886"><span style="font-size:18px;"><strong data-end="902" data-start="886">Особливості:</strong></span><span style="font-size:14px;"> інструмент належить до серії White бренду Fiskars та призначений для догляду за деревними насадженнями середнього розміру.</span></p> </article> | AE40: Гілкоріз Fiskars White L32 — ручний садовий інструмент з подовженими ручками для обрізання та видалення гілок на середній висоті. | AH40: 24 | AI40: 2026-02-15 14:49:22 | AL40: Facebook Feed; Google Feed for Merchant Center | AM40: Новий | AN40: Нет | AO40: 8201 50 00 00 | AP40: 0 | AQ40: Выкл | AR40: Выкл | AU40: 6411501150196 | AW40: Нет | AX40: Нет
A41: 1073084 | B41: 1073084 | C41: 1073084 | D41: Гілкоріз телескопічний Fiskars UPN86 (1073084) | E41: Гілкоріз телескопічний Fiskars UPN86 (1073084) | F41: Гілкоріз телескопічний Fiskars UPN86 (1073084) | G41: FISKARS/Садовий інвентар Fiskars/Гілкорізи | H41: 5999.00 | I41: 7399.00 | J41: UAH | K41: Да | L41: =VLOOKUP(C41,Sheet1!$C:$L,10,0) -> Poland | M41: Немає в наявності | O41: https://fiskars-gratis.com.ua/content/images/50/hilkoriz-teleskopichnyi-fiskars-upn86-1073084-76659777716621_+c5315c786b.jpeg; https://fiskars-gratis.com.ua/content/images/50/hilkoriz-teleskopichnyi-fiskars-upn86-1073084-40450020290400_+76bb3eae67.jpeg; https://fiskars-gratis.com.ua/content/images/50/hilkoriz-teleskopichnyi-fiskars-upn86-1073084-77189696288292_+fe44eca32c.jpeg; https://fiskars-gratis.com.ua/content/images/50/hilkoriz-teleskopichnyi-fiskars-upn86-1073084-20220072350857_+10a493f5a9.jpeg; https://fiskars-gratis.com.ua/content/images/50/hilkoriz-teleskopichnyi-fiskars-upn86-1073084-80020308171186_+5bd1691d96.jpeg | R41: hilkoriz-teleskopichnyi-fiskars-upn86-1073084 | S41: https://fiskars-gratis.com.ua/hilkoriz-teleskopichnyi-fiskars-upn86-1073084/ | T41: 2026-03-13 00:57:52 | X41: Гілкоріз телескопічний Fiskars UPN86 | AA41: 0 | AB41: 0 | AC41: 0 | AD41: <p data-end="319" data-start="0"><span style="font-size:18px;"><strong data-end="80" data-start="0">Гілкоріз телескопічний Fiskars UPN86 (1073084)</strong> </span><span style="font-size:14px;">&mdash; садовий інструмент для обрізання гілок дерев і кущів на висоті без використання драбини. Використовується для догляду за кроною дерев, формування декоративних рослин і видалення сухих або зайвих гілок у саду чи на присадибній ділянці.</span></p> <p data-end="588" data-start="321"><span style="font-size:18px;"><strong data-end="337" data-start="321">Призначення:</strong></span><span style="font-size:14px;"> підходить для обрізання свіжих гілок дерев і кущів товщиною до <strong data-end="410" data-start="401">32 мм</strong>, зокрема у важкодоступних місцях або на значній висоті. Телескопічна конструкція дозволяє працювати із землею, не піднімаючись на висоту.</span></p> <p data-end="900" data-start="590"><span style="font-size:18px;"><strong data-end="606" data-start="590">Конструкція:</strong> </span><span style="font-size:14px;">інструмент оснащений телескопічною штангою з регулюванням довжини приблизно <strong data-end="701" data-start="683">від 2,2 до 4 м</strong>, що забезпечує робочу висоту обрізання до <strong data-end="759" data-start="744">близько 6 м</strong>. Ріжуча головка може повертатися до <strong data-end="804" data-start="796">230&deg;</strong>, що дозволяє виконувати точні зрізи під різними кутами.</span></p> <p data-end="1165" data-start="902"><span style="font-size:18px;"><strong data-end="916" data-start="902">Матеріали:</strong></span><span style="font-size:14px;"> леза виготовлені з високоякісної загартованої сталі для довготривалої гостроти та чистого зрізу. Телескопічна штанга виконана з легкого та міцного алюмінію, стійкого до погодних умов і механічних навантажень.</span></p> <p data-end="1514" data-start="1167"><span style="font-size:18px;"><strong data-end="1183" data-start="1167">Особливості:</strong></span><span style="font-size:14px;"> механізм обрізання забезпечує ефективну передачу зусилля для різання товстих гілок, а конструкція дозволяє працювати як на висоті, так і на рівні землі без нахилів або зайвого фізичного навантаження. Інструмент також сумісний з додатковими насадками, такими як садова пилка або плодознімач</span></p> | AE41: Гілкоріз телескопічний Fiskars UPN86 — садовий інструмент для обрізання гілок дерев і кущів на висоті без використання драбини. Використовується для догляду за кроною дерев, формування декоративних рослин і видалення сухих або зайвих гілок у саду чи на присадибній ділянці. | AH41: 24 | AI41: 2026-03-13 01:00:19 | AM41: Новий | AN41: Нет | AO41: 8201 50 00 00 | AP41: 0 | AQ41: Выкл | AR41: Выкл | AU41: 6411501600899 | AW41: Нет | AX41: Нет
A42: 1056927 | B42: 1056927 | C42: 1056927 | D42: Набір Fiskars мітла дворова М + Граблі Solid (1056927) | E42: Набір Fiskars мітла дворова М + Граблі Solid (1056927) | F42: Fiskars | G42: FISKARS/Садовий інвентар Fiskars/Граблі для саду | H42: 1199.00 | I42: 1699.00 | J42: UAH | K42: Да | L42: =VLOOKUP(C42,Sheet1!$C:$L,10,0) -> Poland | M42: В наявності | O42: https://fiskars-gratis.com.ua/content/images/30/nabir-fiskars-mitla-dvorova-m-hrabli-solid-1056927-82433085609314_+55060e055c.jpg | R42: nabir-fiskars-mitla-dvorova-m-hrabli-solid-1056927 | S42: https://fiskars-gratis.com.ua/nabir-fiskars-mitla-dvorova-m-hrabli-solid-1056927/ | T42: 2026-02-14 16:10:44 | X42: Набір Fiskars мітла дворова М + Граблі Solid | AA42: 0 | AB42: 0 | AC42: 4 | AD42: <p data-end="283" data-start="0"><span style="font-size:18px;"><strong data-end="58" data-start="0">Набір Fiskars мітла дворова М + граблі Solid (1056927)</strong> </span><span style="font-size:14px;">&mdash; комплект ручних інструментів для прибирання двору, саду та присадибної ділянки. Складається з дворoвої мітли середнього розміру та граблів, призначених для збору сміття, листя і рослинних залишків та вирівнювання поверхні.</span></p> <p data-end="562" data-start="285"><span style="font-size:18px;"><strong data-end="301" data-start="285">Призначення:</strong></span><span style="font-size:14px;"> підходить для очищення твердих поверхонь (доріжки, тераси, майданчики), газонів і садових зон від листя, трав&rsquo;яних обрізків, сміття та іншого органічного матеріалу. Також використовується для легкого вирівнювання ґрунту та підготовки ділянки до сезонних робіт.</span></p> <p data-end="894" data-start="564"><span style="font-size:18px;"><strong data-end="580" data-start="564">Конструкція:</strong></span><span style="font-size:14px;"> дворова мітла має широкі щетини для ефективного збирання дрібного сміття і листя за кілька проходів. Граблі оснащені зубцями для збору рослинних залишків і вирівнювання поверхні ґрунту. Ручки інструментів оптимальної довжини адаптовані для роботи у вертикальному положенні з контрольованим навантаженням на спину.</span></p> <p data-end="1122" data-start="896"><span style="font-size:18px;"><strong data-end="910" data-start="896">Матеріали:</strong> </span><span style="font-size:14px;">щетина мітли виготовлена з міцного синтетичного матеріалу, стійкого до стирання. Робочі частини граблів &mdash; зі сталі, що витримує механічні навантаження. Руків&rsquo;я забезпечують надійний захват під час ручної роботи.</span></p> <p data-end="1318" data-is-last-node="" data-is-only-node="" data-start="1124"><span style="font-size:18px;"><strong data-end="1140" data-start="1124">Особливості:</strong></span><span style="font-size:14px;"> набір належить до серії Solid бренду Fiskars та призначений для систематичного прибирання та догляду за прибудинковою територією і садовими зонами.</span></p> | AE42: Набір Fiskars мітла дворова М + граблі Solid — комплект ручних інструментів для прибирання двору, саду та присадибної ділянки | AH42: 24 | AI42: 2026-02-16 20:51:58 | AL42: Facebook Feed; Google Feed for Merchant Center | AM42: Новий | AN42: Нет | AO42: 8201 10 00 90 | AP42: 0 | AQ42: Выкл | AR42: Выкл | AU42: 6411501311252 | AW42: Нет | AX42: Нет
A43: 1000660 | B43: 1000660 | C43: 1000660 | D43: Граблі для листя Fiskars Ergonomic XL (1000660) | E43: Граблі для листя Fiskars Ergonomic XL (1000660) | F43: Fiskars | G43: FISKARS/Садовий інвентар Fiskars/Граблі для саду | H43: 1228.00 | I43: 0.00 | J43: UAH | K43: Да | L43: =VLOOKUP(C43,Sheet1!$C:$L,10,0) -> Poland | M43: В наявності | O43: https://fiskars-gratis.com.ua/content/images/27/hrabli-dlia-lystia-fiskars-ergonomic-xl-1000660-38160386573897_+c708c18211.jpg | R43: hrabli-dlia-lystia-fiskars-ergonomic-xl-1000660 | S43: https://fiskars-gratis.com.ua/hrabli-dlia-lystia-fiskars-ergonomic-xl-1000660/ | T43: 2026-02-14 16:10:43 | X43: Граблі для листя Fiskars Ergonomic XL | AA43: 0 | AB43: 0 | AC43: 3 | AD43: <p data-end="305" data-start="0"><span style="font-size:18px;"><strong data-end="51" data-start="0">Граблі для листя Fiskars Ergonomic XL (1000660)</strong></span><span style="font-size:14px;"> &mdash; ручний садовий інструмент для збору опалого листя, трави, молодих бур&rsquo;янів та легкого сміття на присадибних ділянках, газонах і міжряддях. Використовуються для очищення поверхні ґрунту, упорядкування зелених зон і підготовки ділянок до сезонних робіт.</span></p> <p data-end="496" data-start="307"><span style="font-size:18px;"><strong data-end="323" data-start="307">Призначення:</strong> </span><span style="font-size:14px;">підходять для збору сухого та вологого листя, рослинних залишків після стрижки трави, а також для вирівнювання верхнього шару ґрунту в декоративних і садово‑городніх зонах.</span></p> <p data-end="793" data-start="498"><span style="font-size:18px;"><strong data-end="514" data-start="498">Конструкція:</strong></span><span style="font-size:14px;"> широкі робочі зубці грабель забезпечують великий захват матеріалу за один прохід, а ергономічна телескопічна ручка дозволяє регулювати довжину для роботи у звичному вертикальному положенні. Спеціальна форма руків&rsquo;я знижує навантаження на зап&rsquo;ястя під час тривалого використання.</span></p> <p data-end="1011" data-start="795"><span style="font-size:18px;"><strong data-end="809" data-start="795">Матеріали:</strong></span><span style="font-size:14px;"> робочі частини виготовлені з міцних матеріалів, стійких до механічного зношування і деформацій при роботі з листям і травою. Руків&rsquo;я адаптоване для комфортного захвату і контролю під час ручної роботи.</span></p> <p data-end="1210" data-is-last-node="" data-is-only-node="" data-start="1013"><span style="font-size:18px;"><strong data-end="1029" data-start="1013">Особливості:</strong></span><span style="font-size:14px;"> інструмент належить до серії Ergonomic бренду Fiskars та призначений для систематичного прибирання листя й рослинних залишків на присадибних ділянках.</span></p> | AE43: Граблі для листя Fiskars Ergonomic XL — ручний садовий інструмент для збору опалого листя, трави, молодих бур’янів та легкого сміття на присадибних ділянках, газонах і міжряддях | AH43: 24 | AI43: 2026-02-15 21:37:04 | AL43: Google Feed for Merchant Center; Facebook Feed | AM43: Новий | AN43: Нет | AO43: 8201 10 00 90 | AP43: 0 | AQ43: Выкл | AR43: Выкл | AU43: 5905561335705 | AW43: Нет | AX43: Нет
A44: 1024720 | B44: 1024720 | C44: 1024720 | D44: Граблі Fiskars Solid (1024720) | E44: Граблі Fiskars Solid (1024720) | F44: Fiskars | G44: FISKARS/Садовий інвентар Fiskars/Граблі для саду | H44: 1377.00 | I44: 0.00 | J44: UAH | K44: Да | L44: =VLOOKUP(C44,Sheet1!$C:$L,10,0) -> Poland | M44: В наявності | O44: https://fiskars-gratis.com.ua/content/images/29/hrabli-fiskars-solid-1024720-46645498261926_+f3e1a2f52e.jpg | R44: hrabli-fiskars-solid-1024720 | S44: https://fiskars-gratis.com.ua/hrabli-fiskars-solid-1024720/ | T44: 2026-02-14 16:10:44 | X44: Граблі Fiskars Solid | AA44: 0 | AB44: 0 | AC44: 4 | AD44: <p data-end="299" data-start="0"><span style="font-size:18px;"><strong data-end="34" data-start="0">Граблі Fiskars Solid (1024720)</strong> </span><span style="font-size:14px;">&mdash; ручний садовий інструмент для обробки поверхні ґрунту та збору рослинних залишків на присадибних ділянках і в садово‑городніх зонах. Використовуються для вирівнювання ґрунту, розпушування легкого верхнього шару, збору листя, трав&rsquo;яних обрізків і дрібного сміття.</span></p> <p data-end="526" data-start="301"><span style="font-size:18px;"><strong data-end="317" data-start="301">Призначення:</strong></span><span style="font-size:14px;"> підходять для догляду за газонами, грядками, квітниками й іншими зелениими зонами, де потрібне акуратне вирівнювання ґрунту перед посадкою чи після робіт, а також збір рослинних залишків після сезонних робіт.</span></p> <p data-end="796" data-start="528"><span style="font-size:18px;"><strong data-end="544" data-start="528">Конструкція:</strong></span><span style="font-size:14px;"> робочі зубці грабель розташовані на широкій планці для великого захвату матеріалу за один прохід і рівномірного розподілу посівного чи мульчувального матеріалу. Руків&rsquo;я стандартної довжини забезпечує зручний вертикальний робочий стан і контроль рухів.</span></p> <p data-end="1021" data-start="798"><span style="font-size:18px;"><strong data-end="812" data-start="798">Матеріали:</strong></span><span style="font-size:14px;"> робочі елементи виготовлені зі сталі або іншого жорсткого матеріалу, стійкого до механічного зношування при регулярному використанні. Руків&rsquo;я адаптоване для надійного захвату й контролю під час ручної роботи.</span></p> <p data-end="1234" data-is-last-node="" data-is-only-node="" data-start="1023"><span style="font-size:18px;"><strong data-end="1039" data-start="1023">Особливості:</strong> </span><span style="font-size:14px;">інструмент належить до серії Solid бренду Fiskars та призначений для систематичних садових і господарських робіт із обробки ґрунту та прибирання рослинних залишків.</span></p> | AE44: Граблі Fiskars Solid — ручний садовий інструмент для обробки поверхні ґрунту та збору рослинних залишків на присадибних ділянках і в садово‑городніх зонах. | AH44: 24 | AI44: 2026-02-16 20:51:42 | AL44: Facebook Feed; Google Feed for Merchant Center | AM44: Новий | AN44: Нет | AO44: 8201 10 00 90 | AP44: 0 | AQ44: Выкл | AR44: Выкл | AU44: 6411501330048 | AW44: Нет | AX44: Нет
A45: 1023492 | B45: 1023492 | C45: 1023492 | D45: Граблі великі для листя Fiskars М помаранчеві (1023492) | E45: Граблі великі для листя Fiskars М помаранчеві (1023492) | F45: Fiskars | G45: FISKARS/Садовий інвентар Fiskars/Граблі для саду | H45: 1400.00 | I45: 0.00 | J45: UAH | K45: Да | L45: =VLOOKUP(C45,Sheet1!$C:$L,10,0) -> Finland | M45: В наявності | O45: https://fiskars-gratis.com.ua/content/images/28/hrabli-velyki-dlia-lystia-fiskars-m-pomaranchevi-1023492-98820689201740_+9388495fc8.jpg; https://fiskars-gratis.com.ua/content/images/28/hrabli-velyki-dlia-lystia-fiskars-m-pomaranchevi-1023492-98601955629513_+cc461c8e2f.jpg | R45: hrabli-velyki-dlia-lystia-fiskars-m-pomaranchevi-1023492 | S45: https://fiskars-gratis.com.ua/hrabli-velyki-dlia-lystia-fiskars-m-pomaranchevi-1023492/ | T45: 2026-02-14 16:10:44 | X45: Граблі великі для листя Fiskars М помаранчеві | AA45: 0 | AB45: 0 | AC45: 1 | AD45: <p data-end="338" data-start="0"><span style="font-size:18px;"><strong data-end="59" data-start="0">Граблі великі для листя Fiskars M помаранчеві (1023492)</strong> </span><span style="font-size:14px;">&mdash; ручний садовий інструмент для збору опалого листя, трав&rsquo;яних залишків і легкого органічного сміття на присадибних ділянках, газонах, міжряддях і квітниках. Використовуються для очищення поверхні ґрунту від рослинних відходів та полегшення підготовки ділянок до сезонних робіт.</span></p> <p data-end="552" data-start="340"><span style="font-size:18px;"><strong data-end="356" data-start="340">Призначення:</strong> </span><span style="font-size:14px;">підходять для очищення сухого та вологого листя, трав&rsquo;яних обрізків після стрижки газону, а також для вирівнювання верхнього шару ґрунту у декоративних і садово‑городніх зонах середнього розміру.</span></p> <p data-end="832" data-start="554"><span style="font-size:18px;"><strong data-end="570" data-start="554">Конструкція:</strong> </span><span style="font-size:14px;">широке робоче полотно з гнучкими зубцями забезпечує великий захват матеріалу за один прохід. Помірна довжина ручки дозволяє працювати у зручному вертикальному положенні, а оптимальна ширина забезпечує ефективне прибирання листя з мінімальною кількістю проходів.</span></p> <p data-end="1056" data-start="834"><span style="font-size:18px;"><strong data-end="848" data-start="834">Матеріали:</strong> </span><span style="font-size:14px;">робочі частини виготовлені з міцних матеріалів, стійких до механічного зношування та деформації при контакті з рослинними залишками. Руків&rsquo;я адаптоване для надійного захвату і контролю під час ручної роботи.</span></p> <p data-end="1241" data-is-last-node="" data-is-only-node="" data-start="1058"><span style="font-size:18px;"><strong data-end="1074" data-start="1058">Особливості:</strong></span><span style="font-size:14px;"> інструмент вироблений брендом Fiskars та призначений для регулярного збору листя й рослинних відходів на присадибних ділянках і газонах.</span></p> | AE45: Граблі великі для листя Fiskars M помаранчеві — ручний садовий інструмент для збору опалого листя, трав’яних залишків і легкого органічного сміття на присадибних ділянках, газонах, міжряддях і квітниках. | AH45: 24 | AI45: 2026-02-16 20:51:32 | AL45: Facebook Feed; Google Feed for Merchant Center | AM45: Новий | AN45: Нет | AO45: 8201 10 00 90 | AP45: 0 | AQ45: Выкл | AR45: Выкл | AU45: 6411501350282 | AW45: Нет | AX45: Нет
A46: 1011611 | B46: 1011611 | C46: 1011611 | D46: Граблі для листя Fiskars Prima FSC (1011611) | E46: Граблі для листя Fiskars Prima FSC (1011611) | F46: Fiskars | G46: FISKARS/Садовий інвентар Fiskars/Граблі для саду | H46: 1600.00 | I46: 0.00 | J46: UAH | K46: Да | L46: =VLOOKUP(C46,Sheet1!$C:$L,10,0) -> Poland | M46: В наявності | O46: https://fiskars-gratis.com.ua/content/images/33/hrabli-dlia-lystia-fiskars-prima-fsc-1011611-71858912883553_+7120b776c5.jpeg | R46: hrabli-dlia-lystia-fiskars-prima-fsc-1011611 | S46: https://fiskars-gratis.com.ua/hrabli-dlia-lystia-fiskars-prima-fsc-1011611/ | T46: 2026-02-14 16:10:44 | X46: Граблі для листя Fiskars Prima FSC | AA46: 0 | AB46: 0 | AC46: 4 | AD46: <p data-end="317" data-start="0"><span style="font-size:18px;"><strong data-end="48" data-start="0">Граблі для листя Fiskars Prima FSC (1011611)</strong></span><span style="font-size:14px;"> &mdash; ручний садовий інструмент для прибирання опалого листя, трав&rsquo;яних обрізків і легкого рослинного сміття на присадибних ділянках, газонах і міжряддях. Використовуються для очищення поверхні ґрунту від листя та підготовки ділянок до сезонних робіт із садом або газоном.</span></p> <p data-end="508" data-start="319"><span style="font-size:18px;"><strong data-end="335" data-start="319">Призначення:</strong> </span><span style="font-size:14px;">підходять для збору сухого та вологого листя, трав&rsquo;яних залишків і дрібного органічного сміття у садових і паркових зонах, де потрібне регулярне прибирання поверхні ґрунту.</span></p> <p data-end="763" data-start="510"><span style="font-size:18px;"><strong data-end="526" data-start="510">Конструкція:</strong></span><span style="font-size:14px;"> широке робоче полотно з гнучкими зубцями забезпечує великий захват матеріалу за один прохід. Руків&rsquo;я оптимальної довжини дозволяє працювати у зручному вертикальному положенні, а форма руків&rsquo;я сприяє контролю рухів під час ручної роботи.</span></p> <p data-end="1020" data-start="765"><span style="font-size:18px;"><strong data-end="779" data-start="765">Матеріали:</strong></span><span style="font-size:14px;"> робочі елементи виготовлені з міцних матеріалів, стійких до механічного зношування при роботі з листям та рослинними залишками. Руків&rsquo;я виготовлене з сертифікованої деревини FSC, що підтверджує відповідальне використання природних ресурсів.</span></p> <p data-end="1216" data-is-last-node="" data-is-only-node="" data-start="1022"><span style="font-size:18px;"><strong data-end="1038" data-start="1022">Особливості:</strong></span><span style="font-size:14px;"> інструмент належить до серії Prima бренду Fiskars та призначений для систематичного прибирання листя й органічних залишків на присадибних ділянках.</span></p> | AE46: Граблі для листя Fiskars Prima FSC — ручний садовий інструмент для прибирання опалого листя, трав’яних обрізків і легкого рослинного сміття на присадибних ділянках, газонах і міжряддях. | AH46: 24 | AI46: 2026-02-16 20:52:39 | AL46: Facebook Feed; Google Feed for Merchant Center | AM46: Новий | AN46: Нет | AO46: 8201 10 00 90 | AP46: 0 | AQ46: Выкл | AR46: Выкл | AU46: 7317796551702 | AW46: Нет | AX46: Нет
A47: 1014828 | B47: 1014828 | C47: 1014828 | D47: Граблі для грунту FISKARS PARK FSC (1014828) | E47: Граблі для грунту FISKARS PARK FSC (1014828) | F47: Fiskars | G47: FISKARS/Садовий інвентар Fiskars/Граблі для саду | H47: 1749.00 | I47: 0.00 | J47: UAH | K47: Да | L47: =VLOOKUP(C47,Sheet1!$C:$L,10,0) -> Poland | M47: В наявності | O47: https://fiskars-gratis.com.ua/content/images/34/hrabli-dlia-hruntu-fiskars-park-fsc-1014828-69518233867227_+5a3fe0eb7a.png | P47: https://fiskars-gratis.com.ua/content/images/34/hrabli-dlia-hruntu-fiskars-park-fsc-1014828-12996443831099_+7e4669c0b9.png | R47: hrabli-dlia-hruntu-fiskars-park-fsc-1014828 | S47: https://fiskars-gratis.com.ua/hrabli-dlia-hruntu-fiskars-park-fsc-1014828/ | T47: 2026-02-14 16:10:44 | X47: Граблі для грунту FISKARS PARK FSC | AA47: 0 | AB47: 0 | AC47: 14 | AD47: <p data-end="353" data-start="0"><span style="font-size:18px;"><strong data-end="48" data-start="0">Граблі для ґрунту Fiskars Park FSC (1014828)</strong></span><span style="font-size:14px;"> &mdash; ручний садовий інструмент для підготовки та обробки ґрунту в присадибних ділянках, грядках, клумбах і декоративних зонах. Використовуються для розпушування верхнього шару ґрунту, вирівнювання поверхні, видалення бур&rsquo;янів і перемішування органічних компонентів перед посадкою рослин чи доглядом за ними.</span></p> <p data-end="602" data-start="355"><span style="font-size:18px;"><strong data-end="371" data-start="355">Призначення:</strong> </span><span style="font-size:14px;">підходять для роботи з ґрунтом у декоративних і овочевих насадженнях, забезпечення аерації кореневої зони рослин, підготовки грядок до висаджування розсади чи насіння, а також для видалення бур&rsquo;янів і вирівнювання поверхні ґрунту.</span></p> <p data-end="877" data-start="604"><span style="font-size:18px;"><strong data-end="620" data-start="604">Конструкція:</strong></span><span style="font-size:14px;"> робоча частина оснащена зубцями, що дозволяють акуратно та ефективно розпушувати ґрунт та захоплювати рослинні залишки під час обробки. Руків&rsquo;я стандартної довжини забезпечує зручний вертикальний робочий стан і контроль рухів під час ручної обробки ґрунту.</span></p> <p data-end="1154" data-start="879"><span style="font-size:18px;"><strong data-end="893" data-start="879">Матеріали:</strong></span><span style="font-size:14px;"> робочі елементи виготовлені з матеріалів, стійких до механічного зношування при регулярному використанні. Руків&rsquo;я виконано з сертифікованої деревини FSC, що підтверджує відповідальне використання природних ресурсів, і забезпечує надійний захват під час роботи.</span></p> <p data-end="1329" data-is-last-node="" data-is-only-node="" data-start="1156"><span style="font-size:18px;"><strong data-end="1172" data-start="1156">Особливості:</strong> </span><span style="font-size:14px;">інструмент належить до серії Park бренду Fiskars та призначений для систематичної обробки ґрунту і догляду за садовими зонами.</span></p> | AE47: Граблі для ґрунту Fiskars Park FSC — ручний садовий інструмент для підготовки та обробки ґрунту в присадибних ділянках, грядках, клумбах і декоративних зонах. | AH47: 24 | AI47: 2026-02-16 20:52:50 | AL47: Google Feed for Merchant Center; Facebook Feed | AM47: Новий | AN47: Нет | AO47: 8201 10 00 90 | AP47: 0 | AQ47: Выкл | AR47: Выкл | AU47: 6411501663368 | AW47: Нет | AX47: Нет
A48: 1001587 | B48: 1001587 | C48: 1001587 | D48: Граблі для грунту універсальні Fiskars FSC (1001587) | E48: Граблі для грунту універсальні Fiskars FSC (1001587) | F48: Fiskars | G48: FISKARS/Садовий інвентар Fiskars/Граблі для саду | H48: 799.00 | I48: 2500.00 | J48: UAH | K48: Да | L48: =VLOOKUP(C48,Sheet1!$C:$L,10,0) -> Poland | M48: В наявності | O48: https://fiskars-gratis.com.ua/content/images/32/hrabli-dlia-hruntu-universalni-fiskars-fsc-1001587-14393508411534_+89c2a58089.jpg | R48: hrabli-dlia-hruntu-universalni-fiskars-fsc-1001587 | S48: https://fiskars-gratis.com.ua/hrabli-dlia-hruntu-universalni-fiskars-fsc-1001587/ | T48: 2026-02-14 16:10:44 | X48: Граблі для грунту універсальні Fiskars FSC | AA48: 0 | AB48: 0 | AC48: 3 | AD48: <article data-scroll-anchor="false" data-testid="conversation-turn-141" data-turn="user" data-turn-id="e4546236-afac-48e7-82c2-c99b178ea779" dir="auto" tabindex="-1">&nbsp;</article> <article data-scroll-anchor="true" data-testid="conversation-turn-142" data-turn="assistant" data-turn-id="request-699321d5-8138-832e-b944-980a5aec2874-9" dir="auto" tabindex="-1"> <p data-end="343" data-start="0"><span style="font-size:18px;"><strong data-end="56" data-start="0">Граблі для ґрунту універсальні Fiskars FSC (1001587)</strong></span><span style="font-size:14px;"> &mdash; ручний садовий інструмент для розпушування, вирівнювання та підготовки ґрунту на присадибних ділянках, грядках і клумбах. Використовуються для розпушування верхнього шару ґрунту перед посадкою, вирівнювання поверхні, видалення бур&rsquo;янів і перемішування органічних компонентів у ґрунті.</span></p> <p data-end="583" data-start="345"><span style="font-size:18px;"><strong data-end="361" data-start="345">Призначення:</strong></span><span style="font-size:14px;"> підходять для обробки ґрунту у декоративних і овочевих насадженнях, забезпечення аерації кореневої зони рослин, підготовки грядок до висаджування розсади або насіння, а також для контролю бур&rsquo;янів у верхньому шарі ґрунту.</span></p> <p data-end="820" data-start="585"><span style="font-size:18px;"><strong data-end="601" data-start="585">Конструкція:</strong> </span><span style="font-size:14px;">робоча частина з оптимально розташованими зубцями забезпечує ефективне захоплення та розпушування ґрунту. Руків&rsquo;я стандартної довжини дозволяє працювати у вертикальному положенні з контрольованим навантаженням на тіло.</span></p> <p data-end="1043" data-start="822"><span style="font-size:18px;"><strong data-end="836" data-start="822">Матеріали:</strong> </span><span style="font-size:14px;">робочі елементи виготовлені зі сталі або міцного матеріалу, стійкого до механічного зношування при регулярному використанні. Руків&rsquo;я адаптоване для надійного захвату та контролю рухів під час ручної роботи.</span></p> <p data-end="1255" data-is-last-node="" data-is-only-node="" data-start="1045"><span style="font-size:18px;"><strong data-end="1061" data-start="1045">Особливості:</strong></span><span style="font-size:14px;"> інструмент вироблений із сертифікованої деревини FSC і належить до серії бренду Fiskars, призначений для широкого спектра ґрунтообробних задач у саду та на городі.</span></p> </article> | AE48: Граблі для ґрунту універсальні Fiskars FSC — ручний садовий інструмент для розпушування, вирівнювання та підготовки ґрунту на присадибних ділянках, грядках і клумбах. | AH48: 24 | AI48: 2026-02-16 20:52:23 | AL48: Facebook Feed; Google Feed for Merchant Center | AM48: Новий | AN48: Нет | AO48: 8201 10 00 90 | AP48: 0 | AQ48: Выкл | AR48: Выкл | AU48: 6411503474016 | AW48: Нет | AX48: Нет
A49: 1019608 | B49: 1019608 | C49: 1019608 | D49: Граблі для ґрунту полегшені Fiskars White (1019608) | E49: Граблі для ґрунту полегшені Fiskars White (1019608) | F49: Fiskars | G49: FISKARS/Садовий інвентар Fiskars/Граблі для саду | H49: 899.00 | I49: 1399.00 | J49: UAH | K49: Да | L49: =VLOOKUP(C49,Sheet1!$C:$L,10,0) -> Poland | M49: Немає в наявності | O49: https://fiskars-gratis.com.ua/content/images/31/hrabli-dlia-gruntu-polehsheni-fiskars-white-1019608-39495851024710_+1cf62f0792.jpg; https://fiskars-gratis.com.ua/content/images/31/hrabli-dlia-gruntu-polehsheni-fiskars-white-1019608-52188291701506_+842c24c07c.jpg | R49: hrabli-dlia-gruntu-polehsheni-fiskars-white-1019608 | S49: https://fiskars-gratis.com.ua/hrabli-dlia-gruntu-polehsheni-fiskars-white-1019608/ | T49: 2026-02-14 16:10:44 | X49: Граблі для ґрунту полегшені Fiskars White | AA49: 0 | AB49: 0 | AC49: 0 | AD49: <p data-end="339" data-start="0"><span style="font-size:18px;"><strong data-end="55" data-start="0">Граблі для ґрунту полегшені Fiskars White (1019608)</strong></span><span style="font-size:14px;"> &mdash; ручний садовий інструмент для підготовки та догляду за ґрунтом на присадибних ділянках, у грядках і клумбах. Використовуються для розпушування поверхневого шару ґрунту, вирівнювання поверхні, видалення бур&rsquo;янів і перемішування органічних компонентів перед або після посадки рослин.</span></p> <p data-end="542" data-start="341"><span style="font-size:18px;"><strong data-end="357" data-start="341">Призначення:</strong> </span><span style="font-size:14px;">підходять для обробки верхнього шару ґрунту, аерації кореневої зони рослин, вирівнювання і розпушування ґрунту навколо садових і декоративних насаджень, а також для видалення бур&rsquo;янів.</span></p> <p data-end="816" data-start="544"><span style="font-size:18px;"><strong data-end="560" data-start="544">Конструкція:</strong> </span><span style="font-size:14px;">інструмент оснащений широкою робочою частиною з гнучкими зубцями, що дозволяють ефективно захоплювати ґрунт і рослинні залишки під час одного проходу. Полегшена конструкція забезпечує зниження фізичного навантаження під час тривалого ручного використання.</span></p> <p data-end="1000" data-start="818"><span style="font-size:18px;"><strong data-end="832" data-start="818">Матеріали:</strong></span><span style="font-size:14px;"> робочі зубці виготовлені з міцного матеріалу, стійкого до механічного зношування. Руків&rsquo;я адаптоване для комфортного захвату і контролю рухів під час роботи з ґрунтом.</span></p> <p data-end="1192" data-is-last-node="" data-is-only-node="" data-start="1002"><span style="font-size:18px;"><strong data-end="1018" data-start="1002">Особливості:</strong> </span><span style="font-size:14px;">інструмент належить до серії White бренду Fiskars та призначений для систематичного догляду за ґрунтом і підготовки поверхні до посадки рослин.</span></p> | AE49: Граблі для ґрунту полегшені Fiskars White — ручний садовий інструмент для підготовки та догляду за ґрунтом на присадибних ділянках, у грядках і клумбах. | AH49: 24 | AI49: 2026-02-16 20:52:13 | AL49: Facebook Feed; Google Feed for Merchant Center | AM49: Новий | AN49: Нет | AO49: 8201 10 00 90 | AP49: 0 | AQ49: Выкл | AR49: Выкл | AU49: 6411501355232 | AW49: Нет | AX49: Нет
A50: 1027215 | B50: 1027215 | C50: 1027215 | D50: Болторіз Fiskars PowerGear 76см (1027215) | E50: Болторіз Fiskars PowerGear 76см (1027215) | F50: Fiskars | G50: FISKARS/Садовий інвентар Fiskars/Інструменти для дому | H50: 1699.00 | I50: 8399.00 | J50: UAH | K50: Да | L50: =VLOOKUP(C50,Sheet1!$C:$L,10,0) -> China | M50: В наявності | O50: https://fiskars-gratis.com.ua/content/images/17/boltoriz-fiskars-powergear-76sm-1027215-41556772701657_+16b2cb2dc0.jpg; https://fiskars-gratis.com.ua/content/images/17/boltoriz-fiskars-powergear-76sm-1027215-51157309778454_+ca981619a9.jpg; https://fiskars-gratis.com.ua/content/images/17/boltoriz-fiskars-powergear-76sm-1027215-18914892771798_+e24a5a7770.jpg; https://fiskars-gratis.com.ua/content/images/17/boltoriz-fiskars-powergear-76sm-1027215-95255167378896_+242a899585.jpg | R50: boltoriz-fiskars-powergear-76sm-1027215 | S50: https://fiskars-gratis.com.ua/boltoriz-fiskars-powergear-76sm-1027215/ | T50: 2026-02-14 12:26:23 | X50: Болторіз Fiskars PowerGear 76 см | AA50: 0 | AB50: 0 | AC50: 3 | AD50: <p data-end="354" data-start="0"><span style="font-size:18px;"><strong data-end="46" data-start="0">Болторіз Fiskars PowerGear 76 см (1027215)</strong></span><span style="font-size:14px;"> &mdash; ручний інструмент для перерізання металевих елементів у господарських, ремонтних і монтажних роботах. Використовується для обрізання дроту, болтів, гвинтів, арматури невеликого та середнього перерізу, замків, ланцюгів і інших металевих деталей, коли застосування електроінструменту недоцільне чи обмежене.</span></p> <p data-end="550" data-start="356"><span style="font-size:18px;"><strong data-end="372" data-start="356">Призначення:</strong></span><span style="font-size:14px;"> підходить для демонтажу металевих компонентів, догляду за огорожами, розбирання конструкцій, ремонтних задач і інших операцій, що потребують контролю над різанням металу вручну.</span></p> <p data-end="825" data-start="552"><span style="font-size:18px;"><strong data-end="568" data-start="552">Конструкція:</strong> </span><span style="font-size:14px;">болторіз оснащений довгими рукоятками (&asymp; 76 см) для механічної переваги важеля, що зменшує необхідне зусилля при перерізанні твердих металевих елементів. Ріжучі головки мають оптимальний кут і форму для ефективного контакту з матеріалом під час розрізання.</span></p> <p data-end="1053" data-start="827"><span style="font-size:18px;"><strong data-end="841" data-start="827">Матеріали:</strong></span><span style="font-size:14px;"> головки інструмента виготовлені зі сталі, стійкої до механічного зношування і деформацій при роботі з металом. Руків&rsquo;я обладнане ергономічними накладками для стабільного захвату і контролю рухів під час різання.</span></p> <p data-end="1251" data-is-last-node="" data-is-only-node="" data-start="1055"><span style="font-size:18px;"><strong data-end="1071" data-start="1055">Особливості:</strong></span><span style="font-size:14px;"> інструмент належить до серії PowerGear бренду Fiskars та призначений для ручного перерізання металевих елементів із мінімальними фізичними затратами.</span></p> | AE50: Болторіз Fiskars PowerGear 76 см — ручний інструмент для перерізання металевих елементів у господарських, ремонтних і монтажних роботах. | AH50: 24 | AI50: 2026-02-16 20:49:57 | AL50: Facebook Feed; Google Feed for Merchant Center | AM50: Новий | AN50: Нет | AO50: 8201 50 00 00 | AP50: 0 | AQ50: Выкл | AR50: Выкл | AU50: 6411501701336 | AW50: Нет | AX50: Нет
A51: 1027216 | B51: 1027216 | C51: 1027216 | D51: Болторіз Fiskars PowerGear 91см (1027216) | E51: Болторіз Fiskars PowerGear 91см (1027216) | F51: Fiskars | G51: FISKARS/Садовий інвентар Fiskars/Інструменти для дому | H51: 1799.00 | I51: 10499.00 | J51: UAH | K51: Да | L51: =VLOOKUP(C51,Sheet1!$C:$L,10,0) -> China | M51: Немає в наявності | O51: https://fiskars-gratis.com.ua/content/images/16/boltoriz-fiskars-powergear-91sm-1027216-76365900175027_+fb3ebd6634.jpg; https://fiskars-gratis.com.ua/content/images/16/boltoriz-fiskars-powergear-91sm-1027216-68416312739354_+a19bae1ebf.jpg; https://fiskars-gratis.com.ua/content/images/16/boltoriz-fiskars-powergear-91sm-1027216-33902044235741_+00d3406cea.jpg; https://fiskars-gratis.com.ua/content/images/16/boltoriz-fiskars-powergear-91sm-1027216-44528046384945_+438aadfd72.jpg | R51: boltoriz-fiskars-powergear-91sm-1027216 | S51: https://fiskars-gratis.com.ua/boltoriz-fiskars-powergear-91sm-1027216/ | T51: 2026-02-14 12:26:23 | X51: Болторіз Fiskars PowerGear 91 см | AA51: 0 | AB51: 0 | AC51: 0 | AD51: <p data-end="418" data-start="0"><span style="font-size:18px;"><strong data-end="46" data-start="0">Болторіз Fiskars PowerGear 91 см (1027216)</strong></span><span style="font-size:14px;"> &mdash; ручний садово-господарський інструмент для перерізання металевих елементів, таких як болти, гайки, дріт, ланцюги і замки середнього та великого діаметру, коли використання електроінструменту недоцільне або неможливе. Використовується для демонтажу конструкцій, ремонтних робіт, догляду за огорожами та інших завдань, що потребують контролю над потужним різанням металу.</span></p> <p data-end="605" data-start="420"><span style="font-size:18px;"><strong data-end="436" data-start="420">Призначення:</strong> </span><span style="font-size:14px;">підходить для обрізання металевого дроту, болтів, гвинтів, арматури невеликого перерізу, замків і металевих крепежів під час господарських, ремонтних і монтажних робіт.</span></p> <p data-end="890" data-start="607"><span style="font-size:18px;"><strong data-end="623" data-start="607">Конструкція:</strong></span><span style="font-size:14px;"> інструмент має довгі рукоятки (~91 см) для створення механічної переваги важеля, що зменшує фізичне зусилля при перерізанні твердих металевих елементів. Ріжучі головки з високою міцністю забезпечують контакт із матеріалом під оптимальним кутом для ефективного зрізу.</span></p> <p data-end="1109" data-start="892"><span style="font-size:18px;"><strong data-end="906" data-start="892">Матеріали:</strong> </span><span style="font-size:14px;">головки болторіза виготовлені зі сталі, стійкої до механічного зношування і деформацій при роботі з металом. Руків&rsquo;я оснащене ергономічними накладками для зручності утримання і контролю під час різання.</span></p> <p data-end="1322" data-is-last-node="" data-is-only-node="" data-start="1111"><span style="font-size:18px;"><strong data-end="1127" data-start="1111">Особливості:</strong> </span><span style="font-size:14px;">інструмент належить до серії PowerGear бренду Fiskars та призначений для систематичного ручного перерізання металевих елементів із мінімальними фізичними витратами.</span></p> | AE51: Болторіз Fiskars PowerGear 91 см — ручний садово-господарський інструмент для перерізання металевих елементів, таких як болти, гайки, дріт, ланцюги і замки середнього та великого діаметру, коли використання електроінструменту недоцільне або неможливе | AH51: 24 | AI51: 2026-02-16 20:49:38 | AL51: Facebook Feed; Google Feed for Merchant Center | AM51: Новий | AN51: Нет | AO51: 8201 50 00 00 | AP51: 0 | AQ51: Выкл | AR51: Выкл | AU51: 6411501701343 | AW51: Нет | AX51: Нет
A52: 1061193 | B52: 1061193 | C52: 1061193 | D52: Ніж складаний Fiskars CarbonMax (1061193) | E52: Ніж складаний Fiskars CarbonMax (1061193) | F52: Fiskars | G52: FISKARS/Садовий інвентар Fiskars/Інструменти для дому | H52: 1949.00 | I52: 0.00 | J52: UAH | K52: Да | L52: =VLOOKUP(C52,Sheet1!$C:$L,10,0) -> China | M52: В наявності | O52: https://fiskars-gratis.com.ua/content/images/13/nizh-skladanyi-fiskars-carbonmax-1061193-67692062142256_+1f8cb32340.jpg; https://fiskars-gratis.com.ua/content/images/13/nizh-skladanyi-fiskars-carbonmax-1061193-89970678101857_+272ad4fb94.jpg; https://fiskars-gratis.com.ua/content/images/13/nizh-skladanyi-fiskars-carbonmax-1061193-72791732924194_+c5498e5760.jpg | R52: nizh-skladanyi-fiskars-carbonmax-1061193 | S52: https://fiskars-gratis.com.ua/nizh-skladanyi-fiskars-carbonmax-1061193/ | T52: 2026-02-14 12:26:23 | X52: Ніж складаний Fiskars CarbonMax | AA52: 0 | AB52: 0 | AC52: 120 | AD52: <p data-end="395" data-start="0"><span style="font-size:18px;"><strong data-end="45" data-start="0">Ніж складаний Fiskars CarbonMax (1061193)</strong> </span><span style="font-size:14px;">&mdash; ручний багатофункціональний інструмент із складаним лезом для щоденного використання у побуті, на природі та під час подорожей. Використовується для розрізання різноманітних матеріалів &mdash; мотузок, пакувальних матеріалів, текстилю, харчових продуктів, дрібних гілок і загальних допоміжних робіт, де потрібен гострий та компактний ріжучий інструмент.</span></p> <p data-end="577" data-start="397"><span style="font-size:18px;"><strong data-end="413" data-start="397">Призначення:</strong></span><span style="font-size:14px;"> підходить для кемпінгу, походів, господарських задач, ремонтних операцій, підготовки продуктів і розпакування, де потрібен надійний складаний ніж із гострим лезом.</span></p> <p data-end="821" data-start="579"><span style="font-size:18px;"><strong data-end="595" data-start="579">Конструкція:</strong> </span><span style="font-size:14px;">складане лезо фіксується у відкритому положенні для безпечної роботи. Ергономічна руків&rsquo;я забезпечує зручний захват і контроль під час різання, а механізм складання дозволяє компактно зберігати інструмент у закритому вигляді.</span></p> <p data-end="1054" data-start="823"><span style="font-size:18px;"><strong data-end="837" data-start="823">Матеріали:</strong> </span><span style="font-size:14px;">лезо виготовлене зі сталі з вмістом вуглецю (carbon), що забезпечує гостроту ріжучої кромки та можливість легкої шліфовки. Руків&rsquo;я виготовлене з міцного матеріалу, стійкого до зношування при регулярному використанні.</span></p> <p data-end="1239" data-is-last-node="" data-is-only-node="" data-start="1056"><span style="font-size:18px;"><strong data-end="1072" data-start="1056">Особливості:</strong></span><span style="font-size:14px;"> інструмент належить до серії CarbonMax бренду Fiskars та призначений для широкого спектра різальних задач у польових і побутових умовах.</span></p> | AE52: Ніж складаний Fiskars CarbonMax— ручний багатофункціональний інструмент із складаним лезом для щоденного використання у побуті, на природі та під час подорожей. | AH52: 24 | AI52: 2026-02-16 20:49:10 | AL52: Facebook Feed; Google Feed for Merchant Center | AM52: Новий | AN52: Нет | AO52: 8203 20 00 00 | AP52: 0 | AQ52: Выкл | AR52: Выкл | AU52: 6411501512185 | AW52: Нет | AX52: Нет
A53: 1061192 | B53: 1061192 | C53: 1061192 | D53: Ніж з висувним лезом Fiskars CarbonMax (1061192) | E53: Ніж з висувним лезом Fiskars CarbonMax (1061192) | F53: Fiskars | G53: FISKARS/Садовий інвентар Fiskars/Інструменти для дому | H53: 1949.00 | I53: 0.00 | J53: UAH | K53: Да | L53: =VLOOKUP(C53,Sheet1!$C:$L,10,0) -> China | M53: В наявності | O53: https://fiskars-gratis.com.ua/content/images/14/nizh-z-vysuvnym-lezom-fiskars-carbonmax-1061192-39961808361976_+e5208f1a2a.jpg; https://fiskars-gratis.com.ua/content/images/14/nizh-z-vysuvnym-lezom-fiskars-carbonmax-1061192-21226067212976_+81afb821af.jpg | R53: nizh-z-vysuvnym-lezom-fiskars-carbonmax-1061192 | S53: https://fiskars-gratis.com.ua/nizh-z-vysuvnym-lezom-fiskars-carbonmax-1061192/ | T53: 2026-02-14 12:26:23 | X53: Ніж з висувним лезом Fiskars CarbonMax | AA53: 0 | AB53: 0 | AC53: 6 | AD53: <article data-scroll-anchor="false" data-testid="conversation-turn-105" data-turn="user" data-turn-id="6c9bf924-f15d-4f4c-a329-7ca15cfdaa47" dir="auto" tabindex="-1">&nbsp;</article> <article data-scroll-anchor="true" data-testid="conversation-turn-106" data-turn="assistant" data-turn-id="request-699321d5-8138-832e-b944-980a5aec2874-4" dir="auto" tabindex="-1"> <p data-end="376" data-start="0"><span style="font-size:18px;"><strong data-end="52" data-start="0">Ніж з висувним лезом Fiskars CarbonMax (1061192)</strong> </span><span style="font-size:14px;">&mdash; ручний ріжучий інструмент із висувним лезом, призначений для виконання широкого спектра побутових та допоміжних робіт, де потрібне точне та контрольоване різання. Використовується для розрізання пакувальних матеріалів, картону, мотузок, текстилю, тонких кабелів та інших матеріалів у побуті, на роботі чи під час поїздок.</span></p> <p data-end="558" data-start="378"><span style="font-size:18px;"><strong data-end="394" data-start="378">Призначення:</strong> </span><span style="font-size:14px;">підходить для універсальних різальних задач у домашніх умовах, на дачі, в гаражі або майстерні, де потрібна безпечна, точна та зручна робота з різними матеріалами.</span></p> <p data-end="844" data-start="560"><span style="font-size:18px;"><strong data-end="576" data-start="560">Конструкція:</strong> </span><span style="font-size:14px;">висувне лезо фіксується у робочому положенні за допомогою механізму блокування для безпечної експлуатації. Механізм дозволяє регулювати довжину виступу ріжучої кромки відповідно до завдання. Ергономічна руків&rsquo;я забезпечує комфортний захват і контроль під час різання.</span></p> <p data-end="1070" data-start="846"><span style="font-size:18px;"><strong data-end="860" data-start="846">Матеріали:</strong></span><span style="font-size:14px;"> лезо виготовлене зі сталі з вмістом вуглецю (carbon), що підтримує гостроту ріжучої кромки та полегшує повторне заточування. Корпус і руків&rsquo;я виконані з міцних матеріалів, що витримують регулярне використання.</span></p> <p data-end="1254" data-is-last-node="" data-is-only-node="" data-start="1072"><span style="font-size:18px;"><strong data-end="1088" data-start="1072">Особливості:</strong></span><span style="font-size:14px;"> інструмент належить до серії CarbonMax бренду Fiskars і призначений для універсальних різальних задач із контролем безпеки та точності.</span></p> </article> | AE53: Ніж з висувним лезом Fiskars CarbonMax — ручний ріжучий інструмент із висувним лезом, призначений для виконання широкого спектра побутових та допоміжних робіт, де потрібне точне та контрольоване різання. | AH53: 24 | AI53: 2026-02-16 20:49:19 | AL53: Facebook Feed; Google Feed for Merchant Center | AM53: Новий | AN53: Нет | AO53: 8203 20 00 00 | AP53: 0 | AQ53: Выкл | AR53: Выкл | AU53: 6411501512178 | AW53: Нет | AX53: Нет
A54: 1001622 | B54: 1001622 | C54: 1001622 | D54: Ніж загального призначення K40 Fiskars (1001622) | E54: Ніж загального призначення K40 Fiskars (1001622) | F54: Fiskars | G54: FISKARS/Садовий інвентар Fiskars/Інструменти для дому | H54: 999.00 | I54: 0.00 | J54: UAH | K54: Да | L54: =VLOOKUP(C54,Sheet1!$C:$L,10,0) -> China | M54: В наявності | O54: https://fiskars-gratis.com.ua/content/images/15/nizh-zahalnoho-pryznachennia-k40-fiskars-1001622-38969493694733_+aa39636bec.jpg; https://fiskars-gratis.com.ua/content/images/15/nizh-zahalnoho-pryznachennia-k40-fiskars-1001622-47422005984420_+b641539286.jpg | R54: nizh-zahalnoho-pryznachennia-k40-fiskars-1001622 | S54: https://fiskars-gratis.com.ua/nizh-zahalnoho-pryznachennia-k40-fiskars-1001622/ | T54: 2026-02-14 12:26:23 | X54: Ніж загального призначення K40 Fiskars | AA54: 0 | AB54: 0 | AC54: 149 | AD54: <p data-end="323" data-start="0"><span style="font-size:18px;"><strong data-end="52" data-start="0">Ніж загального призначення K40 Fiskars (1001622)</strong></span><span style="font-size:14px;"> &mdash; ручний різальний інструмент універсального застосування для побутових, господарських і допоміжних задач. Використовується для розрізання пакувальних матеріалів, мотузок, тканин, картону, а також для загальних операцій різання у майстерні, на дачі чи під час подорожей.</span></p> <p data-end="498" data-start="325"><span style="font-size:18px;"><strong data-end="341" data-start="325">Призначення:</strong> </span><span style="font-size:14px;">підходить для щоденних різальних робіт у домашньому побуті, ремонтних і господарських задач, де потрібне надійне та контрольоване різання різних матеріалів.</span></p> <p data-end="692" data-start="500"><span style="font-size:18px;"><strong data-end="516" data-start="500">Конструкція:</strong></span><span style="font-size:14px;"> класичний дизайн ножа з фіксованим лезом забезпечує стабільний та контрольований хід ріжучої кромки. Ергономічна руків&rsquo;я адаптована для зручного захвату і точності при роботі.</span></p> <p data-end="906" data-start="694"><span style="font-size:18px;"><strong data-end="708" data-start="694">Матеріали:</strong> </span><span style="font-size:14px;">ріжуча частина виготовлена зі сталі, що дозволяє підтримувати гостроту кромки та забезпечує тривалий ресурс використання. Руків&rsquo;я виготовлено з міцних матеріалів, стійких до механічного зношування.</span></p> <p data-end="1055" data-is-last-node="" data-is-only-node="" data-start="908"><span style="font-size:18px;"><strong data-end="924" data-start="908">Особливості:</strong> </span><span style="font-size:14px;">інструмент вироблений брендом Fiskars та призначений для широкого спектра загальних різальних задач.</span></p> | AE54: Ніж загального призначення K40 Fiskars— ручний різальний інструмент універсального застосування для побутових, господарських і допоміжних задач. | AH54: 24 | AI54: 2026-02-16 20:49:29 | AL54: Facebook Feed; Google Feed for Merchant Center | AM54: Новий | AN54: Нет | AO54: 8203 20 00 00 | AP54: 0 | AQ54: Выкл | AR54: Выкл | AU54: 6411502870628 | AW54: Нет | AX54: Нет
A55: 1066715 | B55: 1066715 | C55: 1066715 | D55: Лопата туристична Fiskars Solid Metal (1066715) | E55: Лопата туристична Fiskars Solid Metal (1066715) | F55: Fiskars | G55: FISKARS/Садовий інвентар Fiskars/Лопати садові | H55: 1199.00 | I55: 0.00 | J55: UAH | K55: Да | L55: =VLOOKUP(C55,Sheet1!$C:$L,10,0) -> Poland | M55: В наявності | N55: FISKARS/Садовий інвентар Fiskars | O55: https://fiskars-gratis.com.ua/content/images/24/lopata-turystychna-solid-metal-92481688276251_+1dd47097eb.jpg | P55: https://fiskars-gratis.com.ua/content/images/24/lopata-turystychna-solid-metal-38348334293020_+adfab19384.jpg | R55: lopata-turystychna-solid-metal | S55: https://fiskars-gratis.com.ua/lopata-turystychna-solid-metal/ | T55: 2026-01-19 15:23:35 | X55: Лопата туристична Fiskars Solid Metal | Z55: Хіт | AA55: 0 | AB55: 0 | AC55: 2 | AD55: <p data-end="332" data-start="0"><span style="font-size:18px;"><strong data-end="51" data-start="0">Лопата туристична Fiskars Solid Metal (1066715)</strong> </span><span style="font-size:14px;">&mdash; компактний ручний інструмент для виконання допоміжних земляних робіт у похідних та польових умовах. Використовується для копання м&rsquo;якого й середньощільного ґрунту, підготовки місця під намет, облаштування вогнища, дренажних канавок та санітарних ям під час подорожей і кемпінгу.</span></p> <p data-end="467" data-start="334"><span style="font-size:18px;"><strong data-end="350" data-start="334">Призначення:</strong></span><span style="font-size:14px;"> підходить для туристичних походів, автомобільних подорожей, риболовлі, кемпінгу та аварійного використання в дорозі.</span></p> <p data-end="672" data-start="469"><span style="font-size:18px;"><strong data-end="485" data-start="469">Конструкція:</strong></span><span style="font-size:14px;"> суцільнометалева компактна форма поєднує лезо та держак в єдину конструкцію, що підвищує жорсткість і контроль під час роботи. Зменшені габарити зручні для транспортування та зберігання.</span></p> <p data-end="824" data-start="674"><span style="font-size:18px;"><strong data-end="688" data-start="674">Матеріали:</strong></span><span style="font-size:14px;"> інструмент виготовлений зі сталі, стійкої до механічних навантажень і вологи, що забезпечує надійність при змінних умовах експлуатації.</span></p> <p data-end="1001" data-is-last-node="" data-is-only-node="" data-start="826"><span style="font-size:18px;"><strong data-end="842" data-start="826">Особливості:</strong></span><span style="font-size:14px;"> лопата належить до серії Solid Metal бренду Fiskars та розрахована на регулярне використання в туристичних і польових сценаріях.</span></p> | AE55: Лопата туристична Fiskars Solid Metal — компактний ручний інструмент для виконання допоміжних земляних робіт у похідних та польових умовах. | AH55: 60 | AI55: 2026-01-19 15:25:06 | AM55: Новий | AN55: Нет | AO55: 8201 10 00 90 | AP55: 0 | AQ55: Выкл | AR55: Выкл | AU55: 6411501311825 | AW55: Нет | AX55: Нет
A56: 1066716 | B56: 1066716 | C56: 1066716 | D56: Лопата штикова Fiskars Solid (1066716) | E56: Лопата штикова Fiskars Solid (1066716) | F56: Fiskars | G56: FISKARS/Садовий інвентар Fiskars/Лопати садові | H56: 1299.00 | I56: 0.00 | J56: UAH | K56: Да | L56: =VLOOKUP(C56,Sheet1!$C:$L,10,0) -> Poland | M56: В наявності | O56: https://fiskars-gratis.com.ua/content/images/25/lopata-metaleva-shtykova-solid-f-30193213527913_+c5a51c1118.jpg; https://fiskars-gratis.com.ua/content/images/25/lopata-metaleva-shtykova-solid-f-51057855491450_+09d941eea0.jpg; https://fiskars-gratis.com.ua/content/images/25/lopata-metaleva-shtykova-solid-f-31067983264225_+7e56af4dcb.jpg | P56: https://fiskars-gratis.com.ua/content/images/25/lopata-metaleva-shtykova-solid-f-19043015980887_+d5fe7262ca.jpg; https://fiskars-gratis.com.ua/content/images/25/lopata-metaleva-shtykova-solid-f-65300994722293_+c85142b97c.jpg; https://fiskars-gratis.com.ua/content/images/25/lopata-metaleva-shtykova-solid-f-90786615442320_+e1514b37dc.jpg | R56: lopata-metaleva-shtykova-solid-f | S56: https://fiskars-gratis.com.ua/lopata-metaleva-shtykova-solid-f/ | T56: 2026-01-19 15:23:35 | X56: Лопата штикова Fiskars Solid | Z56: Хіт | AA56: 0 | AB56: 0 | AC56: 2 | AD56: <p data-end="264" data-start="0"><span style="font-size:18px;"><strong data-end="42" data-start="0">Лопата штикова Fiskars Solid (1066716)</strong> </span><span style="font-size:14px;">&mdash; ручний інструмент для виконання основних земляних робіт на присадибних ділянках і в господарських зонах. Використовується для перекопування ґрунту, підготовки посадкових лунок, формування грядок, траншей і зняття дерну.</span></p> <p data-end="425" data-start="266"><span style="font-size:18px;"><strong data-end="282" data-start="266">Призначення:</strong></span><span style="font-size:14px;"> підходить для обробки м&rsquo;якого та середньощільного ґрунту під час садово-городніх робіт, благоустрою територій і сезонного догляду за ділянкою.</span></p> <p data-end="641" data-start="427"><span style="font-size:18px;"><strong data-end="443" data-start="427">Конструкція:</strong></span><span style="font-size:14px;"> штикове полотно з прямим ріжучим краєм забезпечує контрольоване заглиблення в ґрунт. Держак стандартної довжини дозволяє працювати у стабільному вертикальному положенні без надмірного навантаження.</span></p> <p data-end="822" data-start="643"><span style="font-size:18px;"><strong data-end="657" data-start="643">Матеріали:</strong></span><span style="font-size:14px;"> робоча частина виготовлена зі сталі, стійкої до зношування при регулярному використанні. Держак розрахований на типові механічні навантаження під час ручної роботи.</span></p> <p data-end="987" data-is-last-node="" data-is-only-node="" data-start="824"><span style="font-size:18px;"><strong data-end="840" data-start="824">Особливості:</strong> </span><span style="font-size:14px;">інструмент належить до серії Solid бренду Fiskars та призначений для повсякденних земляних робіт у побутових умовах.</span></p> | AE56: Лопата штикова Fiskars Solid— ручний інструмент для виконання основних земляних робіт на присадибних ділянках і в господарських зонах. | AH56: 60 | AI56: 2026-01-19 15:25:31 | AM56: Новий | AN56: Нет | AO56: 8201 10 00 90 | AP56: 0 | AQ56: Выкл | AR56: Выкл | AU56: 6411501311832 | AW56: Нет | AX56: Нет
A57: 1014776 | B57: 1014776 | C57: 1014776 | D57: Лопата загострена Fiskars ClassicPro червона FSC (1014776) | E57: Лопата загострена Fiskars ClassicPro червона FSC (1014776) | F57: Fiskars | G57: FISKARS/Садовий інвентар Fiskars/Лопати садові | H57: 1600.00 | I57: 0.00 | J57: UAH | K57: Да | L57: =VLOOKUP(C57,Sheet1!$C:$L,10,0) -> Poland | M57: В наявності | O57: https://fiskars-gratis.com.ua/content/images/8/lopata-zahostrena-fiskars-classicpro-chervona-fsc-1014776-62107306863773_+98e9bf6697.jpeg; https://fiskars-gratis.com.ua/content/images/8/lopata-zahostrena-fiskars-classicpro-chervona-fsc-1014776-54242592592424_+40757a092e.jpeg | R57: lopata-zahostrena-fiskars-classicpro-chervona-fsc-1014776 | S57: https://fiskars-gratis.com.ua/lopata-zahostrena-fiskars-classicpro-chervona-fsc-1014776/ | T57: 2026-02-14 11:10:52 | X57: Лопата загострена Fiskars ClassicPro червона FSC | AA57: 0 | AB57: 0 | AC57: 4 | AD57: <p data-end="283" data-start="0"><span style="font-size:18px;"><strong data-end="62" data-start="0">Лопата загострена Fiskars ClassicPro червона FSC (1014776)</strong></span> <span style="font-size:14px;">&mdash;</span> <span style="font-size:14px;">ручний садово-будівельний інструмент для копання, розпушування та переміщення ґрунту. Використовується для земельних робіт на присадибних ділянках, у садівництві, благоустрої територій і допоміжних будівельних задачах.</span></p> <p data-end="461" data-start="285"><span style="font-size:18px;"><strong data-end="301" data-start="285">Призначення:</strong></span><span style="font-size:14px;"> підходить для роботи з твердим, ущільненим і дернистим ґрунтом, формування ям, траншей, підготовки посадкових місць, а також для переміщення сипких матеріалів.</span></p> <p data-end="653" data-start="463"><span style="font-size:18px;"><strong data-end="479" data-start="463">Конструкція:</strong></span><span style="font-size:14px;"> загострене лезо забезпечує ефективне входження в ґрунт. Пряма форма полотна дозволяє контролювати глибину та напрямок копання. Довгий держак оптимізований для роботи стоячи.</span></p> <p data-end="843" data-start="655"><span style="font-size:18px;"><strong data-end="669" data-start="655">Матеріали:</strong></span> <span style="font-size:14px;">робоча частина виготовлена зі сталі, стійкої до механічних навантажень. Дерев&rsquo;яний держак сертифікований за стандартом FSC, що підтверджує відповідальне походження деревини.</span></p> <p data-end="1011" data-is-last-node="" data-is-only-node="" data-start="845"><span style="font-size:18px;"><strong data-end="861" data-start="845">Особливості:</strong></span> <span style="font-size:14px;">лопата належить до професійної серії ClassicPro бренду Fiskars та призначена для регулярного інтенсивного використання.</span></p> | AE57: Лопата загострена Fiskars ClassicPro червона FSC — ручний садово-будівельний інструмент для копання, розпушування та переміщення ґрунту. | AH57: 60 | AI57: 2026-02-15 16:19:13 | AL57: Google Feed for Merchant Center; Facebook Feed | AM57: Новий | AN57: Нет | AO57: 8201 10 00 90 | AP57: 0 | AQ57: Выкл | AR57: Выкл | AU57: 6411501327635 | AW57: Нет | AX57: Нет
A58: 1067540 | B58: 1067540 | C58: 1067540 | D58: Лопата мала Fiskars White S (1067540) | E58: Лопата мала Fiskars White S (1067540) | F58: Fiskars | G58: FISKARS/Садовий інвентар Fiskars/Лопати садові | H58: 1749.00 | I58: 0.00 | J58: UAH | K58: Да | L58: =VLOOKUP(C58,Sheet1!$C:$L,10,0) -> Poland | M58: В наявності | O58: https://fiskars-gratis.com.ua/content/images/7/lopata-mala-fiskars-white-s-1067540-41347606308531_+4c043b7635.jpg; https://fiskars-gratis.com.ua/content/images/7/lopata-mala-fiskars-white-s-1067540-50594586793063_+60bccf61ce.jpg; https://fiskars-gratis.com.ua/content/images/7/lopata-mala-fiskars-white-s-1067540-11112499568728_+bb1ea3562d.jpg | R58: lopata-mala-fiskars-white-s-1067540 | S58: https://fiskars-gratis.com.ua/lopata-mala-fiskars-white-s-1067540/ | T58: 2026-02-14 11:10:52 | X58: Лопата мала Fiskars White S | AA58: 0 | AB58: 0 | AC58: 2 | AD58: <p data-end="284" data-start="0"><span style="font-size:18px;"><strong data-end="41" data-start="0">Лопата мала Fiskars White S (1067540)</strong> </span><span style="font-size:14px;">&mdash; компактний ручний інструмент для точкових земляних робіт і догляду за рослинами на присадибних ділянках. Використовується для висаджування розсади, роботи в обмеженому просторі, підсипання ґрунту, перекладання землі в клумбах і контейнерах.</span></p> <p data-end="438" data-start="286"><span style="font-size:18px;"><strong data-end="302" data-start="286">Призначення:</strong></span><span style="font-size:14px;"> підходить для садових і городніх робіт малої інтенсивності, догляду за квітниками, теплицями, балконними та декоративними насадженнями.</span></p> <p data-end="622" data-start="440"><span style="font-size:18px;"><strong data-end="456" data-start="440">Конструкція:</strong> </span><span style="font-size:14px;">зменшене полотно дозволяє точно дозувати об&rsquo;єм ґрунту та працювати поблизу кореневої системи рослин. Короткий держак забезпечує контроль рухів під час ручної роботи.</span></p> <p data-end="787" data-start="624"><span style="font-size:18px;"><strong data-end="638" data-start="624">Матеріали:</strong></span><span style="font-size:14px;"> робоча частина виготовлена зі сталі, стійкої до корозії та механічного зношування. Руків&rsquo;я адаптоване для регулярного використання в садових умовах.</span></p> <p data-end="939" data-is-last-node="" data-is-only-node="" data-start="789"><span style="font-size:18px;"><strong data-end="805" data-start="789">Особливості:</strong></span><span style="font-size:14px;"> інструмент належить до серії White бренду Fiskars та призначений для акуратних допоміжних робіт у саду.</span></p> | AE58: Лопата мала Fiskars White S — компактний ручний інструмент для точкових земляних робіт і догляду за рослинами на присадибних ділянках. | AH58: 60 | AI58: 2026-02-15 16:03:54 | AL58: Facebook Feed; Google Feed for Merchant Center | AM58: Новий | AN58: Нет | AO58: 8201 10 00 90 | AP58: 0 | AQ58: Выкл | AR58: Выкл | AU58: 6411501311481 | AW58: Нет | AX58: Нет
A59: 1014823 | B59: 1014823 | C59: 1014823 | D59: Лопата совкова FISKARS PARK FSC (1014823) | E59: Лопата совкова FISKARS PARK FSC (1014823) | F59: Fiskars | G59: FISKARS/Садовий інвентар Fiskars/Лопати садові | H59: 1860.00 | I59: 0.00 | J59: UAH | K59: Да | L59: =VLOOKUP(C59,Sheet1!$C:$L,10,0) -> Poland | M59: В наявності | O59: https://fiskars-gratis.com.ua/content/images/47/lopata-sovkova-fiskars-park-fsc-1014823-25032102955162_+d14f29a5a1.jpg | R59: lopata-sovkova-fiskars-park-fsc-1014823 | S59: https://fiskars-gratis.com.ua/lopata-sovkova-fiskars-park-fsc-1014823/ | T59: 2026-02-24 08:17:00 | X59: Лопата совкова FISKARS PARK FSC | AA59: 0 | AB59: 0 | AC59: 4 | AD59: <p data-end="350" data-start="0"><span style="font-size:18px;"><strong data-end="45" data-start="0">Лопата совкова Fiskars Park FSC (1014823)</strong></span><span style="font-size:14px;"> &mdash; ручний інструмент для роботи з сипкими і напівв&rsquo;язкими матеріалами на присадибних ділянках, у саду та господарських зонах. Використовується для підхоплення, перенесення й розподілу ґрунту, піску, щебеню, мульчі та інших сипучих матеріалів під час посадки, облаштування ґрунту або благоустрою території.</span></p> <p data-end="588" data-start="352"><span style="font-size:18px;"><strong data-end="368" data-start="352">Призначення:</strong></span><span style="font-size:14px;"> підходить для приготування ґрунту перед посадкою рослин, заповнення грядок і клумб, переміщення сипучих будівельних матеріалів і догляду за садовими зонами, де потрібне контрольоване піднімання та переміщення матеріалу.</span></p> <p data-end="807" data-start="590"><span style="font-size:18px;"><strong data-end="606" data-start="590">Конструкція:</strong> </span><span style="font-size:14px;">широке совкове полотно забезпечує велику місткість захоплення матеріалу за один хід. Руків&rsquo;я стандартної довжини дозволяє працювати у вертикальному положенні з комфортом і контролем над навантаженням.</span></p> <p data-end="1087" data-start="809"><span style="font-size:18px;"><strong data-end="823" data-start="809">Матеріали:</strong></span><span style="font-size:14px;"> робоча частина виготовлена з міцних матеріалів, стійких до механічного зношування при регулярному використанні. Руків&rsquo;я виконане з сертифікованої деревини FSC, що підтверджує відповідальне управління лісовими ресурсами і забезпечує надійний захват під час роботи.</span></p> <p data-end="1302" data-is-last-node="" data-is-only-node="" data-start="1089"><span style="font-size:18px;"><strong data-end="1105" data-start="1089">Особливості:</strong> </span><span style="font-size:14px;">інструмент належить до серії Park бренду Fiskars та призначений для широкого спектра ручних робіт із перенесення та розподілу сипких матеріалів у саду і господарстві.</span></p> | AE59: Лопата совкова Fiskars Park FSC — ручний інструмент для роботи з сипкими і напівв’язкими матеріалами на присадибних ділянках, у саду та господарських зонах. | AH59: 60 | AI59: 2026-02-24 08:24:17 | AL59: Facebook Feed; Google Feed for Merchant Center | AM59: Новий | AN59: Нет | AO59: 8201 10 00 90 | AP59: 0 | AQ59: Выкл | AR59: Выкл | AU59: 6411501663320 | AW59: Нет | AX59: Нет
A60: 1014773 | B60: 1014773 | C60: 1014773 | D60: Лопата садова штикова Fiskars Classic FSC (1014773) | E60: Лопата садова штикова Fiskars Classic FSC (1014773) | F60: Fiskars | G60: FISKARS/Садовий інвентар Fiskars/Лопати садові | H60: 2000.00 | I60: 0.00 | J60: UAH | K60: Да | L60: =VLOOKUP(C60,Sheet1!$C:$L,10,0) -> Norway | M60: Немає в наявності | O60: https://fiskars-gratis.com.ua/content/images/48/lopata-sadova-shtykova-fiskars-classic-fsc-1014773-68987635325854_+259fdc7151.jpg | R60: lopata-sadova-shtykova-fiskars-classic-fsc-1014773 | S60: https://fiskars-gratis.com.ua/lopata-sadova-shtykova-fiskars-classic-fsc-1014773/ | T60: 2026-02-24 08:17:00 | X60: Лопата садова штикова Fiskars Classic FSC | Z60: Хіт | AA60: 0 | AB60: 0 | AC60: 0 | AD60: <p data-end="336" data-start="0"><span style="font-size:18px;"><strong data-end="55" data-start="0">Лопата садова штикова Fiskars Classic FSC (1014773)</strong></span><span style="font-size:14px;"> &mdash; ручний інструмент для виконання основних земляних робіт на присадибних ділянках, у садах і господарських зонах. Використовується для перекопування ґрунту, формування грядок і траншей, підготовки посадкових ям, зняття дерну та інших задач, що потребують заглиблення леза у землю.</span></p> <p data-end="528" data-start="338"><span style="font-size:18px;"><strong data-end="354" data-start="338">Призначення:</strong></span><span style="font-size:14px;"> підходить для обробки м&rsquo;якого та середньощільного ґрунту під час сезонних і повсякденних садово-городніх робіт, підготовки ділянки до посадки рослин та планування ландшафту.</span></p> <p data-end="842" data-start="530"><span style="font-size:18px;"><strong data-end="546" data-start="530">Конструкція:</strong> </span><span style="font-size:14px;">штикове полотно з прямим ріжучим краєм забезпечує ефективне проникнення в ґрунт і контрольований зріз дерну. Руків&rsquo;я оптимальної довжини дозволяє працювати у вертикальному положенні з мінімальним навантаженням на спину. Збалансована форма інструмента сприяє контролю рухів під час ручної роботи.</span></p> <p data-end="1126" data-start="844"><span style="font-size:18px;"><strong data-end="858" data-start="844">Матеріали:</strong></span><span style="font-size:14px;"> робоча частина виготовлена зі сталі, що витримує механічні навантаження і зношування при регулярному використанні. Руків&rsquo;я виконане з сертифікованої деревини FSC, що підтверджує відповідальне управління лісовими ресурсами, і забезпечує надійний захват під час роботи.</span></p> <p data-end="1308" data-is-last-node="" data-is-only-node="" data-start="1128"><span style="font-size:18px;"><strong data-end="1144" data-start="1128">Особливості:</strong></span><span style="font-size:14px;"> інструмент належить до серії Classic бренду Fiskars та призначений для систематичних земляних робіт у садових і господарських умовах.</span></p> | AE60: Лопата садова штикова Fiskars Classic FSC — ручний інструмент для виконання основних земляних робіт на присадибних ділянках, у садах і господарських зонах. | AH60: 60 | AI60: 2026-02-24 08:24:57 | AL60: Facebook Feed; Google Feed for Merchant Center | AM60: Новий | AN60: Нет | AO60: 8201 10 00 90 | AP60: 0 | AQ60: Выкл | AR60: Выкл | AU60: 6411501317407 | AW60: Нет | AX60: Нет
A61: 1005016 | B61: 1005016 | C61: 1005016 | D61: Лопата совкова будівельна Fiskars (1005016) | E61: Лопата совкова будівельна Fiskars (1005016) | F61: Fiskars | G61: FISKARS/Садовий інвентар Fiskars/Лопати садові | H61: 2300.00 | I61: 0.00 | J61: UAH | K61: Да | L61: =VLOOKUP(C61,Sheet1!$C:$L,10,0) -> Poland | M61: В наявності | O61: https://fiskars-gratis.com.ua/content/images/9/lopata-sovkova-budivelna-fiskars-1005016-69407303738447_+40a2392cd0.jpg | R61: lopata-sovkova-budivelna-fiskars-1005016 | S61: https://fiskars-gratis.com.ua/lopata-sovkova-budivelna-fiskars-1005016/ | T61: 2026-02-14 11:10:52 | X61: Лопата совкова будівельна Fiskars | AA61: 0 | AB61: 0 | AC61: 4 | AD61: <p data-end="287" data-start="0"><span style="font-size:18px;"><strong data-end="47" data-start="0">Лопата совкова будівельна Fiskars (1005016)</strong> </span><span style="font-size:14px;">&mdash; ручний інструмент для виконання будівельних і господарських робіт із сипкими та напівв&rsquo;язкими матеріалами. Використовується для підхоплення, перенесення та розподілу піску, щебеню, ґрунту, цементно-піщаних сумішей і будівельних розчинів.</span></p> <p data-end="464" data-start="289"><span style="font-size:18px;"><strong data-end="305" data-start="289">Призначення:</strong></span><span style="font-size:14px;"> підходить для підготовчих і ремонтних робіт, приготування та переміщення розчинів, навантаження матеріалів на будівельних майданчиках і в господарських зонах.</span></p> <p data-end="699" data-start="466"><span style="font-size:18px;"><strong data-end="482" data-start="466">Конструкція:</strong></span><span style="font-size:14px;"> совкове полотно з підвищеною місткістю утримує матеріал під час перенесення та зменшує втрати. Форма леза оптимізована для роботи з сипкими масами. Держак стандартної довжини забезпечує контроль і стабільність рухів.</span></p> <p data-end="866" data-start="701"><span style="font-size:18px;"><strong data-end="715" data-start="701">Матеріали:</strong></span><span style="font-size:14px;"> робоча частина виготовлена зі сталі, стійкої до абразивного зношування та механічних навантажень. Держак розрахований на регулярну ручну експлуатацію.</span></p> <p data-end="1020" data-is-last-node="" data-is-only-node="" data-start="868"><span style="font-size:18px;"><strong data-end="884" data-start="868">Особливості:</strong></span><span style="font-size:14px;"> інструмент вироблений брендом Fiskars та призначений для систематичних будівельних і господарських задач.</span></p> | AE61: Лопата совкова будівельна Fiskars — ручний інструмент для виконання будівельних і господарських робіт із сипкими та напівв’язкими матеріалами. | AH61: 60 | AI61: 2026-02-16 18:46:04 | AL61: Facebook Feed; Google Feed for Merchant Center | AM61: Новий | AN61: Нет | AO61: 8201 10 00 90 | AP61: 0 | AQ61: Выкл | AR61: Выкл | AU61: 6411501328007 | AW61: Нет | AX61: Нет
A62: 1024472 | B62: 1024472 | C62: 1024472 | D62: Лопата садова класична Fiskars FSC (1024472) | E62: Лопата садова класична Fiskars FSC (1024472) | F62: Fiskars | G62: FISKARS/Садовий інвентар Fiskars/Лопати садові | H62: 899.00 | I62: 1600.00 | J62: UAH | K62: Да | L62: =VLOOKUP(C62,Sheet1!$C:$L,10,0) -> Norway | M62: В наявності | O62: https://fiskars-gratis.com.ua/content/images/49/lopata-sadova-klasychna-fiskars-fsc-1024472-57800540377835_+bcbde5a5fc.jpeg | R62: lopata-sadova-klasychna-fiskars-fsc-1024472 | S62: https://fiskars-gratis.com.ua/lopata-sadova-klasychna-fiskars-fsc-1024472/ | T62: 2026-02-24 08:17:00 | X62: Лопата садова класична Fiskars FSC | Z62: Хіт | AA62: 0 | AB62: 0 | AC62: 2 | AD62: <p data-end="280" data-start="0"><span style="font-size:18px;"><strong data-end="48" data-start="0">Лопата садова класична Fiskars FSC (1024472)</strong></span><span style="font-size:14px;"> &mdash; ручний інструмент для базових земляних робіт на присадибних ділянках, у городі та господарських зонах. Використовується для копання, перекопування ґрунту, формування грядок, траншей, підготовки посадкових ям і планування ділянки.</span></p> <p data-end="488" data-start="282"><span style="font-size:18px;"><strong data-end="298" data-start="282">Призначення:</strong></span><span style="font-size:14px;"> підходить для обробки м&rsquo;якого та середньощільного ґрунту під час сезонних і щоденних садово-городніх робіт, включно з підготовкою ділянки до посадки рослин або пересадки дерев і чагарників.</span></p> <p data-end="803" data-start="490"><span style="font-size:18px;"><strong data-end="506" data-start="490">Конструкція:</strong> </span><span style="font-size:14px;">традиційне штикове або класичне лезо забезпечує ефективне проникнення в ґрунт і контрольований зріз землі. Руків&rsquo;я оптимальної довжини дозволяє працювати у вертикальному положенні з комфортним розподілом зусиль, а форма держака сприяє стабільному контролю інструмента під час ручної експлуатації.</span></p> <p data-end="1082" data-start="805"><span style="font-size:18px;"><strong data-end="819" data-start="805">Матеріали:</strong> </span><span style="font-size:14px;">робоча частина виготовлена з міцної сталі, стійкої до деформації й зношування при регулярних навантаженнях. Руків&rsquo;я виконано з сертифікованої деревини FSC, що підтверджує відповідальне використання природних ресурсів, і забезпечує надійний захват під час роботи.</span></p> <p data-end="1300" data-is-last-node="" data-is-only-node="" data-start="1084"><span style="font-size:18px;"><strong data-end="1100" data-start="1084">Особливості:</strong></span><span style="font-size:14px;"> інструмент належить до серії класичних садових інструментів бренду Fiskars та призначений для широкого спектра ручних земляних робіт у саду, на городі та в господарстві.</span></p> | AE62: Лопата садова класична Fiskars FSC — ручний інструмент для базових земляних робіт на присадибних ділянках, у городі та господарських зонах | AH62: 60 | AI62: 2026-02-24 08:29:02 | AL62: Facebook Feed; Google Feed for Merchant Center | AM62: Новий | AN62: Нет | AO62: 8201 10 00 90 | AP62: 0 | AQ62: Выкл | AR62: Выкл | AU62: 6411501317506 | AW62: Нет | AX62: Нет
